Workbook

Sheet MASTER
A1: DASHBOARD CONSOLIDADO - GRUPO DELGA 2026
A2: Atualizado: | B2: 13/01/2026 | D2: Semana:
A4: VISÃO GERAL - BIG NUMBERS
A5: META ANUAL | C5: REALIZADO YTD | E5: % ATINGIMENTO | G5: GAP | I5: PROJETOS ATIVOS | K5: KAIZENS
A6: R$ 50,32 Mi | C6: R$ 0 | E6: 0% | G6: R$ 50,32 Mi | I6: 0 | K6: 0
A8: SAVING POR FONTE
A9: FONTE | B9: META | C9: REALIZADO | D9: % ATING. | E9: GAP | F9: STATUS
A10: Diadema | B10: 6947000 | C10: 0 | D10: =IF(B10=0,0,C10/B10) -> 0 | E10: =B10-C10 -> 6947000
A11: Ferraz | B11: 13367000 | C11: 0 | D11: =IF(B11=0,0,C11/B11) -> 0 | E11: =B11-C11 -> 13367000
A12: São Leopoldo | B12: 2100000 | C12: 0 | D12: =IF(B12=0,0,C12/B12) -> 0 | E12: =B12-C12 -> 2100000
A13: Jarinu | B13: 5356000 | C13: 0 | D13: =IF(B13=0,0,C13/B13) -> 0 | E13: =B13-C13 -> 5356000
A14: Anchieta | B14: 3841000 | C14: 0 | D14: =IF(B14=0,0,C14/B14) -> 0 | E14: =B14-C14 -> 3841000
A15: Compras | B15: 7000000 | C15: 0 | D15: =IF(B15=0,0,C15/B15) -> 0 | E15: =B15-C15 -> 7000000
A16: Vendas | B16: 10000000 | C16: 0 | D16: =IF(B16=0,0,C16/B16) -> 0 | E16: =B16-C16 -> 10000000
A17: Corporativo | B17: 1709000
A18: TOTAL | B18: =SUM(B10:B16) -> 48611000 | C18: =SUM(C10:C16) -> 0 | D18: =IF(B18=0,0,C18/B18) -> 0 | E18: =B18-C18 -> 48611000
A20: KPIs OPERACIONAIS - COMPARATIVO UNIDADES
A21: KPI | B21: META | C21: DIADEMA | D21: FERRAZ | E21: SÃO LEOPOLDO | F21: JARINU | G21: ANCHIETA | H21: MÉDIA | I21: STATUS
H22: =AVERAGE(C22:G22) -> #DIV/0!
H23: =AVERAGE(C23:G23) -> #DIV/0!
H24: =AVERAGE(C24:G24) -> #DIV/0!
H25: =AVERAGE(C25:G25) -> #DIV/0!
H26: =AVERAGE(C26:G26) -> #DIV/0!
H27: =AVERAGE(C27:G27) -> #DIV/0!
H28: =AVERAGE(C28:G28) -> #DIV/0!
H29: =AVERAGE(C29:G29) -> #DIV/0!
H30: =AVERAGE(C30:G30) -> #DIV/0!
H31: =AVERAGE(C31:G31) -> #DIV/0!
H32: =AVERAGE(C32:G32) -> #DIV/0!
H33: =AVERAGE(C33:G33) -> #DIV/0!
... H37: =AVERAGE(C37:G37) -> #DIV/0!
A40: DESTAQUES DA SEMANA | H40: RISCOS E AÇÕES
A41: 1. | H41: 1.
A42: 2. | H42: 2.
A43: 3. | H43: 3.
A44: 4. | H44: 4.
A45: 5. | H45: 5.

Sheet 5 Unidades  +
D3: DASHBOARD EXECUTIVO - GRUPO DELGA
D4: Gestão Estratégica de Projetos e Redução de Custos | Grupo Delga | 2026
D6: META DO GRUPO 2026 | E6: RETORNO PREVISTO (Anual) | F6: Retorno Validado (Anual) | G6: PREVISTO 2026 | H6: 💰 RETORNO VALIDADO 2026 | J6: 💰 RETORNO REAL 2026 | K6: Extra DRE (Até o momento) | L6: % ATINGIMENTO DA META | N6: INICIATIVAS | P6: Top 03 Projetos (Maior Retorno REAL até o momento) | V6: Kaizen - Capital de Giro | W6: redução de estoque, melhora o caixa mas não o DRE de forma tangível
D7: =Diadema!A5+Ferraz!A5+'São Leopoldo'!A5+Jarinu!A5+Anchieta!A5+Corporativo!A5+'Compras '!A5+Vendas!A5+'Diretoria Financeira'!A5+'Head Qualidade&Dir. Industrial'!A5 -> 50320000 | E7: =Diadema!B5+Jarinu!B5+Ferraz!B5+Anchieta!B5+'São Leopoldo'!B5+'Compras '!C5+Vendas!C5+Corporativo!C5 -> 54030314 | F7: =Diadema!C5+Jarinu!C5+Ferraz!C5+Anchieta!C5+'São Leopoldo'!C5+'Compras '!D5 -> 24988665 | G7: =Diadema!D5+Jarinu!D5+Ferraz!D5+Anchieta!D5+'São Leopoldo'!D5+'Compras '!E5+Vendas!E5 -> 33811407 | H7: =Diadema!E5+Jarinu!E5+Ferraz!E5+Anchieta!E5+'São Leopoldo'!E5+'Compras '!G5+Vendas!G5 -> 15697315 | J7: =Diadema!G5+Ferraz!G5+Jarinu!G5+'São Leopoldo'!G5+Anchieta!G5+'Compras '!I5+Vendas!I5+Corporativo!G5 -> 5623569.8 | K7: =Diadema!I5+Ferraz!I5+Jarinu!I5+'São Leopoldo'!I5+Anchieta!I5+Vendas!I7 -> 3579261.8 | L7: =J7/D7 -> 0.11175616 | N7: =E21 -> 216 | P7: =K56 -> 1546534.7 | Q7: =F56 -> Negociação de preços materiais carcaça Dana | S7: =E56 -> Compras | V7: Kaizen - Ganho Recorrente | W7: impacto direto e tangível no DRE
P8: =J57 -> 520985.23 | Q8: =F57 -> 07- Reestruturação | S8: =E57 -> São leopoldo | V8: Kaizen - Custo Evitado | W8: Ganho real, mas não reflete diretamente como redução no DRE
P9: =K58 -> 412708.21 | Q9: =F58 -> Projeto DANA - Mudança de CH para BQ | S9: =E58 -> Compras
D11: 📊 SAVING ESPECULADO POR PILAR | I11: 📋 STATUS DAS INICIATIVAS | L11: 🏭 INDICADORES OPERACIONAIS | P11: MATRIZ SPD 5 unidades
D12: Pilar | E12: Qtd. | F12: Saving (R$) | G12: Saving Validado 2026 | H12: Até o Momento | I12: Status | J12: Qtd. | K12: R$ Previsto | L12: Aderência SPD: Unidade | M12: Aderência SPD: Auditado | N12: Análise de Margem | P12: Tipo | Q12: Unidade | R12: Auditado | S12: Meta
D13: Kaizen - Capital de Giro | E13: =Diadema!B8+Ferraz!B8+Jarinu!B8+'São Leopoldo'!B8+Anchieta!B8 -> 1 | F13: =Diadema!C8+Ferraz!C8+Jarinu!C8+'São Leopoldo'!C8+Anchieta!C8 -> 195011 | G13: =Diadema!D8+Ferraz!D8+Jarinu!D8+'São Leopoldo'!D8+Anchieta!D8 -> 0 | H13: =Diadema!E8+Ferraz!E8+Jarinu!E8+'São Leopoldo'!E8+Anchieta!E8 -> 195000 | I13: ✓ Concluído | J13: =Diadema!G8+Ferraz!G8+Jarinu!G8+'São Leopoldo'!G8+Anchieta!G8+'Compras '!H9+Vendas!M11+Vendas!P11 -> 107 | K13: =SUM(Diadema!H8,Ferraz!H8,'São Leopoldo'!H8,Jarinu!H8,Anchieta!H8,Corporativo!I9,'Compras '!I9,Vendas!N11,'Diretoria Financeira'!I9,'Head Qualidade&Dir. Industrial'!I9) -> 19638792 | P13: Produtividade e Controle | Q13: =SUM(Diadema!L219,Anchieta!L132,Ferraz!L174,Jarinu!L174,'São Leopoldo'!L134)/5 -> 0.95 | R13: =SUM(Diadema!M219,Anchieta!M132,Ferraz!M174,Jarinu!M174,'São Leopoldo'!M134)/5 -> 0.9 | S13: 1
D14: Kaizen - Ganho Recorrente | E14: =Diadema!B9+Ferraz!B9+Jarinu!B9+'São Leopoldo'!B9+Anchieta!B9 -> 30 | F14: =Diadema!C9+Ferraz!C9+Jarinu!C9+'São Leopoldo'!C9+Anchieta!C9 -> 3114920.1 | G14: =Diadema!D9+Ferraz!D9+Jarinu!D9+'São Leopoldo'!D9+Anchieta!D9 -> 2409427.6 | H14: =Diadema!E9+Ferraz!E9+Jarinu!E9+'São Leopoldo'!E9+Anchieta!E9 -> 1266744.9 | I14: ⏳ Em Execução | J14: =SUM(Diadema!G9,Ferraz!G9,'São Leopoldo'!G9,Jarinu!G9,Anchieta!G9,Corporativo!H10,'Compras '!H10,Vendas!M12,'Diretoria Financeira'!H10,'Head Qualidade&Dir. Industrial'!H10,Vendas!P12) -> 82 | K14: =SUM(Diadema!H9,Ferraz!H9,'São Leopoldo'!H9,Jarinu!H9,Anchieta!H9,Corporativo!I10,'Compras '!I10,Vendas!N12,'Diretoria Financeira'!I10,'Head Qualidade&Dir. Industrial'!I10) -> 18061986 | L14: =AVERAGE(Diadema!I9,Ferraz!I9,'São Leopoldo'!I9:I10,Jarinu!I9,Anchieta!I9) -> 0.98333333 | M14: =AVERAGE(Diadema!J9,Ferraz!J9,'São Leopoldo'!J9:J10,Jarinu!J9,Anchieta!J9) -> 0.94166667 | N14: =AVERAGE(Diadema!K9,Ferraz!K9,'São Leopoldo'!K9,Jarinu!K9,Anchieta!K9) -> 0.26601787 | P14: Documentos e Registro | Q14: =SUM(Diadema!L220,Anchieta!L133,Ferraz!L175,Jarinu!L175,'São Leopoldo'!L135)/5 -> 0.95 | R14: =SUM(Diadema!M220,Anchieta!M133,Ferraz!M175,Jarinu!M175,'São Leopoldo'!M135)/5 -> 0.85 | S14: 1
D15: Kaizen - Custo Evitado | E15: =Diadema!B10+Ferraz!B10+Jarinu!B10+'São Leopoldo'!B10+Anchieta!B10 -> 21 | F15: =Diadema!C10+Ferraz!C10+Jarinu!C10+'São Leopoldo'!C10+Anchieta!C10 -> 6718186.2 | G15: =Diadema!D10+Ferraz!D10+Jarinu!D10+'São Leopoldo'!D10+Anchieta!D10 -> 0 | H15: =Diadema!E10+Ferraz!E10+Jarinu!E10+'São Leopoldo'!E10+Anchieta!E10 -> 3373042 | I15: 📝 Não iniciado | J15: =SUM(Diadema!G10,Ferraz!G10,'São Leopoldo'!G10,Jarinu!G10,Anchieta!G10,Corporativo!H11,'Compras '!H11,Vendas!M13,'Diretoria Financeira'!H11,'Head Qualidade&Dir. Industrial'!H11,Vendas!P13) -> 17 | K15: =SUM(Diadema!H10,Ferraz!H10,'São Leopoldo'!H10,Jarinu!H10,Anchieta!H10,Corporativo!I11,'Compras '!I11,Vendas!N13,'Diretoria Financeira'!I11,'Head Qualidade&Dir. Industrial'!I11) -> 1397973 | P15: Manutenção do Processo | Q15: =SUM(Diadema!L221,Anchieta!L134,Ferraz!L176,Jarinu!L176,'São Leopoldo'!L136)/5 -> 0.98333333 | R15: =SUM(Diadema!M221,Anchieta!M134,Ferraz!M176,Jarinu!M176,'São Leopoldo'!M136)/5 -> 0.96666667 | S15: 1
D16: Kaizen | E16: =Ferraz!B11+Jarinu!B11+'São Leopoldo'!B11+Anchieta!B11+'Compras '!B9+Vendas!B11+Corporativo!B9 -> 21 | F16: =Ferraz!C11+Jarinu!C11+'São Leopoldo'!C11+Anchieta!C11+'Compras '!C9+Vendas!C11 -> 3087374.2 | G16: =Ferraz!D11+Jarinu!D11+'São Leopoldo'!D11+Anchieta!D11+'Compras '!D9 -> 2082433.4 | H16: =Ferraz!E11+Jarinu!E11+'São Leopoldo'!E11+Anchieta!E11+'Compras '!E9+Vendas!E11 -> 970520.54 | P16: Análise dos Dados | Q16: =SUM(Diadema!L222,Anchieta!L135,Ferraz!L177,Jarinu!L177,'São Leopoldo'!L137)/5 -> 1 | R16: =SUM(Diadema!M222,Anchieta!M135,Ferraz!M177,Jarinu!M177,'São Leopoldo'!M137)/5 -> 1 | S16: 1
D17: Redução de Custo | E17: =Diadema!B11+Ferraz!B12+Jarinu!B12+'São Leopoldo'!B12+Anchieta!B12+'Compras '!B10+Vendas!B12+Corporativo!B10 -> 85 | F17: =Diadema!C11+Ferraz!C12+Jarinu!C12+'São Leopoldo'!C12+Anchieta!C12+'Compras '!C10+Vendas!C12 -> 23699907 | G17: =Diadema!D11+Ferraz!D12+Jarinu!D12+'São Leopoldo'!D12+Anchieta!D12+'Compras '!D10+Vendas!D12+Corporativo!D10 -> 6769731.5 | H17: =Diadema!E11+Ferraz!E12+Jarinu!E12+'São Leopoldo'!E12+Anchieta!E12+'Compras '!E10+Vendas!E12 -> 2600128.3
D18: Você Resolve | E18: =Diadema!B12+Ferraz!B13+Jarinu!B13+'São Leopoldo'!B13+Anchieta!B13+'Compras '!B12+Vendas!B13+Corporativo!B11 -> 1 | F18: =Diadema!C12+Ferraz!C13+Jarinu!C13+'São Leopoldo'!C13+Anchieta!C13+'Compras '!C11+Vendas!C13 -> 1000000 | G18: =Diadema!D12+Ferraz!D13+Jarinu!D13+'São Leopoldo'!D13+Anchieta!D13+'Compras '!D11+Vendas!D13 -> 240000 | H18: =Diadema!E12+Ferraz!E13+Jarinu!E13+'São Leopoldo'!E13+Anchieta!E13+'Compras '!E11+Vendas!E13 -> 0
D19: BSW | E19: =Diadema!B13+Ferraz!B14+Jarinu!B14+'São Leopoldo'!B14+Anchieta!B14+'Compras '!B12+Vendas!B14+Corporativo!B12 -> 57 | F19: =Diadema!C13+Ferraz!C14+Jarinu!C14+'São Leopoldo'!C14+Anchieta!C14+'Compras '!C12+Vendas!C14 -> 6558514.2 | G19: =Diadema!D13+Ferraz!D14+Jarinu!D14+'São Leopoldo'!D14+Anchieta!D14+'Compras '!D13 -> 4414449.3 | H19: =Diadema!E13+Ferraz!E14+Jarinu!E14+'São Leopoldo'!E14+Anchieta!E14+'Compras '!E12+Vendas!E14 -> 774956.23
D20: Estratégia Comercial | E20: =Vendas!B15 -> 1 | F20: =Vendas!C15 -> 9996000 | G20: =Vendas!D15 -> 0 | H20: =Vendas!E15 -> 0
D21: TOTAL | E21: =SUM(E13:E19) -> 216 | F21: =SUM(F13:F20) -> 54369913 | G21: =SUM(G13:G20) -> 15916042 | H21: =SUM(H13:H20) -> 9180392.1
D22: - | E22: Diadema | F22: Ferraz | G22: São Leopoldo | H22: Jarinu | I22: Anchieta | J22: Corporativo | K22: Compras | L22: Vendas
D23: META DA UNIDADE | E23: =Diadema!A5 -> 6947000 | F23: =Ferraz!A5 -> 13367000 | G23: ='São Leopoldo'!A5 -> 2100000 | H23: =Jarinu!A5 -> 5356000 | I23: =Anchieta!A5 -> 3841000 | J23: =Corporativo!A5 -> 1709000 | K23: ='Compras '!A5 -> 7000000 | L23: =Vendas!A5 -> 10000000 | M23: VA | N23: =Diadema!G15+Jarinu!G15+Ferraz!G15+'São Leopoldo'!G15+Anchieta!G15+'Compras '!P17 -> 8370195.8
D24: RETORNO PREVISTO | E24: =Diadema!C5 -> 4424279.6 | F24: =Ferraz!B5 -> 13813000 | G24: ='São Leopoldo'!B5 -> 2230520.7 | H24: =Jarinu!B5 -> 5582548 | I24: =Anchieta!B5 -> 1612623.6 | J24: =Corporativo!C5 -> 0 | K24: ='Compras '!C5 -> 15589000 | L24: =Vendas!C5 -> 10541563 | M24: GGF | N24: =Diadema!G16+Jarinu!G16+Ferraz!G16+'São Leopoldo'!G16+Anchieta!G16+'Compras '!P18 -> 4317459.2
D25: PREVISTO (Concluido) | E25: =Diadema!H8 -> 3446352.2 | F25: =Ferraz!H8 -> 3632600 | G25: ='São Leopoldo'!H8 -> 1422892.8 | H25: =Jarinu!H8 -> 1395112 | I25: =Anchieta!H8 -> 212144 | J25: =Corporativo!I9 -> 0 | K25: ='Compras '!I9 -> 9529691.1 | L25: =Vendas!N11 -> 0 | M25: MA | N25: =Diadema!G17+Jarinu!G17+Ferraz!G17+'São Leopoldo'!G17+Anchieta!G17+'Compras '!P19 -> 2303528.2
D26: 💰 RETORNO VALIDADO | E26: =Diadema!E5 -> 2877285.2 | F26: =Ferraz!E5 -> 2448486.8 | G26: ='São Leopoldo'!E5 -> 2196413.4 | H26: =Jarinu!E5 -> 2945612.6 | I26: =Anchieta!E5 -> 464467.83 | J26: =Corporativo!E5 -> 0 | K26: ='Compras '!G5 -> 4765049.3 | L26: =Vendas!G5 -> 0 | M26: Outros | N26: =Diadema!G18+Jarinu!G18+Ferraz!G18+'São Leopoldo'!G18+Anchieta!G18+'Compras '!P20 -> 706132
D27: 💰 RETORNO REAL | E27: =Diadema!G5 -> 1008796 | F27: =Ferraz!G5 -> 1367465.6 | G27: ='São Leopoldo'!G5 -> 1158700.7 | H27: =Jarinu!G5 -> 463507.45 | I27: =Anchieta!G5 -> 331443.95 | J27: =Corporativo!G5 -> 0 | K27: ='Compras '!I5 -> 1282436.3 | L27: =Vendas!G5 -> 0
D28: % ATINGIMENTO DA META | E28: =Diadema!J5 -> 0.14521318 | F28: =Ferraz!J5 -> 0.10230161 | G28: ='São Leopoldo'!J5 -> 0.55176223 | H28: =Jarinu!J5 -> 0.086539852 | I28: =Anchieta!J5 -> 0.086291056 | J28: =Corporativo!J5 -> 0 | K28: ='Compras '!L5 -> 0.18320519 | L28: =Vendas!J5 -> 0
D29: Extra DRE | E29: =Diadema!I5 -> 137181.16 | F29: =Ferraz!I5 -> 2135000 | G29: ='São Leopoldo'!I5 -> 120860.88 | H29: =Jarinu!I5 -> 1009000 | I29: =Anchieta!I5 -> 166000 | J29: =Diadema!N5 -> 0 | L29: =Vendas!E7 -> 137632.63
D30: INICIATIVAS | E30: =Diadema!L5 -> 57 | F30: =Ferraz!L5 -> 21 | G30: ='São Leopoldo'!L5 -> 18 | H30: =Jarinu!L5 -> 37 | I30: =Anchieta!L5 -> 16 | J30: =Corporativo!M5 -> 0 | K30: ='Compras '!O5 -> 50 | L30: =Vendas!M5 -> 0
D31: Status SPD: Unidade | E31: =Diadema!I9 -> 1 | F31: =Ferraz!I9 -> 1 | G31: ='São Leopoldo'!I9 -> 1 | H31: =Jarinu!I9 -> 0.91666667 | I31: =Anchieta!I9 -> 1
D32: Status SPD: Auditado | E32: =Diadema!J9 -> 0.91666667 | F32: =Ferraz!J9 -> 0.95833333 | G32: ='São Leopoldo'!J9 -> 0.95833333 | H32: =Jarinu!J9 -> 0.91666667 | I32: =Anchieta!J9 -> 0.95833333
D33: Análise de Margem | E33: =N14 -> 0.26601787 | F33: =Ferraz!K9 -> 0.20833333 | G33: ='São Leopoldo'!K9 -> 0.1025641 | H33: =Jarinu!K9 -> 0.43333333 | I33: =Anchieta!K9 -> 0.33333333
F54: ,
D55: Posição | E55: Unidade / Departamento | F55: Nome do projeto /Inicio do Saving | H55: Status | I55: Status de Custos | J55: Previsto em 2026 | K55: Valor Previsto até o Momento | L55: Valor Real até o Momento | M55: Delta | W55: 46023 | X55: 46054 | Y55: 46082 | Z55: 46113 | AA55: 46143 | AB55: 46174 | AC55: 46204 | AD55: 46235 | AE55: 46266 | AF55: 46296 | AG55: 46327 | AH55: 46357 | AI55: total
D56: 1 | E56: =_xlfn.XLOOKUP(F56,Pareto!S:S,Pareto!T:T) -> Compras | F56: =_xlfn.XLOOKUP(K56,Pareto!V:V,Pareto!S:S) -> Negociação de preços materiais carcaça Dana | H56: =_xlfn.XLOOKUP(F56,Pareto!S:S,Pareto!X:X) -> ✓ Concluído | I56: =_xlfn.XLOOKUP('5 Unidades +'!F56,Pareto!S:S,Pareto!Z:Z) -> OK | J56: =_xlfn.XLOOKUP(F56,Pareto!S:S,Pareto!U:U) -> 2651202.3 | K56: =IFERROR(LARGE(Pareto!V:V,'5 Unidades +'!D56),"0") -> 1546534.7 | L56: =_xlfn.XLOOKUP(F56,Pareto!S:S,Pareto!W:W) -> 1154706.2 | M56: =IF(L56="",-K56,L56-K56) -> -391828.45 | V56: Previsto | W56: =SUM(Diadema!T179,Ferraz!S147,'São Leopoldo'!S109,Jarinu!S147,Anchieta!S105,Corporativo!L75,'Compras '!P147,Vendas!L86,'Diretoria Financeira'!L71,'Head Qualidade&Dir. Industrial'!L71) -> 1727858.4 | X56: =SUM(Diadema!U179,Ferraz!T147,'São Leopoldo'!T109,Jarinu!T147,Anchieta!T105,Corporativo!M75,'Compras '!Q147,Vendas!M86,'Diretoria Financeira'!M71,'Head Qualidade&Dir. Industrial'!M71) -> 1401255.9 | Y56: =SUM(Diadema!V179,Ferraz!U147,'São Leopoldo'!U109,Jarinu!U147,Anchieta!U105,Corporativo!N75,'Compras '!R147,Vendas!N86,'Diretoria Financeira'!N71,'Head Qualidade&Dir. Industrial'!N71) -> 1847170.5 | Z56: =SUM(Diadema!W179,Ferraz!V147,'São Leopoldo'!V109,Jarinu!V147,Anchieta!V105,Corporativo!O75,'Compras '!S147,Vendas!O86,'Diretoria Financeira'!O71,'Head Qualidade&Dir. Industrial'!O71) -> 1930171.6 | AA56: =SUM(Diadema!X179,Ferraz!W147,'São Leopoldo'!W109,Jarinu!W147,Anchieta!W105,Corporativo!P75,'Compras '!T147,Vendas!P86,'Diretoria Financeira'!P71,'Head Qualidade&Dir. Industrial'!P71) -> 2108484.9 | AB56: =SUM(Diadema!Y179,Ferraz!X147,'São Leopoldo'!X109,Jarinu!X147,Anchieta!X105,Corporativo!Q75,'Compras '!U147,Vendas!Q86,'Diretoria Financeira'!Q71,'Head Qualidade&Dir. Industrial'!Q71) -> 2694845.5 | AC56: =SUM(Diadema!Z179,Ferraz!Y147,'São Leopoldo'!Y109,Jarinu!Y147,Anchieta!Y105,Corporativo!R75,'Compras '!V147,Vendas!R86,'Diretoria Financeira'!R71,'Head Qualidade&Dir. Industrial'!R71) -> 2949641.2 | AD56: =SUM(Diadema!AA179,Ferraz!Z147,'São Leopoldo'!Z109,Jarinu!Z147,Anchieta!Z105,Corporativo!S75,'Compras '!W147,Vendas!S86,'Diretoria Financeira'!S71,'Head Qualidade&Dir. Industrial'!S71) -> 3749259.2 | ... AH56: =SUM(Diadema!AE179,Ferraz!AD147,'São Leopoldo'!AD109,Jarinu!AD147,Anchieta!AD105,Corporativo!W75,'Compras '!AA147,Vendas!W86,'Diretoria Financeira'!W71,'Head Qualidade&Dir. Industrial'!W71) -> 7305948.1 | AI56: =SUM(W56:AH56) -> 40637373
D57: 2 | E57: =_xlfn.XLOOKUP(F57,Pareto!S:S,Pareto!T:T) -> São leopoldo | F57: =_xlfn.XLOOKUP(K57,Pareto!V:V,Pareto!S:S) -> 07- Reestruturação | H57: =_xlfn.XLOOKUP(F57,Pareto!S:S,Pareto!X:X) -> ✓ Concluído | I57: =_xlfn.XLOOKUP('5 Unidades +'!F57,Pareto!S:S,Pareto!Z:Z) -> OK | J57: =_xlfn.XLOOKUP(F57,Pareto!S:S,Pareto!U:U) -> 520985.23 | K57: =IFERROR(LARGE(Pareto!V:V,D57)," ") -> 868308.71 | L57: =_xlfn.XLOOKUP(F57,Pareto!S:S,Pareto!W:W) -> 933084 | M57: =IF(L57="",-K57,L57-K57) -> 64775.285 | V57: Real | W57: =Diadema!T180+Jarinu!S148+Ferraz!S148+Anchieta!S106+'São Leopoldo'!S110+'Compras '!P148+Vendas!L87+Corporativo!M74 -> 823549.22 | X57: =Diadema!U180+Jarinu!T148+Ferraz!T148+Anchieta!T106+'São Leopoldo'!T110+'Compras '!Q148+Vendas!M87+Corporativo!N74 -> 683834.99 | Y57: =Diadema!V180+Jarinu!U148+Ferraz!U148+Anchieta!U106+'São Leopoldo'!U110+'Compras '!R148+Vendas!N87+Corporativo!O74 -> 830718.25 | Z57: =Diadema!W180+Jarinu!V148+Ferraz!V148+Anchieta!V106+'São Leopoldo'!V110+'Compras '!S148+Vendas!O87+Corporativo!P74 -> 812633.96 | AA57: =Diadema!X180+Jarinu!W148+Ferraz!W148+Anchieta!W106+'São Leopoldo'!W110+'Compras '!T148+Vendas!P87+Corporativo!Q74 -> 997294.15 | AB57: =Diadema!Y180+Jarinu!X148+Ferraz!X148+Anchieta!X106+'São Leopoldo'!X110+'Compras '!U148+Vendas!Q87+Corporativo!R74 -> 1132843.2 | AC57: =Diadema!Z180+Jarinu!Y148+Ferraz!Y148+Anchieta!Y106+'São Leopoldo'!Y110+'Compras '!V148+Vendas!R87+Corporativo!S74 -> 325111.97 | AD57: =Diadema!AA180+Jarinu!Z148+Ferraz!Z148+Anchieta!Z106+'São Leopoldo'!Z110+'Compras '!W148+Vendas!S87+Corporativo!T74 -> 17584 | ... AH57: =Diadema!AE180+Jarinu!AD148+Ferraz!AD148+Anchieta!AD106+'São Leopoldo'!AD110+'Compras '!AA148+Vendas!W87+Corporativo!X74 -> 0 | AI57: =SUM(W57:AH57) -> 5623569.8
D58: 3 | E58: =_xlfn.XLOOKUP(F58,Pareto!S:S,Pareto!T:T) -> Compras | F58: =_xlfn.XLOOKUP(K58,Pareto!V:V,Pareto!S:S) -> Projeto DANA - Mudança de CH para BQ | H58: =_xlfn.XLOOKUP(F58,Pareto!S:S,Pareto!X:X) -> ✓ Concluído | I58: =_xlfn.XLOOKUP('5 Unidades +'!F58,Pareto!S:S,Pareto!Z:Z) -> OK | J58: =_xlfn.XLOOKUP(F58,Pareto!S:S,Pareto!U:U) -> 1444478.7 | K58: =IFERROR(LARGE(Pareto!V:V,D58)," ") -> 412708.21 | L58: =_xlfn.XLOOKUP(F58,Pareto!S:S,Pareto!W:W) | M58: =IF(L58="",-K58,L58-K58) -> -412708.21 | V58: Q. Projetos | W58: =Diadema!T181+Anchieta!S107+Ferraz!S149+Jarinu!S149+'São Leopoldo'!S111+Corporativo!L76+Vendas!L88+'Compras '!P149 -> #REF! | X58: =SUM(Diadema!U181,Ferraz!T149,'São Leopoldo'!T111,Jarinu!T149,Anchieta!T107,Corporativo!M77,'Compras '!Q149,Vendas!M88,'Diretoria Financeira'!M73) -> #REF! | Y58: =SUM(Diadema!V181,Ferraz!U149,'São Leopoldo'!U111,Jarinu!U149,Anchieta!U107,Corporativo!N77,'Compras '!R149,Vendas!N88,'Diretoria Financeira'!N73) -> #REF! | Z58: =SUM(Diadema!W181,Ferraz!V149,'São Leopoldo'!V111,Jarinu!V149,Anchieta!V107,Corporativo!O77,'Compras '!S149,Vendas!O88,'Diretoria Financeira'!O73) -> #REF! | AA58: =SUM(Diadema!X181,Ferraz!W149,'São Leopoldo'!W111,Jarinu!W149,Anchieta!W107,Corporativo!P77,'Compras '!T149,Vendas!P88,'Diretoria Financeira'!P73) -> #REF! | AB58: =SUM(Diadema!Y181,Ferraz!X149,'São Leopoldo'!X111,Jarinu!X149,Anchieta!X107,Corporativo!Q77,'Compras '!U149,Vendas!Q88,'Diretoria Financeira'!Q73) -> #REF! | AC58: =SUM(Diadema!Z181,Ferraz!Y149,'São Leopoldo'!Y111,Jarinu!Y149,Anchieta!Y107,Corporativo!R77,'Compras '!V149,Vendas!R88,'Diretoria Financeira'!R73) -> #REF! | AD58: =SUM(Diadema!AA181,Ferraz!Z149,'São Leopoldo'!Z111,Jarinu!Z149,Anchieta!Z107,Corporativo!S77,'Compras '!W149,Vendas!S88,'Diretoria Financeira'!S73) -> #REF! | AE58: =SUM(Diadema!AB181,Ferraz!AA149,'São Leopoldo'!AA111,Jarinu!AA149,Anchieta!AA107,Corporativo!T77,'Compras '!X149,Vendas!T88,'Diretoria Financeira'!T73) -> #REF! | ... AH58: =SUM(Diadema!AE181,Ferraz!AD149,'São Leopoldo'!AD111,Jarinu!AD149,Anchieta!AD107,Corporativo!W77,'Compras '!AA149,Vendas!W88,'Diretoria Financeira'!W73) -> #REF!
D59: 4 | E59: =_xlfn.XLOOKUP(F59,Pareto!S:S,Pareto!T:T) -> Jarinu | F59: =_xlfn.XLOOKUP(K59,Pareto!V:V,Pareto!S:S) -> 36 - Venda Robos | H59: =_xlfn.XLOOKUP(F59,Pareto!S:S,Pareto!X:X) -> ✓ Concluído | I59: =_xlfn.XLOOKUP('5 Unidades +'!F59,Pareto!S:S,Pareto!Z:Z) -> OK | J59: =_xlfn.XLOOKUP(F59,Pareto!S:S,Pareto!U:U) -> 0 | K59: =IFERROR(LARGE(Pareto!V:V,D59)," ") -> 390000 | L59: =_xlfn.XLOOKUP(F59,Pareto!S:S,Pareto!W:W) -> 390000 | M59: =IF(L59="",-K59,L59-K59) -> -0.003 | V59: Acumulado Previsto | W59: =W56 -> 1727858.4 | X59: =W59+X56 -> 3129114.3 | Y59: =X59+Y56 -> 4976284.8 | Z59: =Y59+Z56 -> 6906456.4 | AA59: =Z59+AA56 -> 9014941.3 | AB59: =AA59+AB56 -> 11709787 | AC59: =AB59+AC56 -> 14659428 | AD59: =AC59+AD56 -> 18408687 | AE59: =AD59+AE56 -> 22455993 | ... AH59: =AG59+AH56 -> 40637373
D60: 5 | E60: =_xlfn.XLOOKUP(F60,Pareto!S:S,Pareto!T:T) -> Ferraz | F60: =_xlfn.XLOOKUP(K60,Pareto!V:V,Pareto!S:S) -> 06 - Reaproveitamento de lixas | H60: =_xlfn.XLOOKUP(F60,Pareto!S:S,Pareto!X:X) -> ✓ Concluído | I60: =_xlfn.XLOOKUP('5 Unidades +'!F60,Pareto!S:S,Pareto!Z:Z) -> OK | J60: =_xlfn.XLOOKUP(F60,Pareto!S:S,Pareto!U:U) -> 151815.13 | K60: =IFERROR(LARGE(Pareto!V:V,D60)," ") -> 354235.3 | L60: =_xlfn.XLOOKUP(F60,Pareto!S:S,Pareto!W:W) -> 276395.48 | M60: =IF(L60="",-K60,L60-K60) -> -77839.823 | V60: Acumulado Real | W60: =W57 -> 823549.22 | X60: =W60+X57 -> 1507384.2 | Y60: =X60+Y57 -> 2338102.5 | Z60: =Y60+Z57 -> 3150736.4 | AA60: =Z60+AA57 -> 4148030.6 | AB60: =AA60+AB57 -> 5280873.8 | AC60: =AB60+AC57 -> 5605985.8 | AD60: =AC60+AD57 -> 5623569.8 | AE60: =AD60+AE57 -> 5623569.8 | ... AH60: =AG60+AH57 -> 5623569.8
D61: 6 | E61: =_xlfn.XLOOKUP(F61,Pareto!S:S,Pareto!T:T) -> Ferraz | F61: =_xlfn.XLOOKUP(K61,Pareto!V:V,Pareto!S:S) -> 03 - Consumo de desmoldante | H61: =_xlfn.XLOOKUP(F61,Pareto!S:S,Pareto!X:X) -> ✓ Concluído | I61: =_xlfn.XLOOKUP('5 Unidades +'!F61,Pareto!S:S,Pareto!Z:Z) -> OK | J61: =_xlfn.XLOOKUP(F61,Pareto!S:S,Pareto!U:U) -> 126310.64 | K61: =IFERROR(LARGE(Pareto!V:V,D61)," ") -> 294724.83 | L61: =_xlfn.XLOOKUP(F61,Pareto!S:S,Pareto!W:W) -> 525129.73 | M61: =IF(L61="",-K61,L61-K61) -> 230404.9 | P61: , | V61: Projeção da Meta | W61: =W60 -> 823549.22 | X61: =IF(AND(ISNUMBER(X57),X57<>0), X60, W61 + ((Parâmetros!$E$15 - MAX($W$60:$AI$60)) / COUNTIF($W$57:$AI$57,0))) -> 1507384.2 | Y61: =IF(AND(ISNUMBER(Y57),Y57<>0), Y60, X61 + ((Parâmetros!$E$15 - MAX($W$60:$AI$60)) / COUNTIF($W$57:$AI$57,0))) -> 2338102.5 | Z61: =IF(AND(ISNUMBER(Z57),Z57<>0), Z60, Y61 + ((Parâmetros!$E$15 - MAX($W$60:$AI$60)) / COUNTIF($W$57:$AI$57,0))) -> 3150736.4 | AA61: =IF(AND(ISNUMBER(AA57),AA57<>0), AA60, Z61 + ((Parâmetros!$E$15 - MAX($W$60:$AI$60)) / COUNTIF($W$57:$AI$57,0))) -> 4148030.6 | AB61: =IF(AND(ISNUMBER(AB57),AB57<>0), AB60, AA61 + ((Parâmetros!$E$15 - MAX($W$60:$AI$60)) / COUNTIF($W$57:$AI$57,0))) -> 5280873.8 | AC61: =IF(AND(ISNUMBER(AC57),AC57<>0), AC60, AB61 + ((Parâmetros!$E$15 - MAX($W$60:$AI$60)) / COUNTIF($W$57:$AI$57,0))) -> 5605985.8 | AD61: =IF(AND(ISNUMBER(AD57),AD57<>0), AD60, AC61 + ((Parâmetros!$E$15 - MAX($W$60:$AI$60)) / COUNTIF($W$57:$AI$57,0))) -> 5623569.8 | AE61: =IF(AND(ISNUMBER(AE57),AE57<>0), AE60, AD61 + ((Parâmetros!$E$15 - MAX($W$60:$AI$60)) / COUNTIF($W$57:$AI$57,0))) -> 16797677 | ... AH61: =IF(AND(ISNUMBER(AH57),AH57<>0), AH60, AG61 + ((Parâmetros!$E$15 - MAX($W$60:$AI$60)) / COUNTIF($W$57:$AI$57,0))) -> 50320000
D62: 7 | E62: =_xlfn.XLOOKUP(F62,Pareto!S:S,Pareto!T:T) -> Ferraz | F62: =_xlfn.XLOOKUP(K62,Pareto!V:V,Pareto!S:S) -> 03 - Consumo de desmoldante | H62: =_xlfn.XLOOKUP(F62,Pareto!S:S,Pareto!X:X) -> ✓ Concluído | I62: =_xlfn.XLOOKUP('5 Unidades +'!F62,Pareto!S:S,Pareto!Z:Z) -> OK | J62: =_xlfn.XLOOKUP(F62,Pareto!S:S,Pareto!U:U) -> 126310.64 | K62: =IFERROR(LARGE(Pareto!V:V,D62)," ") -> 294724.83 | L62: =_xlfn.XLOOKUP(F62,Pareto!S:S,Pareto!W:W) -> 525129.73 | M62: =IF(L62="",-K62,L62-K62) -> 230404.9 | V62: Acumulado prev.Custos | W62: =W63 -> 886433.43 | X62: =W62+X63 -> 1357922.2 | Y62: =X62+Y63 -> 2131437.1 | Z62: =Y62+Z63 -> 2954336.8 | AA62: =Z62+AA63 -> 3889491.6 | AB62: =AA62+AB63 -> 5176381.8 | AC62: =AB62+AC63 -> 6575785.2 | AD62: =AC62+AD63 -> 8109702.2 | AE62: =AD62+AE63 -> 9657948.6 | ... AH62: =AG62+AH63 -> 15701522
D63: 8 | E63: =_xlfn.XLOOKUP(F63,Pareto!S:S,Pareto!T:T) -> Ferraz | F63: =_xlfn.XLOOKUP(K63,Pareto!V:V,Pareto!S:S) -> 07 - Consumo de gás | H63: =_xlfn.XLOOKUP(F63,Pareto!S:S,Pareto!X:X) -> ✓ Concluído | I63: =_xlfn.XLOOKUP('5 Unidades +'!F63,Pareto!S:S,Pareto!Z:Z) -> OK | J63: =_xlfn.XLOOKUP(F63,Pareto!S:S,Pareto!U:U) -> 101344.25 | K63: =IFERROR(LARGE(Pareto!V:V,D63)," ") -> 236469.92 | L63: =_xlfn.XLOOKUP(F63,Pareto!S:S,Pareto!W:W) -> 413825.57 | M63: =IF(L63="",-K63,L63-K63) -> 177355.65 | V63: Custos | W63: =Diadema!T185+Jarinu!S153+Ferraz!S153+'São Leopoldo'!S115+Anchieta!S111+'Compras '!P153+Vendas!L92 -> 886433.43 | X63: =Diadema!U185+Jarinu!T153+Ferraz!T153+'São Leopoldo'!T115+Anchieta!T111+'Compras '!Q153+Vendas!M92 -> 471488.78 | Y63: =Diadema!V185+Jarinu!U153+Ferraz!U153+'São Leopoldo'!U115+Anchieta!U111+'Compras '!R153+Vendas!N92 -> 773514.92 | Z63: =Diadema!W185+Jarinu!V153+Ferraz!V153+'São Leopoldo'!V115+Anchieta!V111+'Compras '!S153+Vendas!O92 -> 822899.7 | AA63: =Diadema!X185+Jarinu!W153+Ferraz!W153+'São Leopoldo'!W115+Anchieta!W111+'Compras '!T153+Vendas!P92 -> 935154.76 | AB63: =Diadema!Y185+Jarinu!X153+Ferraz!X153+'São Leopoldo'!X115+Anchieta!X111+'Compras '!U153+Vendas!Q92 -> 1286890.3 | AC63: =Diadema!Z185+Jarinu!Y153+Ferraz!Y153+'São Leopoldo'!Y115+Anchieta!Y111+'Compras '!V153+Vendas!R92 -> 1399403.4 | AD63: =Diadema!AA185+Jarinu!Z153+Ferraz!Z153+'São Leopoldo'!Z115+Anchieta!Z111+'Compras '!W153+Vendas!S92 -> 1533917 | ... AH63: =Diadema!AE185+Jarinu!AD153+Ferraz!AD153+'São Leopoldo'!AD115+Anchieta!AD111+'Compras '!AA153+Vendas!W92 -> 2023193.3 | AI63: =SUM(W63:AH63) -> 15701522
D64: 9 | E64: =_xlfn.XLOOKUP(F64,Pareto!S:S,Pareto!T:T) -> Diadema | F64: =_xlfn.XLOOKUP(K64,Pareto!V:V,Pareto!S:S) -> 29 - DA000489Z_DA000490Z - STC Scania M_ | H64: =_xlfn.XLOOKUP(F64,Pareto!S:S,Pareto!X:X) -> ✓ Concluído | I64: =_xlfn.XLOOKUP('5 Unidades +'!F64,Pareto!S:S,Pareto!Z:Z) -> OK | J64: =_xlfn.XLOOKUP(F64,Pareto!S:S,Pareto!U:U) -> 446423.79 | K64: =IFERROR(LARGE(Pareto!V:V,D64)," ") -> 223211.9 | L64: =_xlfn.XLOOKUP(F64,Pareto!S:S,Pareto!W:W) -> 282888.46 | M64: =IF(L64="",-K64,L64-K64) -> 59676.57
D65: 10 | E65: =_xlfn.XLOOKUP(F65,Pareto!S:S,Pareto!T:T) -> Jarinu | F65: =_xlfn.XLOOKUP(K65,Pareto!V:V,Pareto!S:S) -> 26 - Redução de gastos com HE | H65: =_xlfn.XLOOKUP(F65,Pareto!S:S,Pareto!X:X) -> ✓ Concluído | I65: =_xlfn.XLOOKUP('5 Unidades +'!F65,Pareto!S:S,Pareto!Z:Z) | J65: =_xlfn.XLOOKUP(F65,Pareto!S:S,Pareto!U:U) -> 107700 | K65: =IFERROR(LARGE(Pareto!V:V,D65)," ") -> 179500 | L65: =_xlfn.XLOOKUP(F65,Pareto!S:S,Pareto!W:W) | M65: =IF(L65="",-K65,L65-K65) -> -179500
D66: 11 | E66: =_xlfn.XLOOKUP(F66,Pareto!S:S,Pareto!T:T) -> Ferraz | F66: =_xlfn.XLOOKUP(K66,Pareto!V:V,Pareto!S:S) -> 17 - Consumo de água | H66: =_xlfn.XLOOKUP(F66,Pareto!S:S,Pareto!X:X) -> ✓ Concluído | I66: =_xlfn.XLOOKUP('5 Unidades +'!F66,Pareto!S:S,Pareto!Z:Z) -> OK | J66: =_xlfn.XLOOKUP(F66,Pareto!S:S,Pareto!U:U) -> 76753.75 | K66: =IFERROR(LARGE(Pareto!V:V,D66)," ") -> 179092.08 | L66: =_xlfn.XLOOKUP(F66,Pareto!S:S,Pareto!W:W) -> 45098 | M66: =IF(L66="",-K66,L66-K66) -> -133994.08
D67: 12 | E67: =_xlfn.XLOOKUP(F67,Pareto!S:S,Pareto!T:T) -> Compras | F67: =_xlfn.XLOOKUP(K67,Pareto!V:V,Pareto!S:S) -> Mão de Obra Terceirizada | H67: =_xlfn.XLOOKUP(F67,Pareto!S:S,Pareto!X:X) -> ✓ Concluído | I67: =_xlfn.XLOOKUP('5 Unidades +'!F67,Pareto!S:S,Pareto!Z:Z) | J67: =_xlfn.XLOOKUP(F67,Pareto!S:S,Pareto!U:U) -> 600868 | K67: =IFERROR(LARGE(Pareto!V:V,D67)," ") -> 171676.57 | L67: =_xlfn.XLOOKUP(F67,Pareto!S:S,Pareto!W:W) | M67: =IF(L67="",-K67,L67-K67) -> -171676.57
D68: 13 | E68: =_xlfn.XLOOKUP(F68,Pareto!S:S,Pareto!T:T) -> Ferraz | F68: =_xlfn.XLOOKUP(K68,Pareto!V:V,Pareto!S:S) -> 04 - Redução dos retrabalhos | H68: =_xlfn.XLOOKUP(F68,Pareto!S:S,Pareto!X:X) -> ✓ Concluído | I68: =_xlfn.XLOOKUP('5 Unidades +'!F68,Pareto!S:S,Pareto!Z:Z) | J68: =_xlfn.XLOOKUP(F68,Pareto!S:S,Pareto!U:U) -> 168750 | K68: =IFERROR(LARGE(Pareto!V:V,D68)," ") -> 168750 | L68: =_xlfn.XLOOKUP(F68,Pareto!S:S,Pareto!W:W) | M68: =IF(L68="",-K68,L68-K68) -> -168750
D69: 14 | E69: =_xlfn.XLOOKUP(F69,Pareto!S:S,Pareto!T:T) -> Compras | F69: =_xlfn.XLOOKUP(K69,Pareto!V:V,Pareto!S:S) -> Negociação de itens Usiminas (SAR55 / scania / Mercedes / demais itens e reajuste frete) | H69: =_xlfn.XLOOKUP(F69,Pareto!S:S,Pareto!X:X) -> ✓ Concluído | I69: =_xlfn.XLOOKUP('5 Unidades +'!F69,Pareto!S:S,Pareto!Z:Z) | J69: =_xlfn.XLOOKUP(F69,Pareto!S:S,Pareto!U:U) -> 572763 | K69: =IFERROR(LARGE(Pareto!V:V,D69)," ") -> 163646.57 | L69: =_xlfn.XLOOKUP(F69,Pareto!S:S,Pareto!W:W) | M69: =IF(L69="",-K69,L69-K69) -> -163646.57
D70: 15 | E70: =_xlfn.XLOOKUP(F70,Pareto!S:S,Pareto!T:T) -> Jarinu | F70: =_xlfn.XLOOKUP(K70,Pareto!V:V,Pareto!S:S) -> 21 - Redução de MOD CSR61014 | H70: =_xlfn.XLOOKUP(F70,Pareto!S:S,Pareto!X:X) -> ✓ Concluído | I70: =_xlfn.XLOOKUP('5 Unidades +'!F70,Pareto!S:S,Pareto!Z:Z) | J70: =_xlfn.XLOOKUP(F70,Pareto!S:S,Pareto!U:U) -> 81818.182 | K70: =IFERROR(LARGE(Pareto!V:V,D70)," ") -> 163636.36 | L70: =_xlfn.XLOOKUP(F70,Pareto!S:S,Pareto!W:W) | M70: =IF(L70="",-K70,L70-K70) -> -163636.36
D71: 16 | E71: =_xlfn.XLOOKUP(F71,Pareto!S:S,Pareto!T:T) -> Jarinu | F71: =_xlfn.XLOOKUP(K71,Pareto!V:V,Pareto!S:S) -> 22 - Redução de MOD CSR61015 | H71: =_xlfn.XLOOKUP(F71,Pareto!S:S,Pareto!X:X) -> ✓ Concluído | I71: =_xlfn.XLOOKUP('5 Unidades +'!F71,Pareto!S:S,Pareto!Z:Z) | J71: =_xlfn.XLOOKUP(F71,Pareto!S:S,Pareto!U:U) -> 81818.182 | K71: =IFERROR(LARGE(Pareto!V:V,D71)," ") -> 163636.36 | L71: =_xlfn.XLOOKUP(F71,Pareto!S:S,Pareto!W:W) | M71: =IF(L71="",-K71,L71-K71) -> -163636.36
D72: 17 | E72: =_xlfn.XLOOKUP(F72,Pareto!S:S,Pareto!T:T) -> Compras | F72: =_xlfn.XLOOKUP(K72,Pareto!V:V,Pareto!S:S) -> Viabilizar itens Usiminas via Gonvarri-Full Service | H72: =_xlfn.XLOOKUP(F72,Pareto!S:S,Pareto!X:X) -> ✓ Concluído | I72: =_xlfn.XLOOKUP('5 Unidades +'!F72,Pareto!S:S,Pareto!Z:Z) | J72: =_xlfn.XLOOKUP(F72,Pareto!S:S,Pareto!U:U) -> 317391 | K72: =IFERROR(LARGE(Pareto!V:V,D72)," ") -> 158695.5 | L72: =_xlfn.XLOOKUP(F72,Pareto!S:S,Pareto!W:W) | M72: =IF(L72="",-K72,L72-K72) -> -158695.5
D73: 18 | E73: =_xlfn.XLOOKUP(F73,Pareto!S:S,Pareto!T:T) -> São leopoldo | F73: =_xlfn.XLOOKUP(K73,Pareto!V:V,Pareto!S:S) -> 01 - Redução de Refugo | H73: =_xlfn.XLOOKUP(F73,Pareto!S:S,Pareto!X:X) -> ✓ Concluído | I73: =_xlfn.XLOOKUP('5 Unidades +'!F73,Pareto!S:S,Pareto!Z:Z) -> OK | J73: =_xlfn.XLOOKUP(F73,Pareto!S:S,Pareto!U:U) -> 59652.758 | K73: =IFERROR(LARGE(Pareto!V:V,D73)," ") -> 119305.52 | L73: =_xlfn.XLOOKUP(F73,Pareto!S:S,Pareto!W:W) -> 186458.31 | M73: =IF(L73="",-K73,L73-K73) -> 67152.794
D74: 19 | E74: =_xlfn.XLOOKUP(F74,Pareto!S:S,Pareto!T:T) -> Compras | F74: =_xlfn.XLOOKUP(K74,Pareto!V:V,Pareto!S:S) -> Redução de custo Abrasivos Curva A Ferraz | H74: =_xlfn.XLOOKUP(F74,Pareto!S:S,Pareto!X:X) -> ✓ Concluído | I74: =_xlfn.XLOOKUP('5 Unidades +'!F74,Pareto!S:S,Pareto!Z:Z) -> OK | J74: =_xlfn.XLOOKUP(F74,Pareto!S:S,Pareto!U:U) -> 200000 | K74: =IFERROR(LARGE(Pareto!V:V,D74)," ") -> 116666.67 | L74: =_xlfn.XLOOKUP(F74,Pareto!S:S,Pareto!W:W) | M74: =IF(L74="",-K74,L74-K74) -> -116666.67
D75: 20 | E75: =_xlfn.XLOOKUP(F75,Pareto!S:S,Pareto!T:T) -> Jarinu | F75: =_xlfn.XLOOKUP(K75,Pareto!V:V,Pareto!S:S) -> 30 - Redução de Refugo | H75: =_xlfn.XLOOKUP(F75,Pareto!S:S,Pareto!X:X) -> ⏳ Em Execução | I75: =_xlfn.XLOOKUP('5 Unidades +'!F75,Pareto!S:S,Pareto!Z:Z) -> OK | J75: =_xlfn.XLOOKUP(F75,Pareto!S:S,Pareto!U:U) -> 114750 | K75: =IFERROR(LARGE(Pareto!V:V,D75)," ") -> 114750 | L75: =_xlfn.XLOOKUP(F75,Pareto!S:S,Pareto!W:W) | M75: =IF(L75="",-K75,L75-K75) -> -114750
... D259: 204 | E259: =_xlfn.XLOOKUP(F259,Pareto!S:S,Pareto!T:T) -> Ferraz | F259: =_xlfn.XLOOKUP(K259,Pareto!V:V,Pareto!S:S) -> 01 - Clientes com baixa margem de contribuição. | H259: =_xlfn.XLOOKUP(F259,Pareto!S:S,Pareto!X:X) -> ⏳ Em Execução | I259: =_xlfn.XLOOKUP('5 Unidades +'!F259,Pareto!S:S,Pareto!Z:Z) | J259: =_xlfn.XLOOKUP(F259,Pareto!S:S,Pareto!U:U) -> 0 | K259: =IFERROR(LARGE(Pareto!V:V,D259)," ") | L259: =_xlfn.XLOOKUP(F259,Pareto!S:S,Pareto!W:W) | M259: =IF(L259="",-K259,L259-K259) -> #VALUE!
J260: =SUBTOTAL(9,J55:J155) -> 11604338 | K260: =SUM(K56:K155) -> 8835611.1 | L260: {=SUM(IFERROR(L56:L155,0))} -> 6125508.4 | M260: =L260-K260 -> -2710102.7
D266: Unidade | E266: Previsto | F266: Real
D267: Compras | E267: =SUMIF($E$56:$E$259,D267,$K$56:$K$259) -> 3358648.2 | F267: =SUMIF($E$56:$E$259,D267,$L$56:$L$259) -> 1282436.3
D268: Ferraz | E268: =SUMIF($E$56:$E$259,D268,$K$56:$K$259) -> 1731364.5 | F268: =SUMIF($E$56:$E$259,D268,$L$56:$L$259) -> 1892595.4
D269: São leopoldo | E269: =SUMIF($E$56:$E$259,D269,$K$56:$K$259) -> 1044577.6 | F269: =SUMIF($E$56:$E$259,D269,$L$56:$L$259) -> 1158700.7
D270: Diadema | E270: =SUMIF($E$56:$E$259,D270,$K$56:$K$259) -> 1179699.9 | F270: =SUMIF($E$56:$E$259,D270,$L$56:$L$259) -> 997266.68
D271: Anchieta | E271: =SUMIF($E$56:$E$259,D271,$K$56:$K$259) -> 348094.48 | F271: =SUMIF($E$56:$E$259,D271,$L$56:$L$259) -> 331443.95
D272: Jarinu | E272: =SUMIF($E$56:$E$259,D272,$K$56:$K$259) -> 1176931.5 | F272: =SUMIF($E$56:$E$259,D272,$L$56:$L$259) -> 463507.45

Sheet Diadema
A1: DASHBOARD EXECUTIVO - UNIDADE DIADEMA
A2: Gestão Estratégica de Projetos e Redução de Custos | Grupo Delga | 2026
A4: META DA UNIDADE 2026 | B4: RETORNO PREVISTO (Anual) | C4: Retorno Validado (Anual) | D4: PREVISTO 2026 | E4: 💰 RETORNO VALIDADO 2026 | G4: 💰 RETORNO REAL 2026 | I4: Extra DRE (Até o momento) | J4: % ATINGIMENTO DA META 2026 | L4: INICIATIVAS | O4: TOP 20 Raking de Projetos Valorizados | AP4: dip | AQ4: perf | AU4: 2025 | AV4: 2026
A5: =Parâmetros!E5 -> 6947000 | B5: =SUM(I55:I176) -> 4661058.2 | C5: =AV53 -> 4424279.6 | D5: =AU53 -> 2988619.3 | E5: =SUM(N55:N176) -> 2877285.2 | G5: =SUM(E9,E11:E13) -> 1008796 | I5: =E8+E10 -> 137181.16 | J5: =G5/A5 -> 0.14521318 | L5: =SUM(G8:G10) -> 57 | O5: POS | P5: Tipo | Q5: Valor Previsto Unidade | R5: Valor Previsto Custos | S5: Retorno Previsto | T5: Retorno Real até hoje | U5: Projetos | Z5: Peso | AA5: Pareto | AB5: % Previsto | AC5: % Real | AD5: Planejado | AE5: % Responsabilidade Delga | AS5: 0.3293 | AT5: 0.9228 | AW5: p | AX5: 0.9261 | AY5: 0.95
A6: 📊 SAVING PREVISTO POR PILAR | F6: 📋 STATUS DAS INICIATIVAS | I6: 🏭 INDICADORES OPERACIONAIS | O6: {=_xlfn.SEQUENCE(20)} -> 1 | P6: =_xlfn.XLOOKUP(U6,$C$55:$C$176,$A$55:$A$176) -> BSW | Q6: =MAX(I55:I176) -> 450000.01 | R6: =_xlfn.XLOOKUP(Q6,$I$55:$I$176,$N$55:$N$176) -> 446423.79 | S6: =_xlfn.XLOOKUP(U6,$C$55:$C$176,$J$55:$J$176) -> 46082 | T6: {=SUMPRODUCT(($C$55:$C$175=U6)*(U$54:$AI$54<=TODAY())*(ISNUMBER(U$56:$AI$176)),U$56:$AI$176)} -> 282888.46 | U6: =IFERROR(HYPERLINK(INDEX($D$55:$D$176,MATCH(Q6,$I$55:$I$176,0)),INDEX($C$55:$C$176,MATCH(Q6,$I$55:$I$176,0)) ), ) -> 29 - DA000489Z_DA000490Z - STC Scania M_ | Z6: =Q6/$C$5 -> 0.10171148 | AA6: =Z6 -> 0.10171148 | AB6: {=IFERROR(INDEX($T$55:$T$176,MATCH(1,($AP$55:$AP$176=U6)*($S$55:$S$176="Previsto"), 0) ), "")} -> 1 | AC6: {=IFERROR( INDEX($T$55:$T$176,MATCH(1,($AP$55:$AP$176=U6)*($S$55:$S$176="Real"),0)),"")} -> 1 | AD6: =IF(OR(AB6="",AC6=""),"",IF(AC6=100%,"CONCLUÍDO",IF(AC6=0,IF(AB6=0,"PROJETO NÃO INICIADO","FALTA DE ACOMPANHAMENTO"),IF(AC6>AB6,"ADIANTADO",IF(AC6=AB6,"CONFORME PLANEJADO","ATRASO"))))) -> CONCLUÍDO | AE6: {=_xlfn.XLOOKUP($U$6:$U$25,$C$55:$C$176,$R$55:$R$176)} -> 1 | AS6: 0.4166 | AT6: 0.9152 | AW6: d | AX6: 0.5017 | AY6: 0.58
A7: Pilar | B7: Qtd. | C7: Saving (R$) | D7: Saving Validado 2026 | E7: Até o Momento | F7: Status | G7: Qtd. | H7: R$ Previsto | I7: Aderência SPD: Unidade | J7: Aderência SPD: Auditado | K7: Análise de Margem (Form 206) | O7: 2 | P7: =_xlfn.XLOOKUP(U7,$C$55:$C$176,$A$55:$A$176) -> BSW | Q7: =IFERROR(LARGE($I$55:$I$176,O7)," ") -> 331600 | R7: =_xlfn.XLOOKUP(Q7,$I$55:$I$176,$N$55:$N$176) -> 160178.29 | S7: =_xlfn.XLOOKUP(U7,$C$55:$C$176,$J$55:$J$176) -> 46082 | T7: {=SUMPRODUCT(($C$55:$C$175=U7)*(U$54:$AI$54<=TODAY())*(ISNUMBER(U$56:$AI$176)),U$56:$AI$176)} -> 84365.272 | U7: =IFERROR(HYPERLINK(INDEX($D$55:$D$176,MATCH(Q7,$I$55:$I$176,0)),INDEX($C$55:$C$176,MATCH(Q7,$I$55:$I$176,0)) ), "" ) -> 01 - Redução de peso bruto DA000489A | Z7: =Q7/$C$5 -> 0.074950056 | AA7: =Z7+AA6 -> 0.17666153 | AB7: {=IFERROR(INDEX($T$55:$T$176,MATCH(1,($AP$55:$AP$176=U7)*($S$55:$S$176="Previsto"), 0) ), "")} -> 1 | AC7: {=IFERROR( INDEX($T$55:$T$176,MATCH(1,($AP$55:$AP$176=U7)*($S$55:$S$176="Real"),0)),"")} -> 1 | AD7: =IF(OR(AB7="",AC7=""),"",IF(AC7=100%,"CONCLUÍDO",IF(AC7=0,IF(AB7=0,"PROJETO NÃO INICIADO","FALTA DE ACOMPANHAMENTO"),IF(AC7>AB7,"ADIANTADO",IF(AC7=AB7,"CONFORME PLANEJADO","ATRASO"))))) -> CONCLUÍDO | AE7: 1 | AS7: 0.4666 | AT7: 0.9202 | AW7: q | AX7: 0.955 | AY7: 0.965
A8: Kaizen - Capital de Giro | B8: =COUNTIF($A$55:$A$176,A8) -> 0 | C8: =SUMIF($A$55:$A$176,A8,$I$55:$I$176) -> 0 | D8: =SUMIF($A$55:$A$176,A8,$N$55:$N$176) -> 0 | E8: =SUMIFS($AK$55:$AK$176,$S$55:$S$176,"Previsto",$AS$55:$AS$176,A8) -> 0 | F8: ✓ Concluído | G8: =COUNTIF($O$55:$O$176,F8) -> 45 | H8: =SUMIF($O$55:$O$176,F8,$I$55:$I$176) -> 3446352.2 | O8: 3 | P8: =_xlfn.XLOOKUP(U8,$C$55:$C$176,$A$55:$A$176) -> Kaizen - Ganho Recorrente | Q8: =IFERROR(LARGE($I$55:$I$176,O8)," ") -> 288000 | R8: =_xlfn.XLOOKUP(Q8,$I$55:$I$176,$N$55:$N$176) -> 189414 | S8: =_xlfn.XLOOKUP(U8,$C$55:$C$176,$J$55:$J$176) -> 46143 | T8: {=SUMPRODUCT(($C$55:$C$175=U8)*(U$54:$AI$54<=TODAY())*(ISNUMBER(U$56:$AI$176)),U$56:$AI$176)} -> 17242 | U8: =IFERROR(HYPERLINK(INDEX($D$55:$D$176,MATCH(Q8,$I$55:$I$176,0)),INDEX($C$55:$C$176,MATCH(Q8,$I$55:$I$176,0)) ), "" ) -> 06 - Produtividade | Z8: =Q8/$C$5 -> 0.065095344 | AA8: =Z8+AA7 -> 0.24175688 | AB8: {=IFERROR(INDEX($T$55:$T$176,MATCH(1,($AP$55:$AP$176=U8)*($S$55:$S$176="Previsto"), 0) ), "")} -> 0.96 | AC8: {=IFERROR( INDEX($T$55:$T$176,MATCH(1,($AP$55:$AP$176=U8)*($S$55:$S$176="Real"),0)),"")} -> 0.98 | AD8: =IF(OR(AB8="",AC8=""),"",IF(AC8=100%,"CONCLUÍDO",IF(AC8=0,IF(AB8=0,"PROJETO NÃO INICIADO","FALTA DE ACOMPANHAMENTO"),IF(AC8>AB8,"ADIANTADO",IF(AC8=AB8,"CONFORME PLANEJADO","ATRASO"))))) -> ADIANTADO | AE8: 1 | AT8: 0.5436 | AU8: 0.9206 | AY8: =AX7*AX6*AX5 -> 0.44371627 | AZ8: =AY7*AY6*AY5 -> 0.531715
A9: Kaizen - Ganho Recorrente | B9: =COUNTIF($A$55:$A$176,A9) -> 16 | C9: =SUMIF($A$55:$A$176,A9,$I$55:$I$176) -> 1102734.3 | D9: =SUMIF($A$55:$A$176,A9,$N$55:$N$176) -> 651481.3 | E9: =SUMIFS($AK$55:$AK$176,$S$55:$S$176,"Real",$AS$55:$AS$176,A9) -> 237950.7 | F9: ⏳ Em Execução | G9: =COUNTIF($O$55:$O$176,F9) -> 12 | H9: =SUMIF($O$55:$O$176,F9,$I$55:$I$176) -> 1214706 | I9: =E207 -> 1 | J9: =F207 -> 0.91666667 | K9: =L214 -> 0.25252525 | O9: 4 | P9: =_xlfn.XLOOKUP(U9,$C$55:$C$176,$A$55:$A$176) -> BSW | Q9: =IFERROR(LARGE($I$55:$I$176,O9)," ") -> 288000 | R9: =_xlfn.XLOOKUP(Q9,$I$55:$I$176,$N$55:$N$176) -> 175018.02 | S9: =_xlfn.XLOOKUP(U9,$C$55:$C$176,$J$55:$J$176) -> 46143 | T9: {=SUMPRODUCT(($C$55:$C$175=U9)*(U$54:$AI$54<=TODAY())*(ISNUMBER(U$56:$AI$176)),U$56:$AI$176)} -> 51802.779 | U9: =IFERROR(HYPERLINK(INDEX($D$55:$D$176,MATCH(Q9,$I$55:$I$176,0)),INDEX($C$55:$C$176,MATCH(Q9,$I$55:$I$176,0)) ), "" ) -> 26 - Redução_de_MP - DJ000059Z_DJ000060Z | Z9: =Q9/$C$5 -> 0.065095344 | AA9: =Z9+AA8 -> 0.30685222 | AB9: {=IFERROR(INDEX($T$55:$T$176,MATCH(1,($AP$55:$AP$176=U9)*($S$55:$S$176="Previsto"), 0) ), "")} -> 1 | AC9: {=IFERROR( INDEX($T$55:$T$176,MATCH(1,($AP$55:$AP$176=U9)*($S$55:$S$176="Real"),0)),"")} -> 1 | AD9: =IF(OR(AB9="",AC9=""),"",IF(AC9=100%,"CONCLUÍDO",IF(AC9=0,IF(AB9=0,"PROJETO NÃO INICIADO","FALTA DE ACOMPANHAMENTO"),IF(AC9>AB9,"ADIANTADO",IF(AC9=AB9,"CONFORME PLANEJADO","ATRASO"))))) -> CONCLUÍDO | AE9: 1 | AT9: 0.5123 | AU9: 0.923
A10: Kaizen - Custo Evitado | B10: =COUNTIF($A$55:$A$176,A10) -> 4 | C10: =SUMIF($A$55:$A$176,A10,$I$55:$I$176) -> 137181.16 | D10: =SUMIF($A$55:$A$176,A10,$N$55:$N$176) -> 0 | E10: =SUMIFS($AK$55:$AK$176,$S$55:$S$176,"Previsto",$AS$55:$AS$176,A10) -> 137181.16 | F10: 📝 Não iniciado | G10: =COUNTIF($O$55:$O$176,F10) -> 0 | H10: =SUMIF($O$55:$O$176,F10,$I$55:$I$176) -> 0 | O10: 5 | P10: =_xlfn.XLOOKUP(U10,$C$55:$C$176,$A$55:$A$176) -> BSW | Q10: =IFERROR(LARGE($I$55:$I$176,O10)," ") -> 270000 | R10: =_xlfn.XLOOKUP(Q10,$I$55:$I$176,$N$55:$N$176) -> 128107.04 | S10: =_xlfn.XLOOKUP(U10,$C$55:$C$176,$J$55:$J$176) -> 46235 | T10: {=SUMPRODUCT(($C$55:$C$175=U10)*(U$54:$AI$54<=TODAY())*(ISNUMBER(U$56:$AI$176)),U$56:$AI$176)} -> 0 | U10: =IFERROR(HYPERLINK(INDEX($D$55:$D$176,MATCH(Q10,$I$55:$I$176,0)),INDEX($C$55:$C$176,MATCH(Q10,$I$55:$I$176,0)) ), "" ) -> 23 - Redução do peso bruto VW000581Z / VW000582Z | Z10: =Q10/$C$5 -> 0.061026885 | AA10: =Z10+AA9 -> 0.36787911 | AB10: {=IFERROR(INDEX($T$55:$T$176,MATCH(1,($AP$55:$AP$176=U10)*($S$55:$S$176="Previsto"), 0) ), "")} -> 0.2 | AC10: {=IFERROR( INDEX($T$55:$T$176,MATCH(1,($AP$55:$AP$176=U10)*($S$55:$S$176="Real"),0)),"")} -> 0.25 | AD10: =IF(OR(AB10="",AC10=""),"",IF(AC10=100%,"CONCLUÍDO",IF(AC10=0,IF(AB10=0,"PROJETO NÃO INICIADO","FALTA DE ACOMPANHAMENTO"),IF(AC10>AB10,"ADIANTADO",IF(AC10=AB10,"CONFORME PLANEJADO","ATRASO"))))) -> ADIANTADO | AE10: 0.8 | AT10: 0.5216 | AU10: 0.9165
A11: Redução de Custo | B11: =COUNTIF($A$55:$A$176,A11) -> 0 | C11: =SUMIF($A$55:$A$176,A11,$I$55:$I$176) -> 0 | D11: =SUMIF($A$55:$A$176,B11,$I$55:$I$176) -> 0 | E11: =SUMIFS($AK$55:$AK$176,$S$55:$S$176,"Real",$AS$55:$AS$176,A11) -> 0 | O11: 6 | P11: =_xlfn.XLOOKUP(U11,$C$55:$C$176,$A$55:$A$176) -> BSW | Q11: =IFERROR(LARGE($I$55:$I$176,O11)," ") -> 236000 | R11: =_xlfn.XLOOKUP(Q11,$I$55:$I$176,$N$55:$N$176) -> 77354.64 | S11: =_xlfn.XLOOKUP(U11,$C$55:$C$176,$J$55:$J$176) -> 46174 | T11: {=SUMPRODUCT(($C$55:$C$175=U11)*(U$54:$AI$54<=TODAY())*(ISNUMBER(U$56:$AI$176)),U$56:$AI$176)} -> 12498.573 | U11: =IFERROR(HYPERLINK(INDEX($D$55:$D$176,MATCH(Q11,$I$55:$I$176,0)),INDEX($C$55:$C$176,MATCH(Q11,$I$55:$I$176,0)) ), "" ) -> 52 - Redução de MP - GM000458Z / GM000459Z | Z11: =Q11/$C$5 -> 0.053342018 | AA11: =Z11+AA10 -> 0.42122112 | AB11: {=IFERROR(INDEX($T$55:$T$176,MATCH(1,($AP$55:$AP$176=U11)*($S$55:$S$176="Previsto"), 0) ), "")} -> 1 | AC11: {=IFERROR( INDEX($T$55:$T$176,MATCH(1,($AP$55:$AP$176=U11)*($S$55:$S$176="Real"),0)),"")} -> 1 | AD11: =IF(OR(AB11="",AC11=""),"",IF(AC11=100%,"CONCLUÍDO",IF(AC11=0,IF(AB11=0,"PROJETO NÃO INICIADO","FALTA DE ACOMPANHAMENTO"),IF(AC11>AB11,"ADIANTADO",IF(AC11=AB11,"CONFORME PLANEJADO","ATRASO"))))) -> CONCLUÍDO | AE11: 1 | AT11: 0.5217 | AU11: 0.9237
A12: Você Resolve | B12: =COUNTIF($A$55:$A$176,A12) -> 0 | C12: =SUMIF($A$55:$A$176,A12,$I$55:$I$176) -> 0 | D12: =SUMIF($A$55:$A$176,A12,$N$55:$N$176) -> 0 | E12: =SUMIFS($AK$55:$AK$176,$S$55:$S$176,"Real",$AS$55:$AS$176,A12) -> 0 | O12: 7 | P12: =_xlfn.XLOOKUP(U12,$C$55:$C$176,$A$55:$A$176) -> BSW | Q12: =IFERROR(LARGE($I$55:$I$176,O12)," ") -> 230000 | R12: =_xlfn.XLOOKUP(Q12,$I$55:$I$176,$N$55:$N$176) -> 115018 | S12: =_xlfn.XLOOKUP(U12,$C$55:$C$176,$J$55:$J$176) -> 46204 | T12: {=SUMPRODUCT(($C$55:$C$175=U12)*(U$54:$AI$54<=TODAY())*(ISNUMBER(U$56:$AI$176)),U$56:$AI$176)} -> 28959.052 | U12: =IFERROR(HYPERLINK(INDEX($D$55:$D$176,MATCH(Q12,$I$55:$I$176,0)),INDEX($C$55:$C$176,MATCH(Q12,$I$55:$I$176,0)) ), "" ) -> 44 - Mudança de fonte Usiminas para Arcelor | Z12: =Q12/$C$5 -> 0.051985865 | AA12: =Z12+AA11 -> 0.47320699 | AB12: {=IFERROR(INDEX($T$55:$T$176,MATCH(1,($AP$55:$AP$176=U12)*($S$55:$S$176="Previsto"), 0) ), "")} -> 0.29 | AC12: {=IFERROR( INDEX($T$55:$T$176,MATCH(1,($AP$55:$AP$176=U12)*($S$55:$S$176="Real"),0)),"")} -> 0.36 | AD12: =IF(OR(AB12="",AC12=""),"",IF(AC12=100%,"CONCLUÍDO",IF(AC12=0,IF(AB12=0,"PROJETO NÃO INICIADO","FALTA DE ACOMPANHAMENTO"),IF(AC12>AB12,"ADIANTADO",IF(AC12=AB12,"CONFORME PLANEJADO","ATRASO"))))) -> ADIANTADO | AE12: 0.2 | AT12: 0.5746 | AU12: 0.936
A13: BSW | B13: =COUNTIF($A$55:$A$176,A13) -> 37 | C13: =SUMIF($A$55:$A$176,A13,$I$55:$I$176) -> 3421142.7 | D13: =SUMIF($A$55:$A$176,A13,$N$55:$N$176) -> 2225803.9 | E13: =SUMIFS($AK$55:$AK$176,$S$55:$S$176,"Real",$AS$55:$AS$176,A13) -> 770845.29 | O13: 8 | P13: =_xlfn.XLOOKUP(U13,$C$55:$C$176,$A$55:$A$176) -> Kaizen - Ganho Recorrente | Q13: =IFERROR(LARGE($I$55:$I$176,O13)," ") -> 228000 | R13: =_xlfn.XLOOKUP(Q13,$I$55:$I$176,$N$55:$N$176) -> 152396 | S13: =_xlfn.XLOOKUP(U13,$C$55:$C$176,$J$55:$J$176) -> 46082 | T13: {=SUMPRODUCT(($C$55:$C$175=U13)*(U$54:$AI$54<=TODAY())*(ISNUMBER(U$56:$AI$176)),U$56:$AI$176)} -> 72521 | U13: =IFERROR(HYPERLINK(INDEX($D$55:$D$176,MATCH(Q13,$I$55:$I$176,0)),INDEX($C$55:$C$176,MATCH(Q13,$I$55:$I$176,0)) ), "" ) -> 16 - Eficiência de MO na linha de Solda e Montagem | Z13: =Q13/$C$5 -> 0.051533814 | AA13: =Z13+AA12 -> 0.5247408 | AB13: {=IFERROR(INDEX($T$55:$T$176,MATCH(1,($AP$55:$AP$176=U13)*($S$55:$S$176="Previsto"), 0) ), "")} -> 1 | AC13: {=IFERROR( INDEX($T$55:$T$176,MATCH(1,($AP$55:$AP$176=U13)*($S$55:$S$176="Real"),0)),"")} -> 1 | AD13: =IF(OR(AB13="",AC13=""),"",IF(AC13=100%,"CONCLUÍDO",IF(AC13=0,IF(AB13=0,"PROJETO NÃO INICIADO","FALTA DE ACOMPANHAMENTO"),IF(AC13>AB13,"ADIANTADO",IF(AC13=AB13,"CONFORME PLANEJADO","ATRASO"))))) -> CONCLUÍDO | AE13: 1 | AT13: 0.5423 | AU13: 0.936
A14: TOTAL | B14: =SUM(B8:B13) -> 57 | C14: =SUM(C8:C13) -> 4661058.2 | D14: =SUM(D8:D13) -> 2877285.2 | E14: =SUM(E8:E13) -> 1145977.2 | O14: 9 | P14: =_xlfn.XLOOKUP(U14,$C$55:$C$176,$A$55:$A$176) -> BSW | Q14: =IFERROR(LARGE($I$55:$I$176,O14)," ") -> 223200 | R14: =_xlfn.XLOOKUP(Q14,$I$55:$I$176,$N$55:$N$176) -> 202515.94 | S14: =_xlfn.XLOOKUP(U14,$C$55:$C$176,$J$55:$J$176) -> 46174 | T14: {=SUMPRODUCT(($C$55:$C$175=U14)*(U$54:$AI$54<=TODAY())*(ISNUMBER(U$56:$AI$176)),U$56:$AI$176)} -> 27146.624 | U14: =IFERROR(HYPERLINK(INDEX($D$55:$D$176,MATCH(Q14,$I$55:$I$176,0)),INDEX($C$55:$C$176,MATCH(Q14,$I$55:$I$176,0)) ), "" ) -> 57 - AlmaCAM_Redução de Peso | Z14: =Q14/$C$5 -> 0.050448891 | AA14: =Z14+AA13 -> 0.57518969 | AB14: {=IFERROR(INDEX($T$55:$T$176,MATCH(1,($AP$55:$AP$176=U14)*($S$55:$S$176="Previsto"), 0) ), "")} -> 1 | AC14: {=IFERROR( INDEX($T$55:$T$176,MATCH(1,($AP$55:$AP$176=U14)*($S$55:$S$176="Real"),0)),"")} -> 1 | AD14: =IF(OR(AB14="",AC14=""),"",IF(AC14=100%,"CONCLUÍDO",IF(AC14=0,IF(AB14=0,"PROJETO NÃO INICIADO","FALTA DE ACOMPANHAMENTO"),IF(AC14>AB14,"ADIANTADO",IF(AC14=AB14,"CONFORME PLANEJADO","ATRASO"))))) -> CONCLUÍDO | AE14: 1 | AS14: 0.5472 | AT14: 0.9115
F15: VA | G15: =SUMIF($B$55:$B$176,F15,$N$55:$N$176) -> 2225803.9 | O15: 10 | P15: =_xlfn.XLOOKUP(U15,$C$55:$C$176,$A$55:$A$176) -> Kaizen - Ganho Recorrente | Q15: =IFERROR(LARGE($I$55:$I$176,O15)," ") -> 210000 | R15: =_xlfn.XLOOKUP(Q15,$I$55:$I$176,$N$55:$N$176) -> 122500 | S15: =_xlfn.XLOOKUP(U15,$C$55:$C$176,$J$55:$J$176) -> 46174 | T15: {=SUMPRODUCT(($C$55:$C$175=U15)*(U$54:$AI$54<=TODAY())*(ISNUMBER(U$56:$AI$176)),U$56:$AI$176)} -> 35000 | U15: =IFERROR(HYPERLINK(INDEX($D$55:$D$176,MATCH(Q15,$I$55:$I$176,0)),INDEX($C$55:$C$176,MATCH(Q15,$I$55:$I$176,0)) ), "" ) -> 42 - Aluguel de Compressor | Z15: =Q15/$C$5 -> 0.047465355 | AA15: =Z15+AA14 -> 0.62265505 | AB15: {=IFERROR(INDEX($T$55:$T$176,MATCH(1,($AP$55:$AP$176=U15)*($S$55:$S$176="Previsto"), 0) ), "")} -> 1 | AC15: {=IFERROR( INDEX($T$55:$T$176,MATCH(1,($AP$55:$AP$176=U15)*($S$55:$S$176="Real"),0)),"")} -> 1 | AD15: =IF(OR(AB15="",AC15=""),"",IF(AC15=100%,"CONCLUÍDO",IF(AC15=0,IF(AB15=0,"PROJETO NÃO INICIADO","FALTA DE ACOMPANHAMENTO"),IF(AC15>AB15,"ADIANTADO",IF(AC15=AB15,"CONFORME PLANEJADO","ATRASO"))))) -> CONCLUÍDO | AE15: 1 | AS15: 0.5483 | AT15: 0.9229
F16: GGF | G16: =SUMIF($B$55:$B$176,F16,$N$55:$N$176) -> 605429.3 | O16: 11 | P16: =_xlfn.XLOOKUP(U16,$C$55:$C$176,$A$55:$A$176) -> BSW | Q16: =IFERROR(LARGE($I$55:$I$176,O16)," ") -> 189200 | R16: =_xlfn.XLOOKUP(Q16,$I$55:$I$176,$N$55:$N$176) -> 70963.59 | S16: =_xlfn.XLOOKUP(U16,$C$55:$C$176,$J$55:$J$176) -> 46235 | T16: {=SUMPRODUCT(($C$55:$C$175=U16)*(U$54:$AI$54<=TODAY())*(ISNUMBER(U$56:$AI$176)),U$56:$AI$176)} -> 0 | U16: =IFERROR(HYPERLINK(INDEX($D$55:$D$176,MATCH(Q16,$I$55:$I$176,0)),INDEX($C$55:$C$176,MATCH(Q16,$I$55:$I$176,0)) ), "" ) -> 47 - REDUÇÃO DE MP DJ000079Z – 80Z | Z16: =Q16/$C$5 -> 0.042764024 | AA16: =Z16+AA15 -> 0.66541907 | AB16: {=IFERROR(INDEX($T$55:$T$176,MATCH(1,($AP$55:$AP$176=U16)*($S$55:$S$176="Previsto"), 0) ), "")} -> 0.24 | AC16: {=IFERROR( INDEX($T$55:$T$176,MATCH(1,($AP$55:$AP$176=U16)*($S$55:$S$176="Real"),0)),"")} -> 0.38 | AD16: =IF(OR(AB16="",AC16=""),"",IF(AC16=100%,"CONCLUÍDO",IF(AC16=0,IF(AB16=0,"PROJETO NÃO INICIADO","FALTA DE ACOMPANHAMENTO"),IF(AC16>AB16,"ADIANTADO",IF(AC16=AB16,"CONFORME PLANEJADO","ATRASO"))))) -> ADIANTADO | AE16: 0.5 | AS16: 0.4958 | AT16: 0.9642
F17: MA | G17: =SUMIF($B$55:$B$176,F17,$N$55:$N$176) -> 0 | O17: 12 | P17: =_xlfn.XLOOKUP(U17,$C$55:$C$176,$A$55:$A$176) -> BSW | Q17: =IFERROR(LARGE($I$55:$I$176,O17)," ") -> 115000 | R17: =_xlfn.XLOOKUP(Q17,$I$55:$I$176,$N$55:$N$176) -> 39111.77 | S17: =_xlfn.XLOOKUP(U17,$C$55:$C$176,$J$55:$J$176) -> 46235 | T17: {=SUMPRODUCT(($C$55:$C$175=U17)*(U$54:$AI$54<=TODAY())*(ISNUMBER(U$56:$AI$176)),U$56:$AI$176)} -> 0 | U17: =IFERROR(HYPERLINK(INDEX($D$55:$D$176,MATCH(Q17,$I$55:$I$176,0)),INDEX($C$55:$C$176,MATCH(Q17,$I$55:$I$176,0)) ), "" ) -> 30 - DA000491Z_DE000492Z - STC Scania G_ | Z17: =Q17/$C$5 -> 0.025992932 | AA17: =Z17+AA16 -> 0.691412 | AB17: {=IFERROR(INDEX($T$55:$T$176,MATCH(1,($AP$55:$AP$176=U17)*($S$55:$S$176="Previsto"), 0) ), "")} -> 1 | AC17: {=IFERROR( INDEX($T$55:$T$176,MATCH(1,($AP$55:$AP$176=U17)*($S$55:$S$176="Real"),0)),"")} -> 0.95 | AD17: =IF(OR(AB17="",AC17=""),"",IF(AC17=100%,"CONCLUÍDO",IF(AC17=0,IF(AB17=0,"PROJETO NÃO INICIADO","FALTA DE ACOMPANHAMENTO"),IF(AC17>AB17,"ADIANTADO",IF(AC17=AB17,"CONFORME PLANEJADO","ATRASO"))))) -> ATRASO | AE17: 1 | AS17: =AVERAGE(AS5:AS16) -> 0.4673 | AT17: =AVERAGE(AT5:AT16) -> 0.731075 | AU17: =AT17*AS17 -> 0.34163135
F18: Outros | G18: =SUMIF($B$55:$B$176,F18,$N$55:$N$176) -> 46052 | O18: 13 | P18: =_xlfn.XLOOKUP(U18,$C$55:$C$176,$A$55:$A$176) -> Kaizen - Custo Evitado | Q18: =IFERROR(LARGE($I$55:$I$176,O18)," ") -> 106763.16 | R18: =_xlfn.XLOOKUP(Q18,$I$55:$I$176,$N$55:$N$176) -> 0 | S18: =_xlfn.XLOOKUP(U18,$C$55:$C$176,$J$55:$J$176) -> 46054 | T18: {=SUMPRODUCT(($C$55:$C$175=U18)*(U$54:$AI$54<=TODAY())*(ISNUMBER(U$56:$AI$176)),U$56:$AI$176)} -> 0 | U18: =IFERROR(HYPERLINK(INDEX($D$55:$D$176,MATCH(Q18,$I$55:$I$176,0)),INDEX($C$55:$C$176,MATCH(Q18,$I$55:$I$176,0)) ), "" ) -> 02 - Redução na quantidade de lâmpadas acessa, na produção | Z18: =Q18/$C$5 -> 0.024131197 | AA18: =Z18+AA17 -> 0.7155432 | AB18: {=IFERROR(INDEX($T$55:$T$176,MATCH(1,($AP$55:$AP$176=U18)*($S$55:$S$176="Previsto"), 0) ), "")} -> 1 | AC18: {=IFERROR( INDEX($T$55:$T$176,MATCH(1,($AP$55:$AP$176=U18)*($S$55:$S$176="Real"),0)),"")} -> 1 | AD18: =IF(OR(AB18="",AC18=""),"",IF(AC18=100%,"CONCLUÍDO",IF(AC18=0,IF(AB18=0,"PROJETO NÃO INICIADO","FALTA DE ACOMPANHAMENTO"),IF(AC18>AB18,"ADIANTADO",IF(AC18=AB18,"CONFORME PLANEJADO","ATRASO"))))) -> CONCLUÍDO | AE18: 1
O19: 14 | P19: =_xlfn.XLOOKUP(U19,$C$55:$C$176,$A$55:$A$176) -> BSW | Q19: =IFERROR(LARGE($I$55:$I$176,O19)," ") -> 106000 | R19: =_xlfn.XLOOKUP(Q19,$I$55:$I$176,$N$55:$N$176) -> 99381.26 | S19: =_xlfn.XLOOKUP(U19,$C$55:$C$176,$J$55:$J$176) -> 46136 | T19: {=SUMPRODUCT(($C$55:$C$175=U19)*(U$54:$AI$54<=TODAY())*(ISNUMBER(U$56:$AI$176)),U$56:$AI$176)} -> 76638.27 | U19: =IFERROR(HYPERLINK(INDEX($D$55:$D$176,MATCH(Q19,$I$55:$I$176,0)),INDEX($C$55:$C$176,MATCH(Q19,$I$55:$I$176,0)) ), "" ) -> 45 - Redução de MP GM000409Z | Z19: =Q19/$C$5 -> 0.023958703 | AA19: =Z19+AA18 -> 0.7395019 | AB19: {=IFERROR(INDEX($T$55:$T$176,MATCH(1,($AP$55:$AP$176=U19)*($S$55:$S$176="Previsto"), 0) ), "")} -> 0.88 | AC19: {=IFERROR( INDEX($T$55:$T$176,MATCH(1,($AP$55:$AP$176=U19)*($S$55:$S$176="Real"),0)),"")} -> 1 | AD19: =IF(OR(AB19="",AC19=""),"",IF(AC19=100%,"CONCLUÍDO",IF(AC19=0,IF(AB19=0,"PROJETO NÃO INICIADO","FALTA DE ACOMPANHAMENTO"),IF(AC19>AB19,"ADIANTADO",IF(AC19=AB19,"CONFORME PLANEJADO","ATRASO"))))) -> CONCLUÍDO | AE19: 1
O20: 15 | P20: =_xlfn.XLOOKUP(U20,$C$55:$C$176,$A$55:$A$176) -> Kaizen - Ganho Recorrente | Q20: =IFERROR(LARGE($I$55:$I$176,O20)," ") -> 96000 | R20: =_xlfn.XLOOKUP(Q20,$I$55:$I$176,$N$55:$N$176) -> 43105 | S20: =_xlfn.XLOOKUP(U20,$C$55:$C$176,$J$55:$J$176) -> 46235 | T20: {=SUMPRODUCT(($C$55:$C$175=U20)*(U$54:$AI$54<=TODAY())*(ISNUMBER(U$56:$AI$176)),U$56:$AI$176)} -> 0 | U20: =IFERROR(HYPERLINK(INDEX($D$55:$D$176,MATCH(Q20,$I$55:$I$176,0)),INDEX($C$55:$C$176,MATCH(Q20,$I$55:$I$176,0)) ), "" ) -> 43 - Automação Boomerang | Z20: =Q20/$C$5 -> 0.021698448 | AA20: =Z20+AA19 -> 0.76120035 | AB20: {=IFERROR(INDEX($T$55:$T$176,MATCH(1,($AP$55:$AP$176=U20)*($S$55:$S$176="Previsto"), 0) ), "")} -> 0.3 | AC20: {=IFERROR( INDEX($T$55:$T$176,MATCH(1,($AP$55:$AP$176=U20)*($S$55:$S$176="Real"),0)),"")} -> 0.32 | AD20: =IF(OR(AB20="",AC20=""),"",IF(AC20=100%,"CONCLUÍDO",IF(AC20=0,IF(AB20=0,"PROJETO NÃO INICIADO","FALTA DE ACOMPANHAMENTO"),IF(AC20>AB20,"ADIANTADO",IF(AC20=AB20,"CONFORME PLANEJADO","ATRASO"))))) -> ADIANTADO | AE20: 1
O21: 16 | P21: =_xlfn.XLOOKUP(U21,$C$55:$C$176,$A$55:$A$176) -> BSW | Q21: =IFERROR(LARGE($I$55:$I$176,O21)," ") -> 92500 | R21: =_xlfn.XLOOKUP(Q21,$I$55:$I$176,$N$55:$N$176) -> 153302.58 | S21: =_xlfn.XLOOKUP(U21,$C$55:$C$176,$J$55:$J$176) -> 46174 | T21: {=SUMPRODUCT(($C$55:$C$175=U21)*(U$54:$AI$54<=TODAY())*(ISNUMBER(U$56:$AI$176)),U$56:$AI$176)} -> 0 | U21: =IFERROR(HYPERLINK(INDEX($D$55:$D$176,MATCH(Q21,$I$55:$I$176,0)),INDEX($C$55:$C$176,MATCH(Q21,$I$55:$I$176,0)) ), "" ) -> 50 - Suporte da lanterna MB003681 | Z21: =Q21/$C$5 -> 0.020907359 | AA21: =Z21+AA20 -> 0.78210771 | AB21: {=IFERROR(INDEX($T$55:$T$176,MATCH(1,($AP$55:$AP$176=U21)*($S$55:$S$176="Previsto"), 0) ), "")} -> 0.86 | AC21: {=IFERROR( INDEX($T$55:$T$176,MATCH(1,($AP$55:$AP$176=U21)*($S$55:$S$176="Real"),0)),"")} -> 0.86 | AD21: =IF(OR(AB21="",AC21=""),"",IF(AC21=100%,"CONCLUÍDO",IF(AC21=0,IF(AB21=0,"PROJETO NÃO INICIADO","FALTA DE ACOMPANHAMENTO"),IF(AC21>AB21,"ADIANTADO",IF(AC21=AB21,"CONFORME PLANEJADO","ATRASO"))))) -> CONFORME PLANEJADO | AE21: 1
O22: 17 | P22: =_xlfn.XLOOKUP(U22,$C$55:$C$176,$A$55:$A$176) -> BSW | Q22: =IFERROR(LARGE($I$55:$I$176,O22)," ") -> 91200 | R22: =_xlfn.XLOOKUP(Q22,$I$55:$I$176,$N$55:$N$176) -> 24530.27 | S22: =_xlfn.XLOOKUP(U22,$C$55:$C$176,$J$55:$J$176) -> 46204 | T22: {=SUMPRODUCT(($C$55:$C$175=U22)*(U$54:$AI$54<=TODAY())*(ISNUMBER(U$56:$AI$176)),U$56:$AI$176)} -> 3614.0314 | U22: =IFERROR(HYPERLINK(INDEX($D$55:$D$176,MATCH(Q22,$I$55:$I$176,0)),INDEX($C$55:$C$176,MATCH(Q22,$I$55:$I$176,0)) ), "" ) -> 56 -Redução de Peso Bruto do item SV001141LA / SV001142LA | Z22: =Q22/$C$5 -> 0.020613526 | AA22: =Z22+AA21 -> 0.80272124 | AB22: {=IFERROR(INDEX($T$55:$T$176,MATCH(1,($AP$55:$AP$176=U22)*($S$55:$S$176="Previsto"), 0) ), "")} -> 1 | AC22: {=IFERROR( INDEX($T$55:$T$176,MATCH(1,($AP$55:$AP$176=U22)*($S$55:$S$176="Real"),0)),"")} -> 1 | AD22: =IF(OR(AB22="",AC22=""),"",IF(AC22=100%,"CONCLUÍDO",IF(AC22=0,IF(AB22=0,"PROJETO NÃO INICIADO","FALTA DE ACOMPANHAMENTO"),IF(AC22>AB22,"ADIANTADO",IF(AC22=AB22,"CONFORME PLANEJADO","ATRASO"))))) -> CONCLUÍDO | AE22: 1
O23: 18 | P23: =_xlfn.XLOOKUP(U23,$C$55:$C$176,$A$55:$A$176) -> BSW | Q23: =IFERROR(LARGE($I$55:$I$176,O23)," ") -> 90000 | R23: =_xlfn.XLOOKUP(Q23,$I$55:$I$176,$N$55:$N$176) -> 41632.63 | S23: =_xlfn.XLOOKUP(U23,$C$55:$C$176,$J$55:$J$176) -> 46174 | T23: {=SUMPRODUCT(($C$55:$C$175=U23)*(U$54:$AI$54<=TODAY())*(ISNUMBER(U$56:$AI$176)),U$56:$AI$176)} -> 11219.738 | U23: =IFERROR(HYPERLINK(INDEX($D$55:$D$176,MATCH(Q23,$I$55:$I$176,0)),INDEX($C$55:$C$176,MATCH(Q23,$I$55:$I$176,0)) ), "" ) -> 27 - DA000459AA - STC Volvo_ | Z23: =Q23/$C$5 -> 0.020342295 | AA23: =Z23+AA22 -> 0.82306353 | AB23: {=IFERROR(INDEX($T$55:$T$176,MATCH(1,($AP$55:$AP$176=U23)*($S$55:$S$176="Previsto"), 0) ), "")} -> 1 | AC23: {=IFERROR( INDEX($T$55:$T$176,MATCH(1,($AP$55:$AP$176=U23)*($S$55:$S$176="Real"),0)),"")} -> 1 | AD23: =IF(OR(AB23="",AC23=""),"",IF(AC23=100%,"CONCLUÍDO",IF(AC23=0,IF(AB23=0,"PROJETO NÃO INICIADO","FALTA DE ACOMPANHAMENTO"),IF(AC23>AB23,"ADIANTADO",IF(AC23=AB23,"CONFORME PLANEJADO","ATRASO"))))) -> CONCLUÍDO | AE23: 1
O24: 19 | P24: =_xlfn.XLOOKUP(U24,$C$55:$C$176,$A$55:$A$176) -> Kaizen - Ganho Recorrente | Q24: =IFERROR(LARGE($I$55:$I$176,O24)," ") -> 68000 | R24: =_xlfn.XLOOKUP(Q24,$I$55:$I$176,$N$55:$N$176) -> 56610.76 | S24: =_xlfn.XLOOKUP(U24,$C$55:$C$176,$J$55:$J$176) -> 46082 | T24: {=SUMPRODUCT(($C$55:$C$175=U24)*(U$54:$AI$54<=TODAY())*(ISNUMBER(U$56:$AI$176)),U$56:$AI$176)} -> 25732.163 | U24: =IFERROR(HYPERLINK(INDEX($D$55:$D$176,MATCH(Q24,$I$55:$I$176,0)),INDEX($C$55:$C$176,MATCH(Q24,$I$55:$I$176,0)) ), "" ) -> 05 - Empilhadeira - Diadema | Z24: =Q24/$C$5 -> 0.015369734 | AA24: =Z24+AA23 -> 0.83843326 | AB24: {=IFERROR(INDEX($T$55:$T$176,MATCH(1,($AP$55:$AP$176=U24)*($S$55:$S$176="Previsto"), 0) ), "")} -> 1 | AC24: {=IFERROR( INDEX($T$55:$T$176,MATCH(1,($AP$55:$AP$176=U24)*($S$55:$S$176="Real"),0)),"")} -> 1 | AD24: =IF(OR(AB24="",AC24=""),"",IF(AC24=100%,"CONCLUÍDO",IF(AC24=0,IF(AB24=0,"PROJETO NÃO INICIADO","FALTA DE ACOMPANHAMENTO"),IF(AC24>AB24,"ADIANTADO",IF(AC24=AB24,"CONFORME PLANEJADO","ATRASO"))))) -> CONCLUÍDO | AE24: 1
O25: 20 | P25: =_xlfn.XLOOKUP(U25,$C$55:$C$176,$A$55:$A$176) -> BSW | Q25: =IFERROR(LARGE($I$55:$I$176,O25)," ") -> 64554.69 | R25: =_xlfn.XLOOKUP(Q25,$I$55:$I$176,$N$55:$N$176) -> 41104.57 | S25: =_xlfn.XLOOKUP(U25,$C$55:$C$176,$J$55:$J$176) -> 46082 | T25: {=SUMPRODUCT(($C$55:$C$175=U25)*(U$54:$AI$54<=TODAY())*(ISNUMBER(U$56:$AI$176)),U$56:$AI$176)} -> 23365.017 | U25: =IFERROR( HYPERLINK( INDEX(Diadema!$D$55:$D$176, MATCH(Q25,Diadema!$I$55:$I$176,0) ), INDEX(Diadema!$C$55:$C$176, MATCH(Q25,Diadema!$I$55:$I$176,0) ) ), "" ) -> 41 - Redução de Peso Bruto do item SV001141LA | Z25: =Q25/$C$5 -> 0.014591006 | AA25: =Z25+AA24 -> 0.85302427 | AB25: {=IFERROR(INDEX($T$55:$T$176,MATCH(1,($AP$55:$AP$176=U25)*($S$55:$S$176="Previsto"), 0) ), "")} -> 1 | AC25: {=IFERROR( INDEX($T$55:$T$176,MATCH(1,($AP$55:$AP$176=U25)*($S$55:$S$176="Real"),0)),"")} -> 1 | AD25: =IF(OR(AB25="",AC25=""),"",IF(AC25=100%,"CONCLUÍDO",IF(AC25=0,IF(AB25=0,"PROJETO NÃO INICIADO","FALTA DE ACOMPANHAMENTO"),IF(AC25>AB25,"ADIANTADO",IF(AC25=AB25,"CONFORME PLANEJADO","ATRASO"))))) -> CONCLUÍDO | AE25: 1
O26: Total | Q26: =SUM(Q6:Q25) -> 3774017.9 | R26: =SUM(R6:R25) -> 2338668.1
A27: 1. KPIs ESTRATÉGICOS
A28: CATEGORIA | B28: KPI | C28: UN | D28: Frequência | E28: TIPO | F28: BASELINE 2025 | G28: META 2026 | H28: Jan | I28: P. Ofensor1 | J28: Fev | K28: P. Ofensor2 | L28: Mar | M28: P. Ofensor3 | N28: Abr | O28: P. Ofensor4 | P28: Mai | Q28: P. Ofensor5 | R28: Jun | S28: P. Ofensor6 | T28: Jul | U28: P. Ofensor7 | V28: Ago | W28: P. Ofensor8 | X28: Set | Y28: P. Ofensor9 | Z28: Out | AA28: P. Ofensor10 | AB28: Nov | AC28: P. Ofensor11 | AD28: Dez | AE28: P. Ofensor12
A29: Financeiro | B29: Margem VA | C29: % | D29: Mensal | E29: Maior Melhor ↑ | F29: 0.346 | G29: 0.361 | H29: 0.321 | I29: Matéria Prima | J29: 0.33 | K29: Matéria Prima | L29: 0.326 | M29: Matéria Prima | N29: 0.358 | O29: Matéria Prima | P29: 0.358 | Q29: Matéria Prima | R29: 0.315 | S29: Matéria Prima | T29: 0.29 | AA29: Matéria Prima
A30: Financeiro | B30: Custo de Scrap (Refugo) | C30: % | D30: Mensal | E30: Menor Melhor ↓ | F30: 0.003 | G30: 0.002 | H30: 0.00201 | I30: Rachadura | J30: 0.0065 | K30: Rachadura | L30: 0.0042 | M30: Rachadura | N30: 0.0043 | O30: Rachadura | P30: 0.0028 | Q30: Rachadura | R30: 0.0021 | S30: Rachadura | T30: 0.0034
A31: Operacional | B31: OEE Prensas Grandes (24) | C31: % | D31: Semanal | E31: Maior Melhor ↑ | F31: 0.501 | G31: 0.56 | H31: 0.4843 | I31: Falta de energia | J31: =J33*J34*J35 -> 0.51104832 | K31: Manutenção | L31: =L33*L34*L35 -> 0.66519873 | M31: Manutenção | N31: 0.7202 | O31: Manutenção | P31: 0.6949 | Q31: Manutenção | R31: 0.6828 | S31: Manutenção | T31: 0.6826 | U31: Manutenção | AA31: Manutenção
A32: Operacional | B32: Eficiência de MO Planta | C32: % | D32: Mensal | E32: Maior Melhor ↑ | F32: 0.562 | G32: 0.64 | H32: 0.551 | I32: Falta de energia | J32: 0.561 | K32: Falta de energia | L32: 0.53 | M32: Falta de OP | N32: 0.508 | O32: Falta de OP | P32: 0.523 | Q32: Falta de OP | R32: 0.595 | S32: Falta de OP | T32: 0.615 | U32: Manutenção | AA32: Manutenção
A33: Operacional | B33: Performance Prensas Grandes (24) | C33: % | D33: Semanal | E33: Maior Melhor ↑ | F33: 0.9261 | G33: 0.95 | H33: 0.8992 | I33: Falta de energia | J33: 0.8879 | K33: Manutenção | L33: 0.9508 | M33: Manutenção | N33: 0.9717 | O33: Manutenção | P33: 0.9461 | Q33: Manutenção | R33: 0.9294 | S33: Manutenção | T33: 0.9542 | U33: Manutenção | AA33: Manutenção
A34: Operacional | B34: Qualidade Prensas Grandes (24) | C34: % | D34: Semanal | E34: Maior Melhor ↑ | F34: 0.955 | G34: 0.965 | H34: 0.9995 | I34: Ferramentaria | J34: 0.9996 | K34: Ferramentaria | L34: 0.9996 | M34: Manutenção | N34: 0.9997 | O34: Manutenção | P34: 0.9997 | Q34: Manutenção | R34: 1 | S34: Manutenção | T34: 0.9994 | U34: Manutenção | AA34: Manutenção
A35: Operacional | B35: Disponibilidade Prensas Grandes (24) | C35: % | D35: Semanal | E35: Maior Melhor ↑ | F35: 0.959 | G35: 0.97 | H35: 0.5389 | I35: Ferramentaria | J35: 0.5758 | K35: Ferramentaria | L35: 0.6999 | M35: Manutenção | N35: 0.7414 | O35: Manutenção | P35: 0.7347 | Q35: Manutenção | R35: 73.47 | S35: Manutenção | T35: 0.7158 | U35: Manutenção | AA35: Manutenção
A36: Operacional | B36: MTBF (Manutenção) | C36: h | D36: Mensal | E36: Maior Melhor ↑ | F36: 13:00 | G36: 15:00 | H36: 0.625 | I36: Quebra mecânica | J36: 0.54166667 | K36: Quebra mecânica | L36: 0.875 | M36: Quebra mecânica | N36: 1.5 | O36: Quebra mecânica | P36: 1.5 | Q36: Quebra mecânica | R36: 2.0833333 | S36: Quebra mecânica
A37: Operacional | B37: MTTR (Manutenção) | C37: h | D37: Mensal | E37: Menor Melhor ↓ | F37: 0:33 | G37: 0:30 | H37: 00:15 | I37: Problema com CLP | J37: 0.048611111 | K37: Quebra mecânica | L37: 0.052083333 | M37: Quebra mecânica | N37: 0.031944444 | O37: Quebra mecânica | P37: 0.038888889 | Q37: Quebra mecânica | R37: 0.14375 | S37: Quebra mecânica
A38: Operacional | B38: Horas Extras | C38: Valor | D38: Mensal | E38: Menor Melhor ↓ | F38: 91000 | G38: 73000 | H38: 108458.31 | I38: Manutenção | J38: 81579 | K38: Manutenção | L38: 95964 | M38: Manutenção | N38: 97861 | O38: Manutenção | P38: 96508 | Q38: Manutenção | R38: 205849 | S38: Manutenção | T38: 125874 | AA38: Manutenção
A39: Operacional | B39: Acuracidade Estoque | C39: Valor | D39: Semanal | E39: Menor Melhor ↓ | F39: 458000 | G39: 358737 | H39: 29000 | I39: Apontamento incorreto | J39: 30000 | K39: Apontamento incorreto | L39: 6176 | M39: Apontamento incorreto | N39: 5680 | O39: Mat. sem saldo | P39: 213.12 | Q39: Mat. sem saldo | R39: 0 | S39: Não aplicável | T39: 2757
A40: Qualidade | B40: PPM Interno | C40: ppm | D40: Mensal | E40: Menor Melhor ↓ | F40: - | G40: 900 | H40: 60593 | I40: Rebarba | J40: 57795 | K40: Rebarba | L40: 19052 | M40: Rebarba | N40: 59710 | O40: Rebarba | P40: 60162 | Q40: Rebarba | R40: 32145 | S40: Rebarba | T40: 20426 | U40: Rebarba | AA40: Rebarba
A41: Qualidade | B41: PPM Externo | C41: ppm | D41: Mensal | E41: Menor Melhor ↓ | F41: 3347 | G41: 3000 | H41: 1 | I41: Solda irregular | J41: 476 | K41: Falta de rosca | L41: 80 | M41: Quebra de FIFO | N41: 30 | O41: Falta de componente | P41: 1 | Q41: Dimensional | R41: 0 | S41: Não aplicável | T41: 5 | U41: Falta de operação | AA41: Falta de operação
A42: Qualidade | B42: CONC | C42: % | D42: Mensal | E42: Menor Melhor ↓ | F42: 0.026 | G42: 0.016 | H42: 0.0098 | I42: Horas extras | J42: 0.0142 | K42: Refugo | L42: 0.0106 | M42: Horas extras | N42: 0.0162 | O42: Refugo | P42: 0.0142 | Q42: Frete extra | R42: 0.0174 | S42: Horas extras | T42: 0.0134 | AA42: Horas extras
A43: Qualidade | B43: Reclamações de Clientes | C43: qtd | D43: Diário | E43: Menor Melhor ↓ | F43: 49 | G43: 45 | H43: 1 | I43: Solda irregular | J43: 2 | K43: Rosca obstruída | L43: 2 | M43: Quebra de FIFO | N43: 2 | O43: Falta de componente | P43: 3 | Q43: Dimensional | R43: 0 | S43: Não aplicável | T43: 2 | U43: Falta de componente | AA43: Falta de operação
A44: Segurança | B44: Taxa de Frequência de Acidente | C44: taxa | D44: Mensal | E44: Menor Melhor ↓ | F44: 28 | G44: 26 | H44: 32 | I44: Lesão dedos | J44: 30 | K44: Lesão dedos | L44: 13 | M44: Lesão dedos | N44: 0 | O44: Lesão dedos | P44: 0 | Q44: Lesão dedos | R44: 56 | S44: Lesão dedos | T44: 14 | U44: Lesão dedos | AA44: Lesão dedos
A45: Validação Processo | B45: % Conformidade vs POC | C45: % | D45: P/ Prioridade | E45: Maior Melhor ↑ | F45: - | G45: 1 | H45: 0 | I45: Engenharia | J45: 0.1 | K45: Custos | L45: 0.13 | M45: Custos | N45: 0.13 | O45: Custos | P45: 0.16 | Q45: Engenharia | R45: 0.16 | S45: Engenharia | T45: 0.52 | U45: Custos | AA45: Custos | AG45: Departamento Suporte
A46: Sistema de Produção Delga (SPD) | B46: % Aderência às Ferramentas SPD | C46: % | D46: Semanal | E46: Maior Melhor ↑ | F46: - | G46: 1 | H46: 0.32 | I46: Logística | J46: 0.87 | K46: Logística | L46: 0.47 | M46: Produção | N46: 0.61 | O46: Produção | P46: 0.64 | Q46: Produção | R46: 1 | S46: Não aplicável | T46: 1 | AG46: Departamentos | AH46: Valor de Impacto
A47: Operacional | B47: MTBF (Ferramentaria) | C47: h | D47: Mensal | E47: Maior Melhor ↑ | F47: 80:00 | G47: 60:00 | H47: 54:25 | I47: Qualidade/dimensional | J47: 57:08 | K47: Qualidade/dimensional | L47: 74:31 | M47: Qualidade/dimensional | N47: 3.4520833 | O47: Linhas de corte/ajustes | P47: 4.7284722 | Q47: Rebarbas | R47: 3.7180556 | S47: Linhas de corte/ajustes | T47: 5.0631944 | U47: Linhas de corte/ajustes | AA47: Linhas de corte/ajustes | AG47: Compras | AH47: =SUMIF($AM$55:$AM$106,AG47,$AO$55:$AO$106) -> 0
A48: Operacional | B48: MTTR (Ferramentaria) | C48: h | D48: Mensal | E48: Menor Melhor ↓ | F48: 2:00 | G48: 1:45 | H48: 0.088194444 | I48: Qualidade/dimensional | J48: 0.058333333 | K48: Rebarbas | L48: 0.061805556 | M48: Rebarbas | N48: 0.10277778 | O48: Qualidade/dimensional | P48: 0.070833333 | Q48: Qualidade/dimensional | R48: 0.06875 | S48: Qualidade/dimensional | T48: 0.071527778 | U48: Qualidade/dimensional | AA48: Qualidade/dimensional | AG48: Vendas | AH48: =SUMIF($AM$55:$AM$106,AG48,$AO$55:$AO$106) -> 0
A49: Gerente de Planta | B49: Performance de GESTÂO | C49: R$ | D49: Mensal | E49: Maior Melhor ↑ | H49: 170000 | J49: 110000 | L49: 487000 | AG49: Orçamento | AH49: =SUMIF($AM$55:$AM$106,AG49,$AO$55:$AO$106) -> 0
AG50: Simulação | AH50: =SUMIF($AM$55:$AM$106,AG50,$AO$55:$AO$106) -> 0
AG51: Eng. Corporativa | AH51: =SUMIF($AM$55:$AM$106,AG51,$AO$55:$AO$106) -> 0
A53: 2. IDEIAS DE KAIZENS E PROJETOS DE REDUÇÃO DE CUSTOS | W53: 1° Tri | Z53: 2° Tri | AD53: 3° Tri | AH53: 4° Tri | AU53: =SUM(AU55:AU176) -> 2988619.3 | AV53: =SUM(AV55:AV176) -> 4424279.6
A54: TIPO Redução de custos Kaizen / Você resolve | B54: VA / GGF / Material Auxiliar | C54: Nome do Projeto | D54: Caminho da Evidência | E54: DESCRIÇÃO | F54: RESPONSÁVEL | G54: Inicio Mês/Ano | H54: Termino Mês/Ano | I54: Previsto (R$) | J54: Mês do 1º RETORNO | K54: Quantidade de meses com retorno | L54: Processo de entrega do projeto a custos | M54: VALIDADOR OK / NOK CUSTOS | N54: SAVING VALIDADO (R$ Valor) | O54: Status | P54: Onde esta parado | Q54: Data de liberação. | R54: % Responsabilidade Delga | S54: Previsto /Real | T54: Avanço | U54: 46023 | V54: 46054 | W54: 46082 | X54: Total 1° Tri | Y54: 46113 | Z54: 46143 | AA54: 46174 | AB54: Total 2° Tri | AC54: 46204 | AD54: 46235 | AE54: 46266 | AF54: Total 3° Tri | AG54: 46296 | AH54: 46327 | AI54: 46357 | AJ54: Total 4° Tri | AK54: Total Ano | AL54: OBS | AM54: Departamento Suporte | AN54: % de Impacto | AO54: Impacto Financeiro | AP54: proj ref. | AR54: Retorno até hoje | AU54: Unidade até Dezembro | AV54: Custos (12M)
A55: BSW | B55: VA | C55: 01 - Redução de peso bruto DA000489A | D55: \\192.168.0.20\DEPARTAMENTOS\\Engenharia\0. Kaizen Diadema\6. 2026\01 Janeiro\01 - DA000489AB -Bruno Manachini_Engenharia\01 - KAIZEN - DA000489AB_Rev00_Bruno Manachini.xlsx | E55: Peso bruto: de 4,27 Kg / peça para 4,18kg / peça | F55: B. Manachini | G55: 46027 | H55: 46087 | I55: 331600 | J55: 46082 | K55: =IF(J55="", "", 12 - MONTH(J55) + 1) -> 10 | M55: OK | N55: 160178.29 | O55: ✓ Concluído | P55: NA | Q55: NA | R55: 1 | S55: Previsto | T55: 1 | U55: =IFERROR(IF(AND(U$54>=EOMONTH($J55,-1)+1,U$54<=EOMONTH(EOMONTH($J55,-1)+1,$K55-1)),IF(NOT(ISBLANK($N55)),$N55/$K55,$I55/$K55),0),0) -> 0 | V55: =IFERROR(IF(AND(V$54>=EOMONTH($J55,-1)+1,V$54<=EOMONTH(EOMONTH($J55,-1)+1,$K55-1)),IF(NOT(ISBLANK($N55)),$N55/$K55,$I55/$K55),0),0) -> 0 | W55: =IFERROR(IF(AND(W$54>=EOMONTH($J55,-1)+1,W$54<=EOMONTH(EOMONTH($J55,-1)+1,$K55-1)),IF(NOT(ISBLANK($N55)),$N55/$K55,$I55/$K55),0),0) -> 16017.829 | X55: =SUM(U55:W55) -> 16017.829 | Y55: =IFERROR(IF(AND(Y$54>=EOMONTH($J55,-1)+1,Y$54<=EOMONTH(EOMONTH($J55,-1)+1,$K55-1)),IF(NOT(ISBLANK($N55)),$N55/$K55,$I55/$K55),0),0) -> 16017.829 | Z55: =IFERROR(IF(AND(Z$54>=EOMONTH($J55,-1)+1,Z$54<=EOMONTH(EOMONTH($J55,-1)+1,$K55-1)),IF(NOT(ISBLANK($N55)),$N55/$K55,$I55/$K55),0),0) -> 16017.829 | AA55: =IFERROR(IF(AND(AA$54>=EOMONTH($J55,-1)+1,AA$54<=EOMONTH(EOMONTH($J55,-1)+1,$K55-1)),IF(NOT(ISBLANK($N55)),$N55/$K55,$I55/$K55),0),0) -> 16017.829 | AB55: =SUM(Y55:AA55) -> 48053.487 | AC55: =IFERROR(IF(AND(AC$54>=EOMONTH($J55,-1)+1,AC$54<=EOMONTH(EOMONTH($J55,-1)+1,$K55-1)),IF(NOT(ISBLANK($N55)),$N55/$K55,$I55/$K55),0),0) -> 16017.829 | AD55: =IFERROR(IF(AND(AD$54>=EOMONTH($J55,-1)+1,AD$54<=EOMONTH(EOMONTH($J55,-1)+1,$K55-1)),IF(NOT(ISBLANK($N55)),$N55/$K55,$I55/$K55),0),0) -> 16017.829 | AE55: =IFERROR(IF(AND(AE$54>=EOMONTH($J55,-1)+1,AE$54<=EOMONTH(EOMONTH($J55,-1)+1,$K55-1)),IF(NOT(ISBLANK($N55)),$N55/$K55,$I55/$K55),0),0) -> 16017.829 | AF55: =SUM(AC55:AE55) -> 48053.487 | AG55: =IFERROR(IF(AND(AG$54>=EOMONTH($J55,-1)+1,AG$54<=EOMONTH(EOMONTH($J55,-1)+1,$K55-1)),IF(NOT(ISBLANK($N55)),$N55/$K55,$I55/$K55),0),0) -> 16017.829 | AH55: =IFERROR(IF(AND(AH$54>=EOMONTH($J55,-1)+1,AH$54<=EOMONTH(EOMONTH($J55,-1)+1,$K55-1)),IF(NOT(ISBLANK($N55)),$N55/$K55,$I55/$K55),0),0) -> 16017.829 | AI55: =IFERROR(IF(AND(AI$54>=EOMONTH($J55,-1)+1,AI$54<=EOMONTH(EOMONTH($J55,-1)+1,$K55-1)),IF(NOT(ISBLANK($N55)),$N55/$K55,$I55/$K55),0),0) -> 16017.829 | AJ55: =SUM(AG55:AI55) -> 48053.487 | AK55: =SUM(X55,AB55,AF55,AJ55) -> 160178.29 | AL55: Validado pela Carolina Reis Machado em 18/12/2025 (e-mail 11:55) - Redução de Peso Bruto do item DA000489AB (Reforço Sup. Tanque) - Revisão em 09/02 - baseado no volume Budget dos itens faturados (Mar a Dez) - considerado apenas a variação do custo peça, pois os processos embora mudem, no efeito resultado continuamos pagando a mão de obra de 2 operadores. | AO55: =N55*AN55 -> 0 | AP55: =C55 -> 01 - Redução de peso bruto DA000489A | AQ55: P | AR55: {=IF(OR(AP55="",AP55=0),"",IF(SUMPRODUCT(($C$55:$C$175=AP55)*(U$54:$AI$54<EOMONTH(TODAY(),-1)+1)*(ISNUMBER(U$55:$AI$175)),U$55:$AI$175)=0,"",SUMPRODUCT(($C$55:$C$175=AP55)*(U$54:$AI$54<EOMONTH(TODAY(),-1)+1)*(ISNUMBER(U$55:$AI$175)),U$55:$AI$175)))} -> 80089.145 | AS55: =A55 -> BSW | AU55: =IF(OR(I55="",K55=""),0,(I55/12)*K55) -> 276333.33 | AV55: =IF(OR(N55="",K55="",K55=0),0,(N55/K55)*12) -> 192213.95
S56: Real | T56: 1 | U56: 0 | W56: 12674.077 | X56: =SUM(U56:W56) -> 12674.077 | Y56: 17853.917 | Z56: 21160.198 | AA56: 19507.06 | AB56: =SUM(Y56:AA56) -> 58521.176 | AC56: 13170.019 | AF56: =SUM(AC56:AE56) -> 13170.019 | AJ56: =SUM(AG56:AI56) -> 0 | AK56: =SUM(X56,AB56,AF56,AJ56) -> 84365.272 | AL56: Projeto de kaizen número 01 de 2026. E-mail de revalidação enviado em 10/02/2026 16h12 - Carolina Rodrigues. | AP56: =C55 -> 01 - Redução de peso bruto DA000489A | AQ56: R | AR56: {=IF(OR(AP56="",AP56=0),"",IF(SUMPRODUCT(($C$55:$C$175=AP56)*($U$54:AI$54<=TODAY())*(ISNUMBER($U$56:AI$176)),$U$56:AI$176)=0,"",SUMPRODUCT(($C$55:$C$175=AP56)*($U$54:AI$54<=TODAY())*(ISNUMBER($U$56:AI$176)),$U$56:AI$176)))} -> 84365.272 | AS56: =A55 -> BSW
A57: Kaizen - Custo Evitado | B57: GGF | C57: 02 - Redução na quantidade de lâmpadas acessa, na produção | D57: \\192.168.0.20\DEPARTAMENTOS\Engenharia\0. Kaizen Diadema\6. 2026\02 Fevereiro\09 - Redução de lampadas acessas na fábrica_Eduardo Fajardo_Concluído\9 - Kaizen Redução de lampadas acessas na fábrica_Eduardo Fajardo.xlsx | E57: Redução no consumo de energia elétrica, por meio do desligamento de lâmpadas e redistribuição, sem afetar iluminamento | F57: E. Fajardo | G57: 46032 | H57: 46081 | I57: =8896.93*12 -> 106763.16 | J57: 46054 | K57: =IF(J57="", "", 12 - MONTH(J57) + 1) -> 11 | O57: ✓ Concluído | P57: NA | Q57: NA | R57: 1 | S57: Previsto | T57: 1 | U57: =IFERROR(IF(AND(U$54>=EOMONTH($J57,-1)+1,U$54<=EOMONTH(EOMONTH($J57,-1)+1,$K57-1)),IF(NOT(ISBLANK($N57)),$N57/$K57,$I57/$K57),0),0) -> 0 | V57: =IFERROR(IF(AND(V$54>=EOMONTH($J57,-1)+1,V$54<=EOMONTH(EOMONTH($J57,-1)+1,$K57-1)),IF(NOT(ISBLANK($N57)),$N57/$K57,$I57/$K57),0),0) -> 9705.7418 | W57: =IFERROR(IF(AND(W$54>=EOMONTH($J57,-1)+1,W$54<=EOMONTH(EOMONTH($J57,-1)+1,$K57-1)),IF(NOT(ISBLANK($N57)),$N57/$K57,$I57/$K57),0),0) -> 9705.7418 | X57: =SUM(U57:W57) -> 19411.484 | Y57: =IFERROR(IF(AND(Y$54>=EOMONTH($J57,-1)+1,Y$54<=EOMONTH(EOMONTH($J57,-1)+1,$K57-1)),IF(NOT(ISBLANK($N57)),$N57/$K57,$I57/$K57),0),0) -> 9705.7418 | Z57: =IFERROR(IF(AND(Z$54>=EOMONTH($J57,-1)+1,Z$54<=EOMONTH(EOMONTH($J57,-1)+1,$K57-1)),IF(NOT(ISBLANK($N57)),$N57/$K57,$I57/$K57),0),0) -> 9705.7418 | AA57: =IFERROR(IF(AND(AA$54>=EOMONTH($J57,-1)+1,AA$54<=EOMONTH(EOMONTH($J57,-1)+1,$K57-1)),IF(NOT(ISBLANK($N57)),$N57/$K57,$I57/$K57),0),0) -> 9705.7418 | AB57: =SUM(Y57:AA57) -> 29117.225 | AC57: =IFERROR(IF(AND(AC$54>=EOMONTH($J57,-1)+1,AC$54<=EOMONTH(EOMONTH($J57,-1)+1,$K57-1)),IF(NOT(ISBLANK($N57)),$N57/$K57,$I57/$K57),0),0) -> 9705.7418 | AD57: =IFERROR(IF(AND(AD$54>=EOMONTH($J57,-1)+1,AD$54<=EOMONTH(EOMONTH($J57,-1)+1,$K57-1)),IF(NOT(ISBLANK($N57)),$N57/$K57,$I57/$K57),0),0) -> 9705.7418 | AE57: =IFERROR(IF(AND(AE$54>=EOMONTH($J57,-1)+1,AE$54<=EOMONTH(EOMONTH($J57,-1)+1,$K57-1)),IF(NOT(ISBLANK($N57)),$N57/$K57,$I57/$K57),0),0) -> 9705.7418 | AF57: =SUM(AC57:AE57) -> 29117.225 | AG57: =IFERROR(IF(AND(AG$54>=EOMONTH($J57,-1)+1,AG$54<=EOMONTH(EOMONTH($J57,-1)+1,$K57-1)),IF(NOT(ISBLANK($N57)),$N57/$K57,$I57/$K57),0),0) -> 9705.7418 | AH57: =IFERROR(IF(AND(AH$54>=EOMONTH($J57,-1)+1,AH$54<=EOMONTH(EOMONTH($J57,-1)+1,$K57-1)),IF(NOT(ISBLANK($N57)),$N57/$K57,$I57/$K57),0),0) -> 9705.7418 | AI57: =IFERROR(IF(AND(AI$54>=EOMONTH($J57,-1)+1,AI$54<=EOMONTH(EOMONTH($J57,-1)+1,$K57-1)),IF(NOT(ISBLANK($N57)),$N57/$K57,$I57/$K57),0),0) -> 9705.7418 | AJ57: =SUM(AG57:AI57) -> 29117.225 | AK57: =SUM(X57,AB57,AF57,AJ57) -> 106763.16 | AL57: 100 luminárias x 180W = 18KWh. 18KWh x 24h x 6dias = 2.592 x 4,2 semanas = 10.886KWh x R$1,00 = R$ 10.886,00 por mês | AO57: =N57*AN57 -> 0 | AP57: =C57 -> 02 - Redução na quantidade de lâmpadas acessa, na produção | AQ57: P | AR57: {=IF(OR(AP57="",AP57=0),"",IF(SUMPRODUCT(($C$55:$C$175=AP57)*(U$54:$AI$54<EOMONTH(TODAY(),-1)+1)*(ISNUMBER(U$55:$AI$175)),U$55:$AI$175)=0,"",SUMPRODUCT(($C$55:$C$175=AP57)*(U$54:$AI$54<EOMONTH(TODAY(),-1)+1)*(ISNUMBER(U$55:$AI$175)),U$55:$AI$175)))} -> 58234.451 | AS57: =A57 -> Kaizen - Custo Evitado | AU57: =IF(OR(I57="",K57=""),0,(I57/12)*K57) -> 97866.23 | AV57: =IF(OR(N57="",K57="",K57=0),0,(N57/K57)*12) -> 0
S58: Real | T58: 1 | X58: =SUM(U58:W58) -> 0 | AB58: =SUM(Y58:AA58) -> 0 | AF58: =SUM(AC58:AE58) -> 0 | AJ58: =SUM(AG58:AI58) -> 0 | AK58: =SUM(X58,AB58,AF58,AJ58) -> 0 | AL58: O baseline 401,7KWh para cada 1.000 peças vendidas. Projeto de kaizen número 09 de 2026 | AP58: =C57 -> 02 - Redução na quantidade de lâmpadas acessa, na produção | AQ58: R | AR58: {=IF(OR(AP58="",AP58=0),"",IF(SUMPRODUCT(($C$55:$C$175=AP58)*($U$54:AI$54<=TODAY())*(ISNUMBER($U$56:AI$176)),$U$56:AI$176)=0,"",SUMPRODUCT(($C$55:$C$175=AP58)*($U$54:AI$54<=TODAY())*(ISNUMBER($U$56:AI$176)),$U$56:AI$176)))} | AS58: =A57 -> Kaizen - Custo Evitado
A59: Kaizen - Ganho Recorrente | B59: GGF | C59: 03 - Otimização de processo - Cavalo Marinho | D59: \\192.168.0.20\DEPARTAMENTOS\\Engenharia\0. Kaizen Diadema\6. 2026\01 Janeiro\03 - GM000463Z_GM000359AA_Robson Luz_Engenharia\3 - Eficiência_Operacional - GM000359AA_GM000463Z_REV01.xlsx | E59: Atualmente usa-se 8 MO e 4 prensas. A proposta é usar 2 prensas e 6MO | F59: R. Luz | G59: 46023 | H59: 46112 | I59: 24000.001 | J59: 46082 | K59: =IF(J59="", "", 12 - MONTH(J59) + 1) -> 10 | O59: ✓ Concluído | P59: NA | Q59: NA | R59: 1 | S59: Previsto | T59: 1 | U59: =IFERROR(IF(AND(U$54>=EOMONTH($J59,-1)+1,U$54<=EOMONTH(EOMONTH($J59,-1)+1,$K59-1)),IF(NOT(ISBLANK($N59)),$N59/$K59,$I59/$K59),0),0) -> 0 | V59: =IFERROR(IF(AND(V$54>=EOMONTH($J59,-1)+1,V$54<=EOMONTH(EOMONTH($J59,-1)+1,$K59-1)),IF(NOT(ISBLANK($N59)),$N59/$K59,$I59/$K59),0),0) -> 0 | W59: =IFERROR(IF(AND(W$54>=EOMONTH($J59,-1)+1,W$54<=EOMONTH(EOMONTH($J59,-1)+1,$K59-1)),IF(NOT(ISBLANK($N59)),$N59/$K59,$I59/$K59),0),0) -> 2400.0001 | X59: =SUM(U59:W59) -> 2400.0001 | Y59: =IFERROR(IF(AND(Y$54>=EOMONTH($J59,-1)+1,Y$54<=EOMONTH(EOMONTH($J59,-1)+1,$K59-1)),IF(NOT(ISBLANK($N59)),$N59/$K59,$I59/$K59),0),0) -> 2400.0001 | Z59: =IFERROR(IF(AND(Z$54>=EOMONTH($J59,-1)+1,Z$54<=EOMONTH(EOMONTH($J59,-1)+1,$K59-1)),IF(NOT(ISBLANK($N59)),$N59/$K59,$I59/$K59),0),0) -> 2400.0001 | AA59: =IFERROR(IF(AND(AA$54>=EOMONTH($J59,-1)+1,AA$54<=EOMONTH(EOMONTH($J59,-1)+1,$K59-1)),IF(NOT(ISBLANK($N59)),$N59/$K59,$I59/$K59),0),0) -> 2400.0001 | AB59: =SUM(Y59:AA59) -> 7200.0003 | AC59: =IFERROR(IF(AND(AC$54>=EOMONTH($J59,-1)+1,AC$54<=EOMONTH(EOMONTH($J59,-1)+1,$K59-1)),IF(NOT(ISBLANK($N59)),$N59/$K59,$I59/$K59),0),0) -> 2400.0001 | AD59: =IFERROR(IF(AND(AD$54>=EOMONTH($J59,-1)+1,AD$54<=EOMONTH(EOMONTH($J59,-1)+1,$K59-1)),IF(NOT(ISBLANK($N59)),$N59/$K59,$I59/$K59),0),0) -> 2400.0001 | AE59: =IFERROR(IF(AND(AE$54>=EOMONTH($J59,-1)+1,AE$54<=EOMONTH(EOMONTH($J59,-1)+1,$K59-1)),IF(NOT(ISBLANK($N59)),$N59/$K59,$I59/$K59),0),0) -> 2400.0001 | AF59: =SUM(AC59:AE59) -> 7200.0003 | AG59: =IFERROR(IF(AND(AG$54>=EOMONTH($J59,-1)+1,AG$54<=EOMONTH(EOMONTH($J59,-1)+1,$K59-1)),IF(NOT(ISBLANK($N59)),$N59/$K59,$I59/$K59),0),0) -> 2400.0001 | AH59: =IFERROR(IF(AND(AH$54>=EOMONTH($J59,-1)+1,AH$54<=EOMONTH(EOMONTH($J59,-1)+1,$K59-1)),IF(NOT(ISBLANK($N59)),$N59/$K59,$I59/$K59),0),0) -> 2400.0001 | AI59: =IFERROR(IF(AND(AI$54>=EOMONTH($J59,-1)+1,AI$54<=EOMONTH(EOMONTH($J59,-1)+1,$K59-1)),IF(NOT(ISBLANK($N59)),$N59/$K59,$I59/$K59),0),0) -> 2400.0001 | AJ59: =SUM(AG59:AI59) -> 7200.0003 | AK59: =SUM(X59,AB59,AF59,AJ59) -> 24000.001 | AL59: Spin 3k pçs/mês, 2 corridas mensais, 180pçs/hora. 1500/180 = 8,33h x 2 = 16,66 x 8 MO = 133,3h. 16,6h x 6MO = 100h. Logo, save de 33,3h / 166 = 0,2MO. Projeto kaizen 03 2026 | AO59: =N59*AN59 -> 0 | AP59: =C59 -> 03 - Otimização de processo - Cavalo Marinho | AQ59: P | AR59: {=IF(OR(AP59="",AP59=0),"",IF(SUMPRODUCT(($C$55:$C$175=AP59)*(U$54:$AI$54<EOMONTH(TODAY(),-1)+1)*(ISNUMBER(U$55:$AI$175)),U$55:$AI$175)=0,"",SUMPRODUCT(($C$55:$C$175=AP59)*(U$54:$AI$54<EOMONTH(TODAY(),-1)+1)*(ISNUMBER(U$55:$AI$175)),U$55:$AI$175)))} -> 12000 | AS59: =A59 -> Kaizen - Ganho Recorrente | AU59: =IF(OR(I59="",K59=""),0,(I59/12)*K59) -> 20000.001 | AV59: =IF(OR(N59="",K59="",K59=0),0,(N59/K59)*12) -> 0
S60: Real | T60: 1 | X60: =SUM(U60:W60) -> 0 | AB60: =SUM(Y60:AA60) -> 0 | AF60: =SUM(AC60:AE60) -> 0 | AJ60: =SUM(AG60:AI60) -> 0 | AK60: =SUM(X60,AB60,AF60,AJ60) -> 0 | AL60: Projeto concluído, tendo redução de 1MO somando este projeto com o projeto 4 (Pulmão) e projeto 19 (Facão). Projeto de kaizen 03 de 2026 | AP60: =C59 -> 03 - Otimização de processo - Cavalo Marinho | AQ60: R | AR60: {=IF(OR(AP60="",AP60=0),"",IF(SUMPRODUCT(($C$55:$C$175=AP60)*($U$54:AI$54<=TODAY())*(ISNUMBER($U$56:AI$176)),$U$56:AI$176)=0,"",SUMPRODUCT(($C$55:$C$175=AP60)*($U$54:AI$54<=TODAY())*(ISNUMBER($U$56:AI$176)),$U$56:AI$176)))} | AS60: =A59 -> Kaizen - Ganho Recorrente
A61: Kaizen - Ganho Recorrente | B61: GGF | C61: 04 - Otimização de processo - Pulmão | D61: \\192.168.0.20\DEPARTAMENTOS\Engenharia\0. Kaizen Diadema\5. 2025\11 Novembro - 5\52 - Kaizen Pulmão.pptx | E61: Atualmente usa-se 20 MO. A proposta é usar 18MO. | F61: J. Oliveira | G61: 46023 | H61: 46054 | I61: 42000 | J61: 46082 | K61: =IF(J61="", "", 12 - MONTH(J61) + 1) -> 10 | O61: ✓ Concluído | P61: NA | Q61: NA | R61: 1 | S61: Previsto | T61: 1 | U61: =IFERROR(IF(AND(U$54>=EOMONTH($J61,-1)+1,U$54<=EOMONTH(EOMONTH($J61,-1)+1,$K61-1)),IF(NOT(ISBLANK($N61)),$N61/$K61,$I61/$K61),0),0) -> 0 | V61: =IFERROR(IF(AND(V$54>=EOMONTH($J61,-1)+1,V$54<=EOMONTH(EOMONTH($J61,-1)+1,$K61-1)),IF(NOT(ISBLANK($N61)),$N61/$K61,$I61/$K61),0),0) -> 0 | W61: =IFERROR(IF(AND(W$54>=EOMONTH($J61,-1)+1,W$54<=EOMONTH(EOMONTH($J61,-1)+1,$K61-1)),IF(NOT(ISBLANK($N61)),$N61/$K61,$I61/$K61),0),0) -> 4200 | X61: =SUM(U61:W61) -> 4200 | Y61: =IFERROR(IF(AND(Y$54>=EOMONTH($J61,-1)+1,Y$54<=EOMONTH(EOMONTH($J61,-1)+1,$K61-1)),IF(NOT(ISBLANK($N61)),$N61/$K61,$I61/$K61),0),0) -> 4200 | Z61: =IFERROR(IF(AND(Z$54>=EOMONTH($J61,-1)+1,Z$54<=EOMONTH(EOMONTH($J61,-1)+1,$K61-1)),IF(NOT(ISBLANK($N61)),$N61/$K61,$I61/$K61),0),0) -> 4200 | AA61: =IFERROR(IF(AND(AA$54>=EOMONTH($J61,-1)+1,AA$54<=EOMONTH(EOMONTH($J61,-1)+1,$K61-1)),IF(NOT(ISBLANK($N61)),$N61/$K61,$I61/$K61),0),0) -> 4200 | AB61: =SUM(Y61:AA61) -> 12600 | AC61: =IFERROR(IF(AND(AC$54>=EOMONTH($J61,-1)+1,AC$54<=EOMONTH(EOMONTH($J61,-1)+1,$K61-1)),IF(NOT(ISBLANK($N61)),$N61/$K61,$I61/$K61),0),0) -> 4200 | AD61: =IFERROR(IF(AND(AD$54>=EOMONTH($J61,-1)+1,AD$54<=EOMONTH(EOMONTH($J61,-1)+1,$K61-1)),IF(NOT(ISBLANK($N61)),$N61/$K61,$I61/$K61),0),0) -> 4200 | AE61: =IFERROR(IF(AND(AE$54>=EOMONTH($J61,-1)+1,AE$54<=EOMONTH(EOMONTH($J61,-1)+1,$K61-1)),IF(NOT(ISBLANK($N61)),$N61/$K61,$I61/$K61),0),0) -> 4200 | AF61: =SUM(AC61:AE61) -> 12600 | AG61: =IFERROR(IF(AND(AG$54>=EOMONTH($J61,-1)+1,AG$54<=EOMONTH(EOMONTH($J61,-1)+1,$K61-1)),IF(NOT(ISBLANK($N61)),$N61/$K61,$I61/$K61),0),0) -> 4200 | AH61: =IFERROR(IF(AND(AH$54>=EOMONTH($J61,-1)+1,AH$54<=EOMONTH(EOMONTH($J61,-1)+1,$K61-1)),IF(NOT(ISBLANK($N61)),$N61/$K61,$I61/$K61),0),0) -> 4200 | AI61: =IFERROR(IF(AND(AI$54>=EOMONTH($J61,-1)+1,AI$54<=EOMONTH(EOMONTH($J61,-1)+1,$K61-1)),IF(NOT(ISBLANK($N61)),$N61/$K61,$I61/$K61),0),0) -> 4200 | AJ61: =SUM(AG61:AI61) -> 12600 | AK61: =SUM(X61,AB61,AF61,AJ61) -> 42000 | AL61: 6k pçs/mês, 4 corridas mensais, 206pçs/hora. 6000/206 = 29,12h x 20MO = 582,5h. 29,12h x 18MO = 524h. Logo, save de 58,34h / 166 = 0,35MO | AO61: =N61*AN61 -> 0 | AP61: =C61 -> 04 - Otimização de processo - Pulmão | AQ61: P | AR61: {=IF(OR(AP61="",AP61=0),"",IF(SUMPRODUCT(($C$55:$C$175=AP61)*(U$54:$AI$54<EOMONTH(TODAY(),-1)+1)*(ISNUMBER(U$55:$AI$175)),U$55:$AI$175)=0,"",SUMPRODUCT(($C$55:$C$175=AP61)*(U$54:$AI$54<EOMONTH(TODAY(),-1)+1)*(ISNUMBER(U$55:$AI$175)),U$55:$AI$175)))} -> 21000 | AS61: =A61 -> Kaizen - Ganho Recorrente | AU61: =IF(OR(I61="",K61=""),0,(I61/12)*K61) -> 35000 | AV61: =IF(OR(N61="",K61="",K61=0),0,(N61/K61)*12) -> 0
S62: Real | T62: 1 | X62: =SUM(U62:W62) -> 0 | AB62: =SUM(Y62:AA62) -> 0 | AF62: =SUM(AC62:AE62) -> 0 | AJ62: =SUM(AG62:AI62) -> 0 | AK62: =SUM(X62,AB62,AF62,AJ62) -> 0 | AL62: Projeto concluído, tendo redução de 1MO somando este projeto com o projeto 3 (Cavalo Marinho) e projeto 19 (Facão). Projeto de kaizen 52 de 2025 | AP62: =C61 -> 04 - Otimização de processo - Pulmão | AQ62: R | AR62: {=IF(OR(AP62="",AP62=0),"",IF(SUMPRODUCT(($C$55:$C$175=AP62)*($U$54:AI$54<=TODAY())*(ISNUMBER($U$56:AI$176)),$U$56:AI$176)=0,"",SUMPRODUCT(($C$55:$C$175=AP62)*($U$54:AI$54<=TODAY())*(ISNUMBER($U$56:AI$176)),$U$56:AI$176)))} | AS62: =A61 -> Kaizen - Ganho Recorrente
A63: Kaizen - Ganho Recorrente | B63: GGF | C63: 05 - Empilhadeira - Diadema | D63: \\192.168.0.20\DEPARTAMENTOS\\Engenharia\0. Kaizen Diadema\6. 2026\02 Fevereiro\17 - Redução do contrato de empilhadeiras_Eduardo Fajardo\17 - Redução de do contrato de empilhadeiras_Eduardo Fajardo.xlsx | E63: Redução de 1 empilhadeira. Eram 8 em operação, e serão 7 | F63: E. Fajardo | G63: 46027 | H63: 46078 | I63: 68000 | J63: 46082 | K63: =IF(J63="", "", 12 - MONTH(J63) + 1) -> 10 | M63: OK | N63: 56610.76 | O63: ✓ Concluído | P63: NA | Q63: NA | R63: 1 | S63: Previsto | T63: 1 | U63: =IFERROR(IF(AND(U$54>=EOMONTH($J63,-1)+1,U$54<=EOMONTH(EOMONTH($J63,-1)+1,$K63-1)),IF(NOT(ISBLANK($N63)),$N63/$K63,$I63/$K63),0),0) -> 0 | V63: =IFERROR(IF(AND(V$54>=EOMONTH($J63,-1)+1,V$54<=EOMONTH(EOMONTH($J63,-1)+1,$K63-1)),IF(NOT(ISBLANK($N63)),$N63/$K63,$I63/$K63),0),0) -> 0 | W63: =IFERROR(IF(AND(W$54>=EOMONTH($J63,-1)+1,W$54<=EOMONTH(EOMONTH($J63,-1)+1,$K63-1)),IF(NOT(ISBLANK($N63)),$N63/$K63,$I63/$K63),0),0) -> 5661.076 | X63: =SUM(U63:W63) -> 5661.076 | Y63: =IFERROR(IF(AND(Y$54>=EOMONTH($J63,-1)+1,Y$54<=EOMONTH(EOMONTH($J63,-1)+1,$K63-1)),IF(NOT(ISBLANK($N63)),$N63/$K63,$I63/$K63),0),0) -> 5661.076 | Z63: =IFERROR(IF(AND(Z$54>=EOMONTH($J63,-1)+1,Z$54<=EOMONTH(EOMONTH($J63,-1)+1,$K63-1)),IF(NOT(ISBLANK($N63)),$N63/$K63,$I63/$K63),0),0) -> 5661.076 | AA63: =IFERROR(IF(AND(AA$54>=EOMONTH($J63,-1)+1,AA$54<=EOMONTH(EOMONTH($J63,-1)+1,$K63-1)),IF(NOT(ISBLANK($N63)),$N63/$K63,$I63/$K63),0),0) -> 5661.076 | AB63: =SUM(Y63:AA63) -> 16983.228 | AC63: =IFERROR(IF(AND(AC$54>=EOMONTH($J63,-1)+1,AC$54<=EOMONTH(EOMONTH($J63,-1)+1,$K63-1)),IF(NOT(ISBLANK($N63)),$N63/$K63,$I63/$K63),0),0) -> 5661.076 | AD63: =IFERROR(IF(AND(AD$54>=EOMONTH($J63,-1)+1,AD$54<=EOMONTH(EOMONTH($J63,-1)+1,$K63-1)),IF(NOT(ISBLANK($N63)),$N63/$K63,$I63/$K63),0),0) -> 5661.076 | AE63: =IFERROR(IF(AND(AE$54>=EOMONTH($J63,-1)+1,AE$54<=EOMONTH(EOMONTH($J63,-1)+1,$K63-1)),IF(NOT(ISBLANK($N63)),$N63/$K63,$I63/$K63),0),0) -> 5661.076 | AF63: =SUM(AC63:AE63) -> 16983.228 | AG63: =IFERROR(IF(AND(AG$54>=EOMONTH($J63,-1)+1,AG$54<=EOMONTH(EOMONTH($J63,-1)+1,$K63-1)),IF(NOT(ISBLANK($N63)),$N63/$K63,$I63/$K63),0),0) -> 5661.076 | AH63: =IFERROR(IF(AND(AH$54>=EOMONTH($J63,-1)+1,AH$54<=EOMONTH(EOMONTH($J63,-1)+1,$K63-1)),IF(NOT(ISBLANK($N63)),$N63/$K63,$I63/$K63),0),0) -> 5661.076 | AI63: =IFERROR(IF(AND(AI$54>=EOMONTH($J63,-1)+1,AI$54<=EOMONTH(EOMONTH($J63,-1)+1,$K63-1)),IF(NOT(ISBLANK($N63)),$N63/$K63,$I63/$K63),0),0) -> 5661.076 | AJ63: =SUM(AG63:AI63) -> 16983.228 | AK63: =SUM(X63,AB63,AF63,AJ63) -> 56610.76 | AL63: 13/02/2026: Projeto de kaizen número 17 de 2026. E empilhaderia já foi devolvida. | AO63: =N63*AN63 -> 0 | AP63: =C63 -> 05 - Empilhadeira - Diadema | AQ63: P | AR63: {=IF(OR(AP63="",AP63=0),"",IF(SUMPRODUCT(($C$55:$C$175=AP63)*(U$54:$AI$54<EOMONTH(TODAY(),-1)+1)*(ISNUMBER(U$55:$AI$175)),U$55:$AI$175)=0,"",SUMPRODUCT(($C$55:$C$175=AP63)*(U$54:$AI$54<EOMONTH(TODAY(),-1)+1)*(ISNUMBER(U$55:$AI$175)),U$55:$AI$175)))} -> 28305.38 | AS63: =A63 -> Kaizen - Ganho Recorrente | AU63: =IF(OR(I63="",K63=""),0,(I63/12)*K63) -> 56666.667 | AV63: =IF(OR(N63="",K63="",K63=0),0,(N63/K63)*12) -> 67932.912
S64: Real | T64: 1 | V64: 0 | W64: 5146.4325 | X64: =SUM(U64:W64) -> 5146.4325 | Y64: 5146.4325 | Z64: 5146.4325 | AA64: 5146.4325 | AB64: =SUM(Y64:AA64) -> 15439.298 | AC64: 5146.4325 | AF64: =SUM(AC64:AE64) -> 5146.4325 | AJ64: =SUM(AG64:AI64) -> 0 | AK64: =SUM(X64,AB64,AF64,AJ64) -> 25732.163 | AL64: 13/02/2026: Falta validação do time de Controladoria -> Considerados valores líquidos para o resultado -> Resultado de Fevereiro ainda contemplou o valor de 8 empilhadeiras. | AP64: =C63 -> 05 - Empilhadeira - Diadema | AQ64: R | AR64: {=IF(OR(AP64="",AP64=0),"",IF(SUMPRODUCT(($C$55:$C$175=AP64)*($U$54:AI$54<=TODAY())*(ISNUMBER($U$56:AI$176)),$U$56:AI$176)=0,"",SUMPRODUCT(($C$55:$C$175=AP64)*($U$54:AI$54<=TODAY())*(ISNUMBER($U$56:AI$176)),$U$56:AI$176)))} -> 25732.163 | AS64: =A63 -> Kaizen - Ganho Recorrente
A65: Kaizen - Ganho Recorrente | B65: GGF | C65: 06 - Produtividade | D65: \\192.168.0.20\DEPARTAMENTOS\Engenharia\0. Kaizen Diadema\6. 2026\02 Fevereiro\18 - Produtividade_Aumento da eficiência para 73%_Rua 2-3-4-8_Eduardo Fajardo\18 - Produtividade_Aumento da eficiência para 73%_Rua 2-3-4-8.xlsx | E65: Aumento da eficiência da rua 2, 3 e 4 \para 73,4%. | F65: E. Fajardo | G65: 46070 | H65: 46142 | I65: 288000 | J65: 46143 | K65: =IF(J65="", "", 12 - MONTH(J65) + 1) -> 8 | M65: OK | N65: 189414 | O65: ✓ Concluído | P65: NA | Q65: NA | R65: 1 | S65: Previsto | T65: 0.96 | U65: =IFERROR(IF(AND(U$54>=EOMONTH($J65,-1)+1,U$54<=EOMONTH(EOMONTH($J65,-1)+1,$K65-1)),IF(NOT(ISBLANK($N65)),$N65/$K65,$I65/$K65),0),0) -> 0 | V65: =IFERROR(IF(AND(V$54>=EOMONTH($J65,-1)+1,V$54<=EOMONTH(EOMONTH($J65,-1)+1,$K65-1)),IF(NOT(ISBLANK($N65)),$N65/$K65,$I65/$K65),0),0) -> 0 | W65: =IFERROR(IF(AND(W$54>=EOMONTH($J65,-1)+1,W$54<=EOMONTH(EOMONTH($J65,-1)+1,$K65-1)),IF(NOT(ISBLANK($N65)),$N65/$K65,$I65/$K65),0),0) -> 0 | X65: =SUM(U65:W65) -> 0 | Y65: =IFERROR(IF(AND(Y$54>=EOMONTH($J65,-1)+1,Y$54<=EOMONTH(EOMONTH($J65,-1)+1,$K65-1)),IF(NOT(ISBLANK($N65)),$N65/$K65,$I65/$K65),0),0) -> 0 | Z65: =IFERROR(IF(AND(Z$54>=EOMONTH($J65,-1)+1,Z$54<=EOMONTH(EOMONTH($J65,-1)+1,$K65-1)),IF(NOT(ISBLANK($N65)),$N65/$K65,$I65/$K65),0),0) -> 23676.75 | AA65: =IFERROR(IF(AND(AA$54>=EOMONTH($J65,-1)+1,AA$54<=EOMONTH(EOMONTH($J65,-1)+1,$K65-1)),IF(NOT(ISBLANK($N65)),$N65/$K65,$I65/$K65),0),0) -> 23676.75 | AB65: =SUM(Y65:AA65) -> 47353.5 | AC65: =IFERROR(IF(AND(AC$54>=EOMONTH($J65,-1)+1,AC$54<=EOMONTH(EOMONTH($J65,-1)+1,$K65-1)),IF(NOT(ISBLANK($N65)),$N65/$K65,$I65/$K65),0),0) -> 23676.75 | AD65: =IFERROR(IF(AND(AD$54>=EOMONTH($J65,-1)+1,AD$54<=EOMONTH(EOMONTH($J65,-1)+1,$K65-1)),IF(NOT(ISBLANK($N65)),$N65/$K65,$I65/$K65),0),0) -> 23676.75 | AE65: =IFERROR(IF(AND(AE$54>=EOMONTH($J65,-1)+1,AE$54<=EOMONTH(EOMONTH($J65,-1)+1,$K65-1)),IF(NOT(ISBLANK($N65)),$N65/$K65,$I65/$K65),0),0) -> 23676.75 | AF65: =SUM(AC65:AE65) -> 71030.25 | AG65: =IFERROR(IF(AND(AG$54>=EOMONTH($J65,-1)+1,AG$54<=EOMONTH(EOMONTH($J65,-1)+1,$K65-1)),IF(NOT(ISBLANK($N65)),$N65/$K65,$I65/$K65),0),0) -> 23676.75 | AH65: =IFERROR(IF(AND(AH$54>=EOMONTH($J65,-1)+1,AH$54<=EOMONTH(EOMONTH($J65,-1)+1,$K65-1)),IF(NOT(ISBLANK($N65)),$N65/$K65,$I65/$K65),0),0) -> 23676.75 | AI65: =IFERROR(IF(AND(AI$54>=EOMONTH($J65,-1)+1,AI$54<=EOMONTH(EOMONTH($J65,-1)+1,$K65-1)),IF(NOT(ISBLANK($N65)),$N65/$K65,$I65/$K65),0),0) -> 23676.75 | AJ65: =SUM(AG65:AI65) -> 71030.25 | AK65: =SUM(X65,AB65,AF65,AJ65) -> 189414 | AL65: 16/02/206: Projeto de kaizen número 18 de 2026. Enviado para validação da controladoria em 02/03/2026. | AO65: =N65*AN65 -> 0 | AP65: =C65 -> 06 - Produtividade | AQ65: P | AR65: {=IF(OR(AP65="",AP65=0),"",IF(SUMPRODUCT(($C$55:$C$175=AP65)*(U$54:$AI$54<EOMONTH(TODAY(),-1)+1)*(ISNUMBER(U$55:$AI$175)),U$55:$AI$175)=0,"",SUMPRODUCT(($C$55:$C$175=AP65)*(U$54:$AI$54<EOMONTH(TODAY(),-1)+1)*(ISNUMBER(U$55:$AI$175)),U$55:$AI$175)))} -> 71030.25 | AS65: =A65 -> Kaizen - Ganho Recorrente | AU65: =IF(OR(I65="",K65=""),0,(I65/12)*K65) -> 192000 | AV65: =IF(OR(N65="",K65="",K65=0),0,(N65/K65)*12) -> 284121
S66: Real | T66: 0.98 | X66: =SUM(U66:W66) -> 0 | Z66: 17242 | AA66: 24596 | AB66: =SUM(Y66:AA66) -> 41838 | AC66: -24596 | AF66: =SUM(AC66:AE66) -> -24596 | AJ66: =SUM(AG66:AI66) -> 0 | AK66: =SUM(X66,AB66,AF66,AJ66) -> 17242 | AP66: =C65 -> 06 - Produtividade | AQ66: R | AR66: {=IF(OR(AP66="",AP66=0),"",IF(SUMPRODUCT(($C$55:$C$175=AP66)*($U$54:AI$54<=TODAY())*(ISNUMBER($U$56:AI$176)),$U$56:AI$176)=0,"",SUMPRODUCT(($C$55:$C$175=AP66)*($U$54:AI$54<=TODAY())*(ISNUMBER($U$56:AI$176)),$U$56:AI$176)))} -> 17242 | AS66: =A65 -> Kaizen - Ganho Recorrente
A67: Kaizen - Custo Evitado | B67: GGF | C67: 07 - Consumo de água | D67: \\192.168.0.20\DEPARTAMENTOS\Engenharia\0. Kaizen Diadema\6. 2026\03 Março\42 - Redução do Consumo de Água_Eduardo Fajardo\42 - Redução do Consumo de Água_Eduardo Fajardo_REV00.xlsx | E67: Instalar válvula corta ar, redução de vazão e pressão nas torneira, caça vazamentos e instalação de hidromêtro na torre Alpina. | F67: E. Fajardo | G67: 46037 | H67: 46127 | I67: 16500 | J67: 46143 | K67: =IF(J67="", "", 12 - MONTH(J67) + 1) -> 8 | O67: ✓ Concluído | P67: NA | Q67: NA | R67: 1 | S67: Previsto | T67: 1 | U67: =IFERROR(IF(AND(U$54>=EOMONTH($J67,-1)+1,U$54<=EOMONTH(EOMONTH($J67,-1)+1,$K67-1)),IF(NOT(ISBLANK($N67)),$N67/$K67,$I67/$K67),0),0) -> 0 | V67: =IFERROR(IF(AND(V$54>=EOMONTH($J67,-1)+1,V$54<=EOMONTH(EOMONTH($J67,-1)+1,$K67-1)),IF(NOT(ISBLANK($N67)),$N67/$K67,$I67/$K67),0),0) -> 0 | W67: =IFERROR(IF(AND(W$54>=EOMONTH($J67,-1)+1,W$54<=EOMONTH(EOMONTH($J67,-1)+1,$K67-1)),IF(NOT(ISBLANK($N67)),$N67/$K67,$I67/$K67),0),0) -> 0 | X67: =SUM(U67:W67) -> 0 | Y67: =IFERROR(IF(AND(Y$54>=EOMONTH($J67,-1)+1,Y$54<=EOMONTH(EOMONTH($J67,-1)+1,$K67-1)),IF(NOT(ISBLANK($N67)),$N67/$K67,$I67/$K67),0),0) -> 0 | Z67: =IFERROR(IF(AND(Z$54>=EOMONTH($J67,-1)+1,Z$54<=EOMONTH(EOMONTH($J67,-1)+1,$K67-1)),IF(NOT(ISBLANK($N67)),$N67/$K67,$I67/$K67),0),0) -> 2062.5 | AA67: =IFERROR(IF(AND(AA$54>=EOMONTH($J67,-1)+1,AA$54<=EOMONTH(EOMONTH($J67,-1)+1,$K67-1)),IF(NOT(ISBLANK($N67)),$N67/$K67,$I67/$K67),0),0) -> 2062.5 | AB67: =SUM(Y67:AA67) -> 4125 | AC67: =IFERROR(IF(AND(AC$54>=EOMONTH($J67,-1)+1,AC$54<=EOMONTH(EOMONTH($J67,-1)+1,$K67-1)),IF(NOT(ISBLANK($N67)),$N67/$K67,$I67/$K67),0),0) -> 2062.5 | AD67: =IFERROR(IF(AND(AD$54>=EOMONTH($J67,-1)+1,AD$54<=EOMONTH(EOMONTH($J67,-1)+1,$K67-1)),IF(NOT(ISBLANK($N67)),$N67/$K67,$I67/$K67),0),0) -> 2062.5 | AE67: =IFERROR(IF(AND(AE$54>=EOMONTH($J67,-1)+1,AE$54<=EOMONTH(EOMONTH($J67,-1)+1,$K67-1)),IF(NOT(ISBLANK($N67)),$N67/$K67,$I67/$K67),0),0) -> 2062.5 | AF67: =SUM(AC67:AE67) -> 6187.5 | AG67: =IFERROR(IF(AND(AG$54>=EOMONTH($J67,-1)+1,AG$54<=EOMONTH(EOMONTH($J67,-1)+1,$K67-1)),IF(NOT(ISBLANK($N67)),$N67/$K67,$I67/$K67),0),0) -> 2062.5 | AH67: =IFERROR(IF(AND(AH$54>=EOMONTH($J67,-1)+1,AH$54<=EOMONTH(EOMONTH($J67,-1)+1,$K67-1)),IF(NOT(ISBLANK($N67)),$N67/$K67,$I67/$K67),0),0) -> 2062.5 | AI67: =IFERROR(IF(AND(AI$54>=EOMONTH($J67,-1)+1,AI$54<=EOMONTH(EOMONTH($J67,-1)+1,$K67-1)),IF(NOT(ISBLANK($N67)),$N67/$K67,$I67/$K67),0),0) -> 2062.5 | AJ67: =SUM(AG67:AI67) -> 6187.5 | AK67: =SUM(X67,AB67,AF67,AJ67) -> 16500 | AL67: O baseline 570l para cada 1.000 peças vendidas. Kaizen número 42 de 2026. Enviado para validação da controladoria em 02/04/2026 | AO67: =N67*AN67 -> 0 | AP67: =C67 -> 07 - Consumo de água | AQ67: P | AR67: {=IF(OR(AP67="",AP67=0),"",IF(SUMPRODUCT(($C$55:$C$175=AP67)*(U$54:$AI$54<EOMONTH(TODAY(),-1)+1)*(ISNUMBER(U$55:$AI$175)),U$55:$AI$175)=0,"",SUMPRODUCT(($C$55:$C$175=AP67)*(U$54:$AI$54<EOMONTH(TODAY(),-1)+1)*(ISNUMBER(U$55:$AI$175)),U$55:$AI$175)))} -> 6187.5 | AS67: =A67 -> Kaizen - Custo Evitado | AU67: =IF(OR(I67="",K67=""),0,(I67/12)*K67) -> 11000 | AV67: =IF(OR(N67="",K67="",K67=0),0,(N67/K67)*12) -> 0
S68: Real | T68: 0.95 | X68: =SUM(U68:W68) -> 0 | AB68: =SUM(Y68:AA68) -> 0 | AF68: =SUM(AC68:AE68) -> 0 | AJ68: =SUM(AG68:AI68) -> 0 | AK68: =SUM(X68,AB68,AF68,AJ68) -> 0 | AP68: =C67 -> 07 - Consumo de água | AQ68: R | AR68: {=IF(OR(AP68="",AP68=0),"",IF(SUMPRODUCT(($C$55:$C$175=AP68)*($U$54:AI$54<=TODAY())*(ISNUMBER($U$56:AI$176)),$U$56:AI$176)=0,"",SUMPRODUCT(($C$55:$C$175=AP68)*($U$54:AI$54<=TODAY())*(ISNUMBER($U$56:AI$176)),$U$56:AI$176)))} | AS68: =A67 -> Kaizen - Custo Evitado
A69: BSW | B69: VA | C69: 08 - Redução de peso bruto MB002446LA / MB003670LA / MB003671LA | D69: \\192.168.0.20\DEPARTAMENTOS\\Engenharia\0. Kaizen Diadema\6. 2026\01 Janeiro\02 - MB2446LA_MB3670LA_MB3671LA_Engenharia_Bruno Manachini_Validado Pela Controladoria\02 - KAIZEN - MB2446LA_MB3670LA_MB3671LA_Rev00_Bruno Manachini.xlsx | E69: Reduzir a largura da chapa de 1150mm para 1000, resultando em maior aproveitamento. | F69: B. Manachini | G69: 46036 | H69: 46142 | I69: 44400 | J69: 46143 | K69: =IF(J69="", "", 12 - MONTH(J69) + 1) -> 8 | M69: OK | N69: 13137.64 | O69: ✓ Concluído | P69: NA | Q69: NA | R69: 0.5 | S69: Previsto | T69: 0.97 | U69: =IFERROR(IF(AND(U$54>=EOMONTH($J69,-1)+1,U$54<=EOMONTH(EOMONTH($J69,-1)+1,$K69-1)),IF(NOT(ISBLANK($N69)),$N69/$K69,$I69/$K69),0),0) -> 0 | V69: =IFERROR(IF(AND(V$54>=EOMONTH($J69,-1)+1,V$54<=EOMONTH(EOMONTH($J69,-1)+1,$K69-1)),IF(NOT(ISBLANK($N69)),$N69/$K69,$I69/$K69),0),0) -> 0 | W69: =IFERROR(IF(AND(W$54>=EOMONTH($J69,-1)+1,W$54<=EOMONTH(EOMONTH($J69,-1)+1,$K69-1)),IF(NOT(ISBLANK($N69)),$N69/$K69,$I69/$K69),0),0) -> 0 | X69: =SUM(U69:W69) -> 0 | Y69: =IFERROR(IF(AND(Y$54>=EOMONTH($J69,-1)+1,Y$54<=EOMONTH(EOMONTH($J69,-1)+1,$K69-1)),IF(NOT(ISBLANK($N69)),$N69/$K69,$I69/$K69),0),0) -> 0 | Z69: =IFERROR(IF(AND(Z$54>=EOMONTH($J69,-1)+1,Z$54<=EOMONTH(EOMONTH($J69,-1)+1,$K69-1)),IF(NOT(ISBLANK($N69)),$N69/$K69,$I69/$K69),0),0) -> 1642.205 | AA69: =IFERROR(IF(AND(AA$54>=EOMONTH($J69,-1)+1,AA$54<=EOMONTH(EOMONTH($J69,-1)+1,$K69-1)),IF(NOT(ISBLANK($N69)),$N69/$K69,$I69/$K69),0),0) -> 1642.205 | AB69: =SUM(Y69:AA69) -> 3284.41 | AC69: =IFERROR(IF(AND(AC$54>=EOMONTH($J69,-1)+1,AC$54<=EOMONTH(EOMONTH($J69,-1)+1,$K69-1)),IF(NOT(ISBLANK($N69)),$N69/$K69,$I69/$K69),0),0) -> 1642.205 | AD69: =IFERROR(IF(AND(AD$54>=EOMONTH($J69,-1)+1,AD$54<=EOMONTH(EOMONTH($J69,-1)+1,$K69-1)),IF(NOT(ISBLANK($N69)),$N69/$K69,$I69/$K69),0),0) -> 1642.205 | AE69: =IFERROR(IF(AND(AE$54>=EOMONTH($J69,-1)+1,AE$54<=EOMONTH(EOMONTH($J69,-1)+1,$K69-1)),IF(NOT(ISBLANK($N69)),$N69/$K69,$I69/$K69),0),0) -> 1642.205 | AF69: =SUM(AC69:AE69) -> 4926.615 | AG69: =IFERROR(IF(AND(AG$54>=EOMONTH($J69,-1)+1,AG$54<=EOMONTH(EOMONTH($J69,-1)+1,$K69-1)),IF(NOT(ISBLANK($N69)),$N69/$K69,$I69/$K69),0),0) -> 1642.205 | AH69: =IFERROR(IF(AND(AH$54>=EOMONTH($J69,-1)+1,AH$54<=EOMONTH(EOMONTH($J69,-1)+1,$K69-1)),IF(NOT(ISBLANK($N69)),$N69/$K69,$I69/$K69),0),0) -> 1642.205 | AI69: =IFERROR(IF(AND(AI$54>=EOMONTH($J69,-1)+1,AI$54<=EOMONTH(EOMONTH($J69,-1)+1,$K69-1)),IF(NOT(ISBLANK($N69)),$N69/$K69,$I69/$K69),0),0) -> 1642.205 | AJ69: =SUM(AG69:AI69) -> 4926.615 | AK69: =SUM(X69,AB69,AF69,AJ69) -> 13137.64 | AL69: 05/02/2026: Com base no volume médio, e redução de peso bruto para cada PN, estima-se redução de 674kg/mês. Ao preço de R$5,5/kg, a redução especulada é de R$3700/mês | AO69: =N69*AN69 -> 0 | AP69: =C69 -> 08 - Redução de peso bruto MB002446LA / MB003670LA / MB003671LA | AQ69: P | AR69: {=IF(OR(AP69="",AP69=0),"",IF(SUMPRODUCT(($C$55:$C$175=AP69)*(U$54:$AI$54<EOMONTH(TODAY(),-1)+1)*(ISNUMBER(U$55:$AI$175)),U$55:$AI$175)=0,"",SUMPRODUCT(($C$55:$C$175=AP69)*(U$54:$AI$54<EOMONTH(TODAY(),-1)+1)*(ISNUMBER(U$55:$AI$175)),U$55:$AI$175)))} -> 4926.615 | AS69: =A69 -> BSW | AU69: =IF(OR(I69="",K69=""),0,(I69/12)*K69) -> 29600 | AV69: =IF(OR(N69="",K69="",K69=0),0,(N69/K69)*12) -> 19706.46
S70: Real | T70: 0.8 | X70: =SUM(U70:W70) -> 0 | Z70: 3901.66 | AA70: 3319.7771 | AB70: =SUM(Y70:AA70) -> 7221.4371 | AC70: 3858.7815 | AF70: =SUM(AC70:AE70) -> 3858.7815 | AJ70: =SUM(AG70:AI70) -> 0 | AK70: =SUM(X70,AB70,AF70,AJ70) -> 11080.219 | AL70: Projeto de kaizen número 02 de 2026 - CUSTOS >> Validação em andamento, LT incorreta.. Não se compra Bobina desde 08/2025 e o preço calculado em Budget é menor do que o efetuado por Compras em Dez/26, gerando um penalti no Kaizen (será agendado um alinhamento entre as areas para definição das premissas, nesses casos) | AP70: =C69 -> 08 - Redução de peso bruto MB002446LA / MB003670LA / MB003671LA | AQ70: R | AR70: {=IF(OR(AP70="",AP70=0),"",IF(SUMPRODUCT(($C$55:$C$175=AP70)*($U$54:AI$54<=TODAY())*(ISNUMBER($U$56:AI$176)),$U$56:AI$176)=0,"",SUMPRODUCT(($C$55:$C$175=AP70)*($U$54:AI$54<=TODAY())*(ISNUMBER($U$56:AI$176)),$U$56:AI$176)))} -> 11080.219 | AS70: =A69 -> BSW
A71: Kaizen - Custo Evitado | B71: GGF | C71: 09 - Taxa de Esgoto | D71: \\192.168.0.20\departamentos\Engenharia\0. Kaizen Diadema\6. 2026\04 Abril\51 - Taxa de Esgoto_Eduardo Fajardo)REV00\51_Taxa de Esgoto_Eduardo Fajardo_Rev00.xlsx | E71: Redução do pagamento da conta de água/esgoto gerado na planta devido a evaporação dos processos | F71: E. Fajardo | G71: 46082 | H71: 46233 | I71: =1513*6 -> 9078 | J71: 46235 | K71: =IF(J71="", "", 12 - MONTH(J71) + 1) -> 5 | O71: ⏳ Em Execução | P71: SABESP: aguardando retorno da SABESP | Q71: 46295 | R71: 1 | S71: Previsto | T71: 0.48 | U71: =IFERROR(IF(AND(U$54>=EOMONTH($J71,-1)+1,U$54<=EOMONTH(EOMONTH($J71,-1)+1,$K71-1)),IF(NOT(ISBLANK($N71)),$N71/$K71,$I71/$K71),0),0) -> 0 | V71: =IFERROR(IF(AND(V$54>=EOMONTH($J71,-1)+1,V$54<=EOMONTH(EOMONTH($J71,-1)+1,$K71-1)),IF(NOT(ISBLANK($N71)),$N71/$K71,$I71/$K71),0),0) -> 0 | W71: =IFERROR(IF(AND(W$54>=EOMONTH($J71,-1)+1,W$54<=EOMONTH(EOMONTH($J71,-1)+1,$K71-1)),IF(NOT(ISBLANK($N71)),$N71/$K71,$I71/$K71),0),0) -> 0 | X71: =SUM(U71:W71) -> 0 | Y71: =IFERROR(IF(AND(Y$54>=EOMONTH($J71,-1)+1,Y$54<=EOMONTH(EOMONTH($J71,-1)+1,$K71-1)),IF(NOT(ISBLANK($N71)),$N71/$K71,$I71/$K71),0),0) -> 0 | Z71: =IFERROR(IF(AND(Z$54>=EOMONTH($J71,-1)+1,Z$54<=EOMONTH(EOMONTH($J71,-1)+1,$K71-1)),IF(NOT(ISBLANK($N71)),$N71/$K71,$I71/$K71),0),0) -> 0 | AA71: =IFERROR(IF(AND(AA$54>=EOMONTH($J71,-1)+1,AA$54<=EOMONTH(EOMONTH($J71,-1)+1,$K71-1)),IF(NOT(ISBLANK($N71)),$N71/$K71,$I71/$K71),0),0) -> 0 | AB71: =SUM(Y71:AA71) -> 0 | AC71: =IFERROR(IF(AND(AC$54>=EOMONTH($J71,-1)+1,AC$54<=EOMONTH(EOMONTH($J71,-1)+1,$K71-1)),IF(NOT(ISBLANK($N71)),$N71/$K71,$I71/$K71),0),0) -> 0 | AD71: =IFERROR(IF(AND(AD$54>=EOMONTH($J71,-1)+1,AD$54<=EOMONTH(EOMONTH($J71,-1)+1,$K71-1)),IF(NOT(ISBLANK($N71)),$N71/$K71,$I71/$K71),0),0) -> 1815.6 | AE71: =IFERROR(IF(AND(AE$54>=EOMONTH($J71,-1)+1,AE$54<=EOMONTH(EOMONTH($J71,-1)+1,$K71-1)),IF(NOT(ISBLANK($N71)),$N71/$K71,$I71/$K71),0),0) -> 1815.6 | AF71: =SUM(AC71:AE71) -> 3631.2 | AG71: =IFERROR(IF(AND(AG$54>=EOMONTH($J71,-1)+1,AG$54<=EOMONTH(EOMONTH($J71,-1)+1,$K71-1)),IF(NOT(ISBLANK($N71)),$N71/$K71,$I71/$K71),0),0) -> 1815.6 | AH71: =IFERROR(IF(AND(AH$54>=EOMONTH($J71,-1)+1,AH$54<=EOMONTH(EOMONTH($J71,-1)+1,$K71-1)),IF(NOT(ISBLANK($N71)),$N71/$K71,$I71/$K71),0),0) -> 1815.6 | AI71: =IFERROR(IF(AND(AI$54>=EOMONTH($J71,-1)+1,AI$54<=EOMONTH(EOMONTH($J71,-1)+1,$K71-1)),IF(NOT(ISBLANK($N71)),$N71/$K71,$I71/$K71),0),0) -> 1815.6 | AJ71: =SUM(AG71:AI71) -> 5446.8 | AK71: =SUM(X71,AB71,AF71,AJ71) -> 9078 | AL71: 29/04/2026: Projeto de kaizen númeor 51 de 2026. Enviado para validaç!ao da controladoria em 29/04/2026 | AO71: =N71*AN71 -> 0 | AP71: =C71 -> 09 - Taxa de Esgoto | AQ71: P | AR71: {=IF(OR(AP71="",AP71=0),"",IF(SUMPRODUCT(($C$55:$C$175=AP71)*(U$54:$AI$54<EOMONTH(TODAY(),-1)+1)*(ISNUMBER(U$55:$AI$175)),U$55:$AI$175)=0,"",SUMPRODUCT(($C$55:$C$175=AP71)*(U$54:$AI$54<EOMONTH(TODAY(),-1)+1)*(ISNUMBER(U$55:$AI$175)),U$55:$AI$175)))} | AS71: =A71 -> Kaizen - Custo Evitado | AU71: =IF(OR(I71="",K71=""),0,(I71/12)*K71) -> 3782.5 | AV71: =IF(OR(N71="",K71="",K71=0),0,(N71/K71)*12) -> 0
S72: Real | T72: 0.56 | X72: =SUM(U72:W72) -> 0 | AB72: =SUM(Y72:AA72) -> 0 | AF72: =SUM(AC72:AE72) -> 0 | AJ72: =SUM(AG72:AI72) -> 0 | AK72: =SUM(X72,AB72,AF72,AJ72) -> 0 | AP72: =C71 -> 09 - Taxa de Esgoto | AQ72: R | AR72: {=IF(OR(AP72="",AP72=0),"",IF(SUMPRODUCT(($C$55:$C$175=AP72)*($U$54:AI$54<=TODAY())*(ISNUMBER($U$56:AI$176)),$U$56:AI$176)=0,"",SUMPRODUCT(($C$55:$C$175=AP72)*($U$54:AI$54<=TODAY())*(ISNUMBER($U$56:AI$176)),$U$56:AI$176)))} | AS72: =A71 -> Kaizen - Custo Evitado
A73: Kaizen - Ganho Recorrente | B73: GGF | C73: 10 - Padronização de arame de solda | D73: \\192.168.0.20\DEPARTAMENTOS\\Engenharia\0. Kaizen Diadema\6. 2026\01 Janeiro\06 - Padronização de Arame de Solda_Izaias Junior_Engenharia\06_Padronização Arame de Solda. rev01_Izaias Junior.xlsx | E73: Padronizar todos os processos de solda com arame de 1,2mm | F73: I. Junior | G73: 46042 | H73: 46388 | I73: 2928 | K73: =IF(J73="", "", 12 - MONTH(J73) + 1) | O73: ⏳ Em Execução | P73: Produção: a mudança será feita no shutdown | Q73: 46374 | R73: 1 | S73: Previsto | T73: 0.97 | U73: =IFERROR(IF(AND(U$54>=EOMONTH($J73,-1)+1,U$54<=EOMONTH(EOMONTH($J73,-1)+1,$K73-1)),IF(NOT(ISBLANK($N73)),$N73/$K73,$I73/$K73),0),0) -> 0 | V73: =IFERROR(IF(AND(V$54>=EOMONTH($J73,-1)+1,V$54<=EOMONTH(EOMONTH($J73,-1)+1,$K73-1)),IF(NOT(ISBLANK($N73)),$N73/$K73,$I73/$K73),0),0) -> 0 | W73: =IFERROR(IF(AND(W$54>=EOMONTH($J73,-1)+1,W$54<=EOMONTH(EOMONTH($J73,-1)+1,$K73-1)),IF(NOT(ISBLANK($N73)),$N73/$K73,$I73/$K73),0),0) -> 0 | X73: =SUM(U73:W73) -> 0 | Y73: =IFERROR(IF(AND(Y$54>=EOMONTH($J73,-1)+1,Y$54<=EOMONTH(EOMONTH($J73,-1)+1,$K73-1)),IF(NOT(ISBLANK($N73)),$N73/$K73,$I73/$K73),0),0) -> 0 | Z73: =IFERROR(IF(AND(Z$54>=EOMONTH($J73,-1)+1,Z$54<=EOMONTH(EOMONTH($J73,-1)+1,$K73-1)),IF(NOT(ISBLANK($N73)),$N73/$K73,$I73/$K73),0),0) -> 0 | AA73: =IFERROR(IF(AND(AA$54>=EOMONTH($J73,-1)+1,AA$54<=EOMONTH(EOMONTH($J73,-1)+1,$K73-1)),IF(NOT(ISBLANK($N73)),$N73/$K73,$I73/$K73),0),0) -> 0 | AB73: =SUM(Y73:AA73) -> 0 | AC73: =IFERROR(IF(AND(AC$54>=EOMONTH($J73,-1)+1,AC$54<=EOMONTH(EOMONTH($J73,-1)+1,$K73-1)),IF(NOT(ISBLANK($N73)),$N73/$K73,$I73/$K73),0),0) -> 0 | AD73: =IFERROR(IF(AND(AD$54>=EOMONTH($J73,-1)+1,AD$54<=EOMONTH(EOMONTH($J73,-1)+1,$K73-1)),IF(NOT(ISBLANK($N73)),$N73/$K73,$I73/$K73),0),0) -> 0 | AE73: =IFERROR(IF(AND(AE$54>=EOMONTH($J73,-1)+1,AE$54<=EOMONTH(EOMONTH($J73,-1)+1,$K73-1)),IF(NOT(ISBLANK($N73)),$N73/$K73,$I73/$K73),0),0) -> 0 | AF73: =SUM(AC73:AE73) -> 0 | AG73: =IFERROR(IF(AND(AG$54>=EOMONTH($J73,-1)+1,AG$54<=EOMONTH(EOMONTH($J73,-1)+1,$K73-1)),IF(NOT(ISBLANK($N73)),$N73/$K73,$I73/$K73),0),0) -> 0 | AH73: =IFERROR(IF(AND(AH$54>=EOMONTH($J73,-1)+1,AH$54<=EOMONTH(EOMONTH($J73,-1)+1,$K73-1)),IF(NOT(ISBLANK($N73)),$N73/$K73,$I73/$K73),0),0) -> 0 | AI73: =IFERROR(IF(AND(AI$54>=EOMONTH($J73,-1)+1,AI$54<=EOMONTH(EOMONTH($J73,-1)+1,$K73-1)),IF(NOT(ISBLANK($N73)),$N73/$K73,$I73/$K73),0),0) -> 0 | AJ73: =SUM(AG73:AI73) -> 0 | AK73: =SUM(X73,AB73,AF73,AJ73) -> 0 | AL73: Projeto de kaizen número 06 de 2026 | AO73: =N73*AN73 -> 0 | AP73: =C73 -> 10 - Padronização de arame de solda | AQ73: P | AR73: {=IF(OR(AP73="",AP73=0),"",IF(SUMPRODUCT(($C$55:$C$175=AP73)*(U$54:$AI$54<EOMONTH(TODAY(),-1)+1)*(ISNUMBER(U$55:$AI$175)),U$55:$AI$175)=0,"",SUMPRODUCT(($C$55:$C$175=AP73)*(U$54:$AI$54<EOMONTH(TODAY(),-1)+1)*(ISNUMBER(U$55:$AI$175)),U$55:$AI$175)))} | AS73: =A73 -> Kaizen - Ganho Recorrente | AU73: =IF(OR(I73="",K73=""),0,(I73/12)*K73) -> 0 | AV73: =IF(OR(N73="",K73="",K73=0),0,(N73/K73)*12) -> 0
S74: Real | T74: 0.9 | X74: =SUM(U74:W74) -> 0 | AB74: =SUM(Y74:AA74) -> 0 | AF74: =SUM(AC74:AE74) -> 0 | AJ74: =SUM(AG74:AI74) -> 0 | AK74: =SUM(X74,AB74,AF74,AJ74) -> 0 | AP74: =C73 -> 10 - Padronização de arame de solda | AQ74: R | AR74: {=IF(OR(AP74="",AP74=0),"",IF(SUMPRODUCT(($C$55:$C$175=AP74)*($U$54:AI$54<=TODAY())*(ISNUMBER($U$56:AI$176)),$U$56:AI$176)=0,"",SUMPRODUCT(($C$55:$C$175=AP74)*($U$54:AI$54<=TODAY())*(ISNUMBER($U$56:AI$176)),$U$56:AI$176)))} | AS74: =A73 -> Kaizen - Ganho Recorrente
A75: Kaizen - Ganho Recorrente | B75: GGF | C75: 11 - Resourcing de DSL para DD | D75: NA | E75: Trazer 2 ferramentas da VW1131 | F75: E. Fajardo | G75: 46113 | H75: 46113 | I75: =3.071/2 -> 1.5355 | J75: 46143 | K75: 0 | M75: Não Ok | N75: 0 | O75: ✓ Concluído | P75: NA | Q75: NA | R75: 1 | S75: Previsto | T75: 1 | U75: =IFERROR(IF(AND(U$54>=EOMONTH($J75,-1)+1,U$54<=EOMONTH(EOMONTH($J75,-1)+1,$K75-1)),IF(NOT(ISBLANK($N75)),$N75/$K75,$I75/$K75),0),0) -> 0 | V75: =IFERROR(IF(AND(V$54>=EOMONTH($J75,-1)+1,V$54<=EOMONTH(EOMONTH($J75,-1)+1,$K75-1)),IF(NOT(ISBLANK($N75)),$N75/$K75,$I75/$K75),0),0) -> 0 | W75: =IFERROR(IF(AND(W$54>=EOMONTH($J75,-1)+1,W$54<=EOMONTH(EOMONTH($J75,-1)+1,$K75-1)),IF(NOT(ISBLANK($N75)),$N75/$K75,$I75/$K75),0),0) -> 0 | X75: =SUM(U75:W75) -> 0 | Y75: =IFERROR(IF(AND(Y$54>=EOMONTH($J75,-1)+1,Y$54<=EOMONTH(EOMONTH($J75,-1)+1,$K75-1)),IF(NOT(ISBLANK($N75)),$N75/$K75,$I75/$K75),0),0) -> 0 | Z75: =IFERROR(IF(AND(Z$54>=EOMONTH($J75,-1)+1,Z$54<=EOMONTH(EOMONTH($J75,-1)+1,$K75-1)),IF(NOT(ISBLANK($N75)),$N75/$K75,$I75/$K75),0),0) -> 0 | AA75: =IFERROR(IF(AND(AA$54>=EOMONTH($J75,-1)+1,AA$54<=EOMONTH(EOMONTH($J75,-1)+1,$K75-1)),IF(NOT(ISBLANK($N75)),$N75/$K75,$I75/$K75),0),0) -> 0 | AB75: =SUM(Y75:AA75) -> 0 | AC75: =IFERROR(IF(AND(AC$54>=EOMONTH($J75,-1)+1,AC$54<=EOMONTH(EOMONTH($J75,-1)+1,$K75-1)),IF(NOT(ISBLANK($N75)),$N75/$K75,$I75/$K75),0),0) -> 0 | AD75: =IFERROR(IF(AND(AD$54>=EOMONTH($J75,-1)+1,AD$54<=EOMONTH(EOMONTH($J75,-1)+1,$K75-1)),IF(NOT(ISBLANK($N75)),$N75/$K75,$I75/$K75),0),0) -> 0 | AE75: =IFERROR(IF(AND(AE$54>=EOMONTH($J75,-1)+1,AE$54<=EOMONTH(EOMONTH($J75,-1)+1,$K75-1)),IF(NOT(ISBLANK($N75)),$N75/$K75,$I75/$K75),0),0) -> 0 | AF75: =SUM(AC75:AE75) -> 0 | AG75: =IFERROR(IF(AND(AG$54>=EOMONTH($J75,-1)+1,AG$54<=EOMONTH(EOMONTH($J75,-1)+1,$K75-1)),IF(NOT(ISBLANK($N75)),$N75/$K75,$I75/$K75),0),0) -> 0 | AH75: =IFERROR(IF(AND(AH$54>=EOMONTH($J75,-1)+1,AH$54<=EOMONTH(EOMONTH($J75,-1)+1,$K75-1)),IF(NOT(ISBLANK($N75)),$N75/$K75,$I75/$K75),0),0) -> 0 | AI75: =IFERROR(IF(AND(AI$54>=EOMONTH($J75,-1)+1,AI$54<=EOMONTH(EOMONTH($J75,-1)+1,$K75-1)),IF(NOT(ISBLANK($N75)),$N75/$K75,$I75/$K75),0),0) -> 0 | AJ75: =SUM(AG75:AI75) -> 0 | AK75: =SUM(X75,AB75,AF75,AJ75) -> 0 | AO75: =N75*AN75 -> 0 | AP75: =C75 -> 11 - Resourcing de DSL para DD | AQ75: P | AR75: {=IF(OR(AP75="",AP75=0),"",IF(SUMPRODUCT(($C$55:$C$175=AP75)*(U$54:$AI$54<EOMONTH(TODAY(),-1)+1)*(ISNUMBER(U$55:$AI$175)),U$55:$AI$175)=0,"",SUMPRODUCT(($C$55:$C$175=AP75)*(U$54:$AI$54<EOMONTH(TODAY(),-1)+1)*(ISNUMBER(U$55:$AI$175)),U$55:$AI$175)))} | AS75: =A75 -> Kaizen - Ganho Recorrente | AU75: =IF(OR(I75="",K75=""),0,(I75/12)*K75) -> 0 | AV75: =IF(OR(N75="",K75="",K75=0),0,(N75/K75)*12) -> 0
S76: Real | T76: 0 | X76: =SUM(U76:W76) -> 0 | AB76: =SUM(Y76:AA76) -> 0 | AF76: =SUM(AC76:AE76) -> 0 | AJ76: =SUM(AG76:AI76) -> 0 | AK76: =SUM(X76,AB76,AF76,AJ76) -> 0 | AP76: =C75 -> 11 - Resourcing de DSL para DD | AQ76: R | AR76: {=IF(OR(AP76="",AP76=0),"",IF(SUMPRODUCT(($C$55:$C$175=AP76)*($U$54:AI$54<=TODAY())*(ISNUMBER($U$56:AI$176)),$U$56:AI$176)=0,"",SUMPRODUCT(($C$55:$C$175=AP76)*($U$54:AI$54<=TODAY())*(ISNUMBER($U$56:AI$176)),$U$56:AI$176)))} | AS76: =A75 -> Kaizen - Ganho Recorrente
A77: Kaizen - Ganho Recorrente | B77: GGF | C77: 12 - Aproveitamento de peças Obsoletas - A9583176540 | D77: \\192.168.0.20\DEPARTAMENTOS\Engenharia\0. Kaizen Diadema\5. 2025\12 Dezembro - 5\54 - Aproveitamento_de_peças_obsoletas.xlsx | E77: Transformar o PN obsoleto no PN conrrete A9583178440, por meio de corte laser 3D | F77: R. Luz | G77: 46023 | H77: 46053 | I77: 38583 | J77: 46023 | K77: 1 | M77: OK | N77: 37746.6 | O77: ✓ Concluído | P77: NA | Q77: NA | R77: 1 | S77: Previsto | T77: 1 | U77: =IFERROR(IF(AND(U$54>=EOMONTH($J77,-1)+1,U$54<=EOMONTH(EOMONTH($J77,-1)+1,$K77-1)),IF(NOT(ISBLANK($N77)),$N77/$K77,$I77/$K77),0),0) -> 37746.6 | V77: =IFERROR(IF(AND(V$54>=EOMONTH($J77,-1)+1,V$54<=EOMONTH(EOMONTH($J77,-1)+1,$K77-1)),IF(NOT(ISBLANK($N77)),$N77/$K77,$I77/$K77),0),0) -> 0 | W77: =IFERROR(IF(AND(W$54>=EOMONTH($J77,-1)+1,W$54<=EOMONTH(EOMONTH($J77,-1)+1,$K77-1)),IF(NOT(ISBLANK($N77)),$N77/$K77,$I77/$K77),0),0) -> 0 | X77: =SUM(U77:W77) -> 37746.6 | Y77: =IFERROR(IF(AND(Y$54>=EOMONTH($J77,-1)+1,Y$54<=EOMONTH(EOMONTH($J77,-1)+1,$K77-1)),IF(NOT(ISBLANK($N77)),$N77/$K77,$I77/$K77),0),0) -> 0 | Z77: =IFERROR(IF(AND(Z$54>=EOMONTH($J77,-1)+1,Z$54<=EOMONTH(EOMONTH($J77,-1)+1,$K77-1)),IF(NOT(ISBLANK($N77)),$N77/$K77,$I77/$K77),0),0) -> 0 | AA77: =IFERROR(IF(AND(AA$54>=EOMONTH($J77,-1)+1,AA$54<=EOMONTH(EOMONTH($J77,-1)+1,$K77-1)),IF(NOT(ISBLANK($N77)),$N77/$K77,$I77/$K77),0),0) -> 0 | AB77: =SUM(Y77:AA77) -> 0 | AC77: =IFERROR(IF(AND(AC$54>=EOMONTH($J77,-1)+1,AC$54<=EOMONTH(EOMONTH($J77,-1)+1,$K77-1)),IF(NOT(ISBLANK($N77)),$N77/$K77,$I77/$K77),0),0) -> 0 | AD77: =IFERROR(IF(AND(AD$54>=EOMONTH($J77,-1)+1,AD$54<=EOMONTH(EOMONTH($J77,-1)+1,$K77-1)),IF(NOT(ISBLANK($N77)),$N77/$K77,$I77/$K77),0),0) -> 0 | AE77: =IFERROR(IF(AND(AE$54>=EOMONTH($J77,-1)+1,AE$54<=EOMONTH(EOMONTH($J77,-1)+1,$K77-1)),IF(NOT(ISBLANK($N77)),$N77/$K77,$I77/$K77),0),0) -> 0 | AF77: =SUM(AC77:AE77) -> 0 | AG77: =IFERROR(IF(AND(AG$54>=EOMONTH($J77,-1)+1,AG$54<=EOMONTH(EOMONTH($J77,-1)+1,$K77-1)),IF(NOT(ISBLANK($N77)),$N77/$K77,$I77/$K77),0),0) -> 0 | AH77: =IFERROR(IF(AND(AH$54>=EOMONTH($J77,-1)+1,AH$54<=EOMONTH(EOMONTH($J77,-1)+1,$K77-1)),IF(NOT(ISBLANK($N77)),$N77/$K77,$I77/$K77),0),0) -> 0 | AI77: =IFERROR(IF(AND(AI$54>=EOMONTH($J77,-1)+1,AI$54<=EOMONTH(EOMONTH($J77,-1)+1,$K77-1)),IF(NOT(ISBLANK($N77)),$N77/$K77,$I77/$K77),0),0) -> 0 | AJ77: =SUM(AG77:AI77) -> 0 | AK77: =SUM(X77,AB77,AF77,AJ77) -> 37746.6 | AL77: 23/01/2026: Aguardando validação da controladoria. Projeto de kaizen número 54 de 2025. | AO77: =N77*AN77 -> 0 | AP77: =C77 -> 12 - Aproveitamento de peças Obsoletas - A9583176540 | AQ77: P | AR77: {=IF(OR(AP77="",AP77=0),"",IF(SUMPRODUCT(($C$55:$C$175=AP77)*(U$54:$AI$54<EOMONTH(TODAY(),-1)+1)*(ISNUMBER(U$55:$AI$175)),U$55:$AI$175)=0,"",SUMPRODUCT(($C$55:$C$175=AP77)*(U$54:$AI$54<EOMONTH(TODAY(),-1)+1)*(ISNUMBER(U$55:$AI$175)),U$55:$AI$175)))} -> 37746.6 | AS77: =A77 -> Kaizen - Ganho Recorrente | AU77: 38583 | AV77: 37746.6
S78: Real | T78: 1 | U78: =N77 -> 37746.6 | V78: 0 | W78: 0 | X78: =SUM(U78:W78) -> 37746.6 | Y78: 0 | AB78: =SUM(Y78:AA78) -> 0 | AF78: =SUM(AC78:AE78) -> 0 | AJ78: =SUM(AG78:AI78) -> 0 | AK78: =SUM(X78,AB78,AF78,AJ78) -> 37746.6 | AL78: 03/02/2026: todas as peças foram expedidas ao cliente. Todas as NF de movimentaçção foram anexadas como evidência na pasta do projeto. Fica pendente a validação da controladoria. -> Validado - o valor total foi atualizado com base no custo médio da peça no estoque em Dez/25 quando enviada ao fornecedor. | AP78: =C77 -> 12 - Aproveitamento de peças Obsoletas - A9583176540 | AQ78: R | AR78: {=IF(OR(AP78="",AP78=0),"",IF(SUMPRODUCT(($C$55:$C$175=AP78)*($U$54:AI$54<=TODAY())*(ISNUMBER($U$56:AI$176)),$U$56:AI$176)=0,"",SUMPRODUCT(($C$55:$C$175=AP78)*($U$54:AI$54<=TODAY())*(ISNUMBER($U$56:AI$176)),$U$56:AI$176)))} -> 37746.6 | AS78: =A77 -> Kaizen - Ganho Recorrente
A79: Kaizen - Ganho Recorrente | B79: GGF | C79: 13 - Redução de Componente - 4065 de 6 para 4 | D79: \\192.168.0.20\DEPARTAMENTOS\Engenharia\0. Kaizen Diadema\5. 2025\12 Dezembro - 5\53 - Redução de Componente - 4065 de 6 para 4.xlsx | E79: O item pedaleira da MBB atualmente contém 6 porcas, porém, o desenho solicita 4 porcas. | F79: R. Luz | G79: 46023 | H79: 46127 | I79: 1890 | J79: 46113 | K79: =IF(J79="", "", 12 - MONTH(J79) + 1) -> 9 | M79: Não Ok | O79: ✓ Concluído | P79: NA | Q79: NA | R79: 1 | S79: 0 | T79: 1 | U79: =IFERROR(IF(AND(U$54>=EOMONTH($J79,-1)+1,U$54<=EOMONTH(EOMONTH($J79,-1)+1,$K79-1)),IF(NOT(ISBLANK($N79)),$N79/$K79,$I79/$K79),0),0) -> 0 | V79: =IFERROR(IF(AND(V$54>=EOMONTH($J79,-1)+1,V$54<=EOMONTH(EOMONTH($J79,-1)+1,$K79-1)),IF(NOT(ISBLANK($N79)),$N79/$K79,$I79/$K79),0),0) -> 0 | W79: =IFERROR(IF(AND(W$54>=EOMONTH($J79,-1)+1,W$54<=EOMONTH(EOMONTH($J79,-1)+1,$K79-1)),IF(NOT(ISBLANK($N79)),$N79/$K79,$I79/$K79),0),0) -> 0 | X79: =SUM(U79:W79) -> 0 | Y79: =IFERROR(IF(AND(Y$54>=EOMONTH($J79,-1)+1,Y$54<=EOMONTH(EOMONTH($J79,-1)+1,$K79-1)),IF(NOT(ISBLANK($N79)),$N79/$K79,$I79/$K79),0),0) -> 210 | Z79: =IFERROR(IF(AND(Z$54>=EOMONTH($J79,-1)+1,Z$54<=EOMONTH(EOMONTH($J79,-1)+1,$K79-1)),IF(NOT(ISBLANK($N79)),$N79/$K79,$I79/$K79),0),0) -> 210 | AA79: =IFERROR(IF(AND(AA$54>=EOMONTH($J79,-1)+1,AA$54<=EOMONTH(EOMONTH($J79,-1)+1,$K79-1)),IF(NOT(ISBLANK($N79)),$N79/$K79,$I79/$K79),0),0) -> 210 | AB79: =SUM(Y79:AA79) -> 630 | AC79: =IFERROR(IF(AND(AC$54>=EOMONTH($J79,-1)+1,AC$54<=EOMONTH(EOMONTH($J79,-1)+1,$K79-1)),IF(NOT(ISBLANK($N79)),$N79/$K79,$I79/$K79),0),0) -> 210 | AD79: =IFERROR(IF(AND(AD$54>=EOMONTH($J79,-1)+1,AD$54<=EOMONTH(EOMONTH($J79,-1)+1,$K79-1)),IF(NOT(ISBLANK($N79)),$N79/$K79,$I79/$K79),0),0) -> 210 | AE79: =IFERROR(IF(AND(AE$54>=EOMONTH($J79,-1)+1,AE$54<=EOMONTH(EOMONTH($J79,-1)+1,$K79-1)),IF(NOT(ISBLANK($N79)),$N79/$K79,$I79/$K79),0),0) -> 210 | AF79: =SUM(AC79:AE79) -> 630 | AG79: =IFERROR(IF(AND(AG$54>=EOMONTH($J79,-1)+1,AG$54<=EOMONTH(EOMONTH($J79,-1)+1,$K79-1)),IF(NOT(ISBLANK($N79)),$N79/$K79,$I79/$K79),0),0) -> 210 | AH79: =IFERROR(IF(AND(AH$54>=EOMONTH($J79,-1)+1,AH$54<=EOMONTH(EOMONTH($J79,-1)+1,$K79-1)),IF(NOT(ISBLANK($N79)),$N79/$K79,$I79/$K79),0),0) -> 210 | AI79: =IFERROR(IF(AND(AI$54>=EOMONTH($J79,-1)+1,AI$54<=EOMONTH(EOMONTH($J79,-1)+1,$K79-1)),IF(NOT(ISBLANK($N79)),$N79/$K79,$I79/$K79),0),0) -> 210 | AJ79: =SUM(AG79:AI79) -> 630 | AK79: =SUM(X79,AB79,AF79,AJ79) -> 1890 | AL79: 23/01/2026: Aguardando validação da controladoria. Projeto de kaizen número 53 de 2025. | AO79: =N79*AN79 -> 0 | AP79: =C79 -> 13 - Redução de Componente - 4065 de 6 para 4 | AQ79: P | AR79: {=IF(OR(AP79="",AP79=0),"",IF(SUMPRODUCT(($C$55:$C$175=AP79)*(U$54:$AI$54<EOMONTH(TODAY(),-1)+1)*(ISNUMBER(U$55:$AI$175)),U$55:$AI$175)=0,"",SUMPRODUCT(($C$55:$C$175=AP79)*(U$54:$AI$54<EOMONTH(TODAY(),-1)+1)*(ISNUMBER(U$55:$AI$175)),U$55:$AI$175)))} -> 840 | AS79: =A79 -> Kaizen - Ganho Recorrente | AU79: =IF(OR(I79="",K79=""),0,(I79/12)*K79) -> 1417.5 | AV79: =IF(OR(N79="",K79="",K79=0),0,(N79/K79)*12) -> 0
S80: Real | T80: 1 | X80: =SUM(U80:W80) -> 0 | AB80: =SUM(Y80:AA80) -> 0 | AF80: =SUM(AC80:AE80) -> 0 | AJ80: =SUM(AG80:AI80) -> 0 | AK80: =SUM(X80,AB80,AF80,AJ80) -> 0 | AP80: =C79 -> 13 - Redução de Componente - 4065 de 6 para 4 | AQ80: R | AR80: {=IF(OR(AP80="",AP80=0),"",IF(SUMPRODUCT(($C$55:$C$175=AP80)*($U$54:AI$54<=TODAY())*(ISNUMBER($U$56:AI$176)),$U$56:AI$176)=0,"",SUMPRODUCT(($C$55:$C$175=AP80)*($U$54:AI$54<=TODAY())*(ISNUMBER($U$56:AI$176)),$U$56:AI$176)))} | AS80: =A79 -> Kaizen - Ganho Recorrente
A81: BSW | B81: VA | C81: 14 - REDUÇÃO DE MP DA000518Z (Anchieta) Código DD - VB000324Z | D81: \\192.168.0.20\DEPARTAMENTOS\\Engenharia\0. Kaizen Diadema\6. 2026\01 Janeiro\04 - DA000518Z_Thiago Cardoso_Engenharia\4 - KAIZEN DA000518Z.xlsx | E81: Aumentar a largura da bobina de 1100 para 1250, eliminando sobra (retalho). | F81: T. Cardodo | G81: 46023 | H81: 46054 | I81: 39996 | J81: 46054 | K81: =IF(J81="", "", 12 - MONTH(J81) + 1) -> 11 | M81: OK | N81: 46996.932 | O81: ✓ Concluído | P81: NA | Q81: NA | R81: 1 | S81: Previsto | T81: 1 | U81: =IFERROR(IF(AND(U$54>=EOMONTH($J81,-1)+1,U$54<=EOMONTH(EOMONTH($J81,-1)+1,$K81-1)),IF(NOT(ISBLANK($N81)),$N81/$K81,$I81/$K81),0),0) -> 0 | V81: =IFERROR(IF(AND(V$54>=EOMONTH($J81,-1)+1,V$54<=EOMONTH(EOMONTH($J81,-1)+1,$K81-1)),IF(NOT(ISBLANK($N81)),$N81/$K81,$I81/$K81),0),0) -> 4272.4484 | W81: =IFERROR(IF(AND(W$54>=EOMONTH($J81,-1)+1,W$54<=EOMONTH(EOMONTH($J81,-1)+1,$K81-1)),IF(NOT(ISBLANK($N81)),$N81/$K81,$I81/$K81),0),0) -> 4272.4484 | X81: =SUM(U81:W81) -> 8544.8967 | Y81: =IFERROR(IF(AND(Y$54>=EOMONTH($J81,-1)+1,Y$54<=EOMONTH(EOMONTH($J81,-1)+1,$K81-1)),IF(NOT(ISBLANK($N81)),$N81/$K81,$I81/$K81),0),0) -> 4272.4484 | Z81: =IFERROR(IF(AND(Z$54>=EOMONTH($J81,-1)+1,Z$54<=EOMONTH(EOMONTH($J81,-1)+1,$K81-1)),IF(NOT(ISBLANK($N81)),$N81/$K81,$I81/$K81),0),0) -> 4272.4484 | AA81: =IFERROR(IF(AND(AA$54>=EOMONTH($J81,-1)+1,AA$54<=EOMONTH(EOMONTH($J81,-1)+1,$K81-1)),IF(NOT(ISBLANK($N81)),$N81/$K81,$I81/$K81),0),0) -> 4272.4484 | AB81: =SUM(Y81:AA81) -> 12817.345 | AC81: =IFERROR(IF(AND(AC$54>=EOMONTH($J81,-1)+1,AC$54<=EOMONTH(EOMONTH($J81,-1)+1,$K81-1)),IF(NOT(ISBLANK($N81)),$N81/$K81,$I81/$K81),0),0) -> 4272.4484 | AD81: =IFERROR(IF(AND(AD$54>=EOMONTH($J81,-1)+1,AD$54<=EOMONTH(EOMONTH($J81,-1)+1,$K81-1)),IF(NOT(ISBLANK($N81)),$N81/$K81,$I81/$K81),0),0) -> 4272.4484 | AE81: =IFERROR(IF(AND(AE$54>=EOMONTH($J81,-1)+1,AE$54<=EOMONTH(EOMONTH($J81,-1)+1,$K81-1)),IF(NOT(ISBLANK($N81)),$N81/$K81,$I81/$K81),0),0) -> 4272.4484 | AF81: =SUM(AC81:AE81) -> 12817.345 | AG81: =IFERROR(IF(AND(AG$54>=EOMONTH($J81,-1)+1,AG$54<=EOMONTH(EOMONTH($J81,-1)+1,$K81-1)),IF(NOT(ISBLANK($N81)),$N81/$K81,$I81/$K81),0),0) -> 4272.4484 | AH81: =IFERROR(IF(AND(AH$54>=EOMONTH($J81,-1)+1,AH$54<=EOMONTH(EOMONTH($J81,-1)+1,$K81-1)),IF(NOT(ISBLANK($N81)),$N81/$K81,$I81/$K81),0),0) -> 4272.4484 | AI81: =IFERROR(IF(AND(AI$54>=EOMONTH($J81,-1)+1,AI$54<=EOMONTH(EOMONTH($J81,-1)+1,$K81-1)),IF(NOT(ISBLANK($N81)),$N81/$K81,$I81/$K81),0),0) -> 4272.4484 | AJ81: =SUM(AG81:AI81) -> 12817.345 | AK81: =SUM(X81,AB81,AF81,AJ81) -> 46996.932 | AL81: 23/01/2026: Aguardando validação da controladoria. Projeto de kaizen número 04 de 2026 | AO81: =N81*AN81 -> 0 | AP81: =C81 -> 14 - REDUÇÃO DE MP DA000518Z (Anchieta) Código DD - VB000324Z | AQ81: P | AR81: {=IF(OR(AP81="",AP81=0),"",IF(SUMPRODUCT(($C$55:$C$175=AP81)*(U$54:$AI$54<EOMONTH(TODAY(),-1)+1)*(ISNUMBER(U$55:$AI$175)),U$55:$AI$175)=0,"",SUMPRODUCT(($C$55:$C$175=AP81)*(U$54:$AI$54<EOMONTH(TODAY(),-1)+1)*(ISNUMBER(U$55:$AI$175)),U$55:$AI$175)))} -> 25634.69 | AS81: =A81 -> BSW | AU81: =IF(OR(I81="",K81=""),0,(I81/12)*K81) -> 36663 | AV81: =IF(OR(N81="",K81="",K81=0),0,(N81/K81)*12) -> 51269.38
S82: Real | T82: 1 | V82: 4586.7548 | W82: 4262.5124 | X82: =SUM(U82:W82) -> 8849.2673 | Y82: 6339.1211 | Z82: 4808.99 | AA82: 5355.4644 | AB82: =SUM(Y82:AA82) -> 16503.575 | AC82: 6011.2355 | AF82: =SUM(AC82:AE82) -> 6011.2355 | AJ82: =SUM(AG82:AI82) -> 0 | AK82: =SUM(X82,AB82,AF82,AJ82) -> 31364.078 | AL82: 03/02/2026: A bobina deu entrada na DELGA Diadema em 22/01/2026 NF 139598. Fica pendente a validação da controladoria. | AP82: =C81 -> 14 - REDUÇÃO DE MP DA000518Z (Anchieta) Código DD - VB000324Z | AQ82: R | AR82: {=IF(OR(AP82="",AP82=0),"",IF(SUMPRODUCT(($C$55:$C$175=AP82)*($U$54:AI$54<=TODAY())*(ISNUMBER($U$56:AI$176)),$U$56:AI$176)=0,"",SUMPRODUCT(($C$55:$C$175=AP82)*($U$54:AI$54<=TODAY())*(ISNUMBER($U$56:AI$176)),$U$56:AI$176)))} -> 31364.078 | AS82: =A81 -> BSW
A83: Kaizen - Ganho Recorrente | B83: GGF | C83: 15 - Kaizem - Botões BI - MANUAL | D83: \\192.168.0.20\DEPARTAMENTOS\\Engenharia\0. Kaizen Diadema\6. 2026\01 Janeiro\05 - Kaizem - Botões BI - MANUAL_Rafael Almeida_Ferramentaria\5 - Kaizem - Botões BI - MANUAL_Rev00.xlsx | E83: Reduzir custos de fabricação, utilizando recursos internos. | F83: S. Souza | G83: 46023 | H83: 46053 | I83: 3279.77 | J83: 46023 | K83: 1 | M83: OK | N83: 3656.94 | O83: ✓ Concluído | P83: NA | Q83: NA | R83: 1 | S83: Previsto | T83: 1 | U83: =IFERROR(IF(AND(U$54>=EOMONTH($J83,-1)+1,U$54<=EOMONTH(EOMONTH($J83,-1)+1,$K83-1)),IF(NOT(ISBLANK($N83)),$N83/$K83,$I83/$K83),0),0) -> 3656.94 | V83: =IFERROR(IF(AND(V$54>=EOMONTH($J83,-1)+1,V$54<=EOMONTH(EOMONTH($J83,-1)+1,$K83-1)),IF(NOT(ISBLANK($N83)),$N83/$K83,$I83/$K83),0),0) -> 0 | W83: =IFERROR(IF(AND(W$54>=EOMONTH($J83,-1)+1,W$54<=EOMONTH(EOMONTH($J83,-1)+1,$K83-1)),IF(NOT(ISBLANK($N83)),$N83/$K83,$I83/$K83),0),0) -> 0 | X83: =SUM(U83:W83) -> 3656.94 | Y83: =IFERROR(IF(AND(Y$54>=EOMONTH($J83,-1)+1,Y$54<=EOMONTH(EOMONTH($J83,-1)+1,$K83-1)),IF(NOT(ISBLANK($N83)),$N83/$K83,$I83/$K83),0),0) -> 0 | Z83: =IFERROR(IF(AND(Z$54>=EOMONTH($J83,-1)+1,Z$54<=EOMONTH(EOMONTH($J83,-1)+1,$K83-1)),IF(NOT(ISBLANK($N83)),$N83/$K83,$I83/$K83),0),0) -> 0 | AA83: =IFERROR(IF(AND(AA$54>=EOMONTH($J83,-1)+1,AA$54<=EOMONTH(EOMONTH($J83,-1)+1,$K83-1)),IF(NOT(ISBLANK($N83)),$N83/$K83,$I83/$K83),0),0) -> 0 | AB83: =SUM(Y83:AA83) -> 0 | AC83: =IFERROR(IF(AND(AC$54>=EOMONTH($J83,-1)+1,AC$54<=EOMONTH(EOMONTH($J83,-1)+1,$K83-1)),IF(NOT(ISBLANK($N83)),$N83/$K83,$I83/$K83),0),0) -> 0 | AD83: =IFERROR(IF(AND(AD$54>=EOMONTH($J83,-1)+1,AD$54<=EOMONTH(EOMONTH($J83,-1)+1,$K83-1)),IF(NOT(ISBLANK($N83)),$N83/$K83,$I83/$K83),0),0) -> 0 | AE83: =IFERROR(IF(AND(AE$54>=EOMONTH($J83,-1)+1,AE$54<=EOMONTH(EOMONTH($J83,-1)+1,$K83-1)),IF(NOT(ISBLANK($N83)),$N83/$K83,$I83/$K83),0),0) -> 0 | AF83: =SUM(AC83:AE83) -> 0 | AG83: =IFERROR(IF(AND(AG$54>=EOMONTH($J83,-1)+1,AG$54<=EOMONTH(EOMONTH($J83,-1)+1,$K83-1)),IF(NOT(ISBLANK($N83)),$N83/$K83,$I83/$K83),0),0) -> 0 | AH83: =IFERROR(IF(AND(AH$54>=EOMONTH($J83,-1)+1,AH$54<=EOMONTH(EOMONTH($J83,-1)+1,$K83-1)),IF(NOT(ISBLANK($N83)),$N83/$K83,$I83/$K83),0),0) -> 0 | AI83: =IFERROR(IF(AND(AI$54>=EOMONTH($J83,-1)+1,AI$54<=EOMONTH(EOMONTH($J83,-1)+1,$K83-1)),IF(NOT(ISBLANK($N83)),$N83/$K83,$I83/$K83),0),0) -> 0 | AJ83: =SUM(AG83:AI83) -> 0 | AK83: =SUM(X83,AB83,AF83,AJ83) -> 3656.94 | AL83: 23/01/2026: Aguardando validação da controladoria. Projeto de kaizen número 05 de 2026 | AO83: =N83*AN83 -> 0 | AP83: =C83 -> 15 - Kaizem - Botões BI - MANUAL | AQ83: P | AR83: {=IF(OR(AP83="",AP83=0),"",IF(SUMPRODUCT(($C$55:$C$175=AP83)*(U$54:$AI$54<EOMONTH(TODAY(),-1)+1)*(ISNUMBER(U$55:$AI$175)),U$55:$AI$175)=0,"",SUMPRODUCT(($C$55:$C$175=AP83)*(U$54:$AI$54<EOMONTH(TODAY(),-1)+1)*(ISNUMBER(U$55:$AI$175)),U$55:$AI$175)))} -> 3656.94 | AS83: =A83 -> Kaizen - Ganho Recorrente | AU83: 3279.77 | AV83: 3656.94
S84: Real | T84: 1 | U84: 3656.94 | X84: =SUM(U84:W84) -> 3656.94 | AB84: =SUM(Y84:AA84) -> 0 | AF84: =SUM(AC84:AE84) -> 0 | AJ84: =SUM(AG84:AI84) -> 0 | AK84: =SUM(X84,AB84,AF84,AJ84) -> 3656.94 | AL84: 03/02/2026: o trabalho já foi conclído. Fica pendente apenas a validação da controladoria. | AP84: =C83 -> 15 - Kaizem - Botões BI - MANUAL | AQ84: R | AR84: {=IF(OR(AP84="",AP84=0),"",IF(SUMPRODUCT(($C$55:$C$175=AP84)*($U$54:AI$54<=TODAY())*(ISNUMBER($U$56:AI$176)),$U$56:AI$176)=0,"",SUMPRODUCT(($C$55:$C$175=AP84)*($U$54:AI$54<=TODAY())*(ISNUMBER($U$56:AI$176)),$U$56:AI$176)))} -> 3656.94 | AS84: =A83 -> Kaizen - Ganho Recorrente
A85: Kaizen - Ganho Recorrente | B85: GGF | C85: 16 - Eficiência de MO na linha de Solda e Montagem | D85: \\192.168.0.20\DEPARTAMENTOS\Engenharia\0. Kaizen Diadema\6. 2026\02 Fevereiro\Kaizens 10_11_12_consolidados_ Redução de 2MOD.xlsx | E85: Foram realizados 3 kaizens na linha de solda e montagem, melhorando a eficiência de MO (redução de 2MO). Kaizens 10, 11 e 12. | F85: V. Moreira | G85: 46027 | H85: 46112 | I85: 228000 | J85: 46082 | K85: =IF(J85="", "", 12 - MONTH(J85) + 1) -> 10 | M85: OK | N85: 152396 | O85: ✓ Concluído | P85: NA | Q85: NA | R85: 1 | S85: Previsto | T85: 1 | U85: =IFERROR(IF(AND(U$54>=EOMONTH($J85,-1)+1,U$54<=EOMONTH(EOMONTH($J85,-1)+1,$K85-1)),IF(NOT(ISBLANK($N85)),$N85/$K85,$I85/$K85),0),0) -> 0 | V85: =IFERROR(IF(AND(V$54>=EOMONTH($J85,-1)+1,V$54<=EOMONTH(EOMONTH($J85,-1)+1,$K85-1)),IF(NOT(ISBLANK($N85)),$N85/$K85,$I85/$K85),0),0) -> 0 | W85: =IFERROR(IF(AND(W$54>=EOMONTH($J85,-1)+1,W$54<=EOMONTH(EOMONTH($J85,-1)+1,$K85-1)),IF(NOT(ISBLANK($N85)),$N85/$K85,$I85/$K85),0),0) -> 15239.6 | X85: =SUM(U85:W85) -> 15239.6 | Y85: =IFERROR(IF(AND(Y$54>=EOMONTH($J85,-1)+1,Y$54<=EOMONTH(EOMONTH($J85,-1)+1,$K85-1)),IF(NOT(ISBLANK($N85)),$N85/$K85,$I85/$K85),0),0) -> 15239.6 | Z85: =IFERROR(IF(AND(Z$54>=EOMONTH($J85,-1)+1,Z$54<=EOMONTH(EOMONTH($J85,-1)+1,$K85-1)),IF(NOT(ISBLANK($N85)),$N85/$K85,$I85/$K85),0),0) -> 15239.6 | AA85: =IFERROR(IF(AND(AA$54>=EOMONTH($J85,-1)+1,AA$54<=EOMONTH(EOMONTH($J85,-1)+1,$K85-1)),IF(NOT(ISBLANK($N85)),$N85/$K85,$I85/$K85),0),0) -> 15239.6 | AB85: =SUM(Y85:AA85) -> 45718.8 | AC85: =IFERROR(IF(AND(AC$54>=EOMONTH($J85,-1)+1,AC$54<=EOMONTH(EOMONTH($J85,-1)+1,$K85-1)),IF(NOT(ISBLANK($N85)),$N85/$K85,$I85/$K85),0),0) -> 15239.6 | AD85: =IFERROR(IF(AND(AD$54>=EOMONTH($J85,-1)+1,AD$54<=EOMONTH(EOMONTH($J85,-1)+1,$K85-1)),IF(NOT(ISBLANK($N85)),$N85/$K85,$I85/$K85),0),0) -> 15239.6 | AE85: =IFERROR(IF(AND(AE$54>=EOMONTH($J85,-1)+1,AE$54<=EOMONTH(EOMONTH($J85,-1)+1,$K85-1)),IF(NOT(ISBLANK($N85)),$N85/$K85,$I85/$K85),0),0) -> 15239.6 | AF85: =SUM(AC85:AE85) -> 45718.8 | AG85: =IFERROR(IF(AND(AG$54>=EOMONTH($J85,-1)+1,AG$54<=EOMONTH(EOMONTH($J85,-1)+1,$K85-1)),IF(NOT(ISBLANK($N85)),$N85/$K85,$I85/$K85),0),0) -> 15239.6 | AH85: =IFERROR(IF(AND(AH$54>=EOMONTH($J85,-1)+1,AH$54<=EOMONTH(EOMONTH($J85,-1)+1,$K85-1)),IF(NOT(ISBLANK($N85)),$N85/$K85,$I85/$K85),0),0) -> 15239.6 | AI85: =IFERROR(IF(AND(AI$54>=EOMONTH($J85,-1)+1,AI$54<=EOMONTH(EOMONTH($J85,-1)+1,$K85-1)),IF(NOT(ISBLANK($N85)),$N85/$K85,$I85/$K85),0),0) -> 15239.6 | AJ85: =SUM(AG85:AI85) -> 45718.8 | AK85: =SUM(X85,AB85,AF85,AJ85) -> 152396 | AL85: 03/02/206 - O Vitório entregou 3 kaizens que juntos reduzirão 2 MOD. Projetos de kaizen número 10, 11 e 12 de 2026 | AO85: =N85*AN85 -> 0 | AP85: =C85 -> 16 - Eficiência de MO na linha de Solda e Montagem | AQ85: P | AR85: {=IF(OR(AP85="",AP85=0),"",IF(SUMPRODUCT(($C$55:$C$175=AP85)*(U$54:$AI$54<EOMONTH(TODAY(),-1)+1)*(ISNUMBER(U$55:$AI$175)),U$55:$AI$175)=0,"",SUMPRODUCT(($C$55:$C$175=AP85)*(U$54:$AI$54<EOMONTH(TODAY(),-1)+1)*(ISNUMBER(U$55:$AI$175)),U$55:$AI$175)))} -> 76198 | AS85: =A85 -> Kaizen - Ganho Recorrente | AU85: =IF(OR(I85="",K85=""),0,(I85/12)*K85) -> 190000 | AV85: =IF(OR(N85="",K85="",K85=0),0,(N85/K85)*12) -> 182875.2
S86: Real | T86: 1 | U86: 0 | V86: 0 | W86: 8621 | X86: =SUM(U86:W86) -> 8621 | Y86: 15975 | Z86: 15975 | AA86: 15975 | AB86: =SUM(Y86:AA86) -> 47925 | AC86: 15975 | AF86: =SUM(AC86:AE86) -> 15975 | AJ86: =SUM(AG86:AI86) -> 0 | AK86: =SUM(X86,AB86,AF86,AJ86) -> 72521 | AL86: 03/02/2026 - No dia 06/02/2026 foi executado a primeira redução de MOD. | AP86: =C85 -> 16 - Eficiência de MO na linha de Solda e Montagem | AQ86: R | AR86: {=IF(OR(AP86="",AP86=0),"",IF(SUMPRODUCT(($C$55:$C$175=AP86)*($U$54:AI$54<=TODAY())*(ISNUMBER($U$56:AI$176)),$U$56:AI$176)=0,"",SUMPRODUCT(($C$55:$C$175=AP86)*($U$54:AI$54<=TODAY())*(ISNUMBER($U$56:AI$176)),$U$56:AI$176)))} -> 72521 | AS86: =A85 -> Kaizen - Ganho Recorrente
A87: BSW | B87: VA | C87: 17 - MB003537LB_MB003538LB | D87: \\192.168.0.20\DEPARTAMENTOS\\Engenharia\0. Kaizen Diadema\6. 2026\02 Fevereiro\13 - MB003537LB_MB003538LB - Bruno Manachini_Engenharia\13 - KAIZEN - MB003537LB_MB003538LB_Rev00_Bruno Manachini.xlsx | E87: De 111 peças por chapa para 160 | F87: B. Manachini | G87: 46054 | H87: 46112 | I87: 51480 | J87: 46082 | K87: =IF(J87="", "", 12 - MONTH(J87) + 1) -> 10 | M87: OK | N87: 33838.06 | O87: ✓ Concluído | P87: NA | Q87: NA | R87: 1 | S87: Previsto | T87: 1 | U87: =IFERROR(IF(AND(U$54>=EOMONTH($J87,-1)+1,U$54<=EOMONTH(EOMONTH($J87,-1)+1,$K87-1)),IF(NOT(ISBLANK($N87)),$N87/$K87,$I87/$K87),0),0) -> 0 | V87: =IFERROR(IF(AND(V$54>=EOMONTH($J87,-1)+1,V$54<=EOMONTH(EOMONTH($J87,-1)+1,$K87-1)),IF(NOT(ISBLANK($N87)),$N87/$K87,$I87/$K87),0),0) -> 0 | W87: =IFERROR(IF(AND(W$54>=EOMONTH($J87,-1)+1,W$54<=EOMONTH(EOMONTH($J87,-1)+1,$K87-1)),IF(NOT(ISBLANK($N87)),$N87/$K87,$I87/$K87),0),0) -> 3383.806 | X87: =SUM(U87:W87) -> 3383.806 | Y87: =IFERROR(IF(AND(Y$54>=EOMONTH($J87,-1)+1,Y$54<=EOMONTH(EOMONTH($J87,-1)+1,$K87-1)),IF(NOT(ISBLANK($N87)),$N87/$K87,$I87/$K87),0),0) -> 3383.806 | Z87: =IFERROR(IF(AND(Z$54>=EOMONTH($J87,-1)+1,Z$54<=EOMONTH(EOMONTH($J87,-1)+1,$K87-1)),IF(NOT(ISBLANK($N87)),$N87/$K87,$I87/$K87),0),0) -> 3383.806 | AA87: =IFERROR(IF(AND(AA$54>=EOMONTH($J87,-1)+1,AA$54<=EOMONTH(EOMONTH($J87,-1)+1,$K87-1)),IF(NOT(ISBLANK($N87)),$N87/$K87,$I87/$K87),0),0) -> 3383.806 | AB87: =SUM(Y87:AA87) -> 10151.418 | AC87: =IFERROR(IF(AND(AC$54>=EOMONTH($J87,-1)+1,AC$54<=EOMONTH(EOMONTH($J87,-1)+1,$K87-1)),IF(NOT(ISBLANK($N87)),$N87/$K87,$I87/$K87),0),0) -> 3383.806 | AD87: =IFERROR(IF(AND(AD$54>=EOMONTH($J87,-1)+1,AD$54<=EOMONTH(EOMONTH($J87,-1)+1,$K87-1)),IF(NOT(ISBLANK($N87)),$N87/$K87,$I87/$K87),0),0) -> 3383.806 | AE87: =IFERROR(IF(AND(AE$54>=EOMONTH($J87,-1)+1,AE$54<=EOMONTH(EOMONTH($J87,-1)+1,$K87-1)),IF(NOT(ISBLANK($N87)),$N87/$K87,$I87/$K87),0),0) -> 3383.806 | AF87: =SUM(AC87:AE87) -> 10151.418 | AG87: =IFERROR(IF(AND(AG$54>=EOMONTH($J87,-1)+1,AG$54<=EOMONTH(EOMONTH($J87,-1)+1,$K87-1)),IF(NOT(ISBLANK($N87)),$N87/$K87,$I87/$K87),0),0) -> 3383.806 | AH87: =IFERROR(IF(AND(AH$54>=EOMONTH($J87,-1)+1,AH$54<=EOMONTH(EOMONTH($J87,-1)+1,$K87-1)),IF(NOT(ISBLANK($N87)),$N87/$K87,$I87/$K87),0),0) -> 3383.806 | AI87: =IFERROR(IF(AND(AI$54>=EOMONTH($J87,-1)+1,AI$54<=EOMONTH(EOMONTH($J87,-1)+1,$K87-1)),IF(NOT(ISBLANK($N87)),$N87/$K87,$I87/$K87),0),0) -> 3383.806 | AJ87: =SUM(AG87:AI87) -> 10151.418 | AK87: =SUM(X87,AB87,AF87,AJ87) -> 33838.06 | AL87: 05/02/2026 - Kaizen número 13 de 2026, em processo de implementação. Programa de corte laser e LT SAP. Projeto de kaizen número 13 de 2026 | AO87: =N87*AN87 -> 0 | AP87: =C87 -> 17 - MB003537LB_MB003538LB | AQ87: P | AR87: {=IF(OR(AP87="",AP87=0),"",IF(SUMPRODUCT(($C$55:$C$175=AP87)*(U$54:$AI$54<EOMONTH(TODAY(),-1)+1)*(ISNUMBER(U$55:$AI$175)),U$55:$AI$175)=0,"",SUMPRODUCT(($C$55:$C$175=AP87)*(U$54:$AI$54<EOMONTH(TODAY(),-1)+1)*(ISNUMBER(U$55:$AI$175)),U$55:$AI$175)))} -> 16919.03 | AS87: =A87 -> BSW | AU87: =IF(OR(I87="",K87=""),0,(I87/12)*K87) -> 42900 | AV87: =IF(OR(N87="",K87="",K87=0),0,(N87/K87)*12) -> 40605.672
S88: Real | T88: 1 | W88: 3976.6832 | X88: =SUM(U88:W88) -> 3976.6832 | Y88: 3849.0581 | Z88: 2730.8879 | AA88: 3344.3587 | AB88: =SUM(Y88:AA88) -> 9924.3047 | AC88: 3190.6284 | AF88: =SUM(AC88:AE88) -> 3190.6284 | AJ88: =SUM(AG88:AI88) -> 0 | AK88: =SUM(X88,AB88,AF88,AJ88) -> 17091.616 | AL88: 05/02/2026 - Aguardando validçaão da controladoria; 10/02/2026: validado pela Carolina Rodrigues em 10/02/2026 15h31 - e-mail -> Calculado o ganho direto da MP, visto que os processos não mudam - baseado no volume Budget dos itens que são faturados (Março a Dezembro) | AP88: =C87 -> 17 - MB003537LB_MB003538LB | AQ88: R | AR88: {=IF(OR(AP88="",AP88=0),"",IF(SUMPRODUCT(($C$55:$C$175=AP88)*($U$54:AI$54<=TODAY())*(ISNUMBER($U$56:AI$176)),$U$56:AI$176)=0,"",SUMPRODUCT(($C$55:$C$175=AP88)*($U$54:AI$54<=TODAY())*(ISNUMBER($U$56:AI$176)),$U$56:AI$176)))} -> 17091.616 | AS88: =A87 -> BSW
A89: Kaizen - Ganho Recorrente | B89: Outros | C89: 18 - Venda de Embalagens, ativos e sucatas | D89: \\192.168.0.20\DEPARTAMENTOS\\Engenharia\0. Kaizen Diadema\6. 2026\03 Março\41 - VENDA DE ATIVOS OBSOLETOS_Paulo Algodoal_Produção\41 - VENDA DE ATIVOS OBSOLETOS_REV00.xlsx | E89: Fazer levantamento de embalagens obsoletas, quantificar e pesar. | F89: P. Algodoal | G89: 46058 | H89: 46147 | I89: =20000+26052 -> 46052 | K89: =IF(J89="", "", 12 - MONTH(J89) + 1) | M89: OK | N89: 46052 | O89: ✓ Concluído | P89: NA | Q89: NA | R89: 1 | S89: Previsto | T89: 1 | U89: =IFERROR(IF(AND(U$54>=EOMONTH($J89,-1)+1,U$54<=EOMONTH(EOMONTH($J89,-1)+1,$K89-1)),IF(NOT(ISBLANK($N89)),$N89/$K89,$I89/$K89),0),0) -> 0 | V89: =IFERROR(IF(AND(V$54>=EOMONTH($J89,-1)+1,V$54<=EOMONTH(EOMONTH($J89,-1)+1,$K89-1)),IF(NOT(ISBLANK($N89)),$N89/$K89,$I89/$K89),0),0) -> 0 | W89: =IFERROR(IF(AND(W$54>=EOMONTH($J89,-1)+1,W$54<=EOMONTH(EOMONTH($J89,-1)+1,$K89-1)),IF(NOT(ISBLANK($N89)),$N89/$K89,$I89/$K89),0),0) -> 0 | X89: =SUM(U89:W89) -> 0 | Y89: =IFERROR(IF(AND(Y$54>=EOMONTH($J89,-1)+1,Y$54<=EOMONTH(EOMONTH($J89,-1)+1,$K89-1)),IF(NOT(ISBLANK($N89)),$N89/$K89,$I89/$K89),0),0) -> 0 | Z89: =IFERROR(IF(AND(Z$54>=EOMONTH($J89,-1)+1,Z$54<=EOMONTH(EOMONTH($J89,-1)+1,$K89-1)),IF(NOT(ISBLANK($N89)),$N89/$K89,$I89/$K89),0),0) -> 0 | AA89: =20000+26052 -> 46052 | AB89: =SUM(Y89:AA89) -> 46052 | AC89: =IFERROR(IF(AND(AC$54>=EOMONTH($J89,-1)+1,AC$54<=EOMONTH(EOMONTH($J89,-1)+1,$K89-1)),IF(NOT(ISBLANK($N89)),$N89/$K89,$I89/$K89),0),0) -> 0 | AD89: =IFERROR(IF(AND(AD$54>=EOMONTH($J89,-1)+1,AD$54<=EOMONTH(EOMONTH($J89,-1)+1,$K89-1)),IF(NOT(ISBLANK($N89)),$N89/$K89,$I89/$K89),0),0) -> 0 | AE89: =IFERROR(IF(AND(AE$54>=EOMONTH($J89,-1)+1,AE$54<=EOMONTH(EOMONTH($J89,-1)+1,$K89-1)),IF(NOT(ISBLANK($N89)),$N89/$K89,$I89/$K89),0),0) -> 0 | AF89: =SUM(AC89:AE89) -> 0 | AG89: =IFERROR(IF(AND(AG$54>=EOMONTH($J89,-1)+1,AG$54<=EOMONTH(EOMONTH($J89,-1)+1,$K89-1)),IF(NOT(ISBLANK($N89)),$N89/$K89,$I89/$K89),0),0) -> 0 | AH89: =IFERROR(IF(AND(AH$54>=EOMONTH($J89,-1)+1,AH$54<=EOMONTH(EOMONTH($J89,-1)+1,$K89-1)),IF(NOT(ISBLANK($N89)),$N89/$K89,$I89/$K89),0),0) -> 0 | AI89: =IFERROR(IF(AND(AI$54>=EOMONTH($J89,-1)+1,AI$54<=EOMONTH(EOMONTH($J89,-1)+1,$K89-1)),IF(NOT(ISBLANK($N89)),$N89/$K89,$I89/$K89),0),0) -> 0 | AJ89: =SUM(AG89:AI89) -> 0 | AK89: =SUM(X89,AB89,AF89,AJ89) -> 46052 | AL89: 02/04/2026: Projeto de kaizen número 42 de 2026. | AO89: =N89*AN89 -> 0 | AP89: =C89 -> 18 - Venda de Embalagens, ativos e sucatas | AQ89: P | AR89: {=IF(OR(AP89="",AP89=0),"",IF(SUMPRODUCT(($C$55:$C$175=AP89)*(U$54:$AI$54<EOMONTH(TODAY(),-1)+1)*(ISNUMBER(U$55:$AI$175)),U$55:$AI$175)=0,"",SUMPRODUCT(($C$55:$C$175=AP89)*(U$54:$AI$54<EOMONTH(TODAY(),-1)+1)*(ISNUMBER(U$55:$AI$175)),U$55:$AI$175)))} -> 46052 | AS89: =A89 -> Kaizen - Ganho Recorrente | AU89: =IF(OR(I89="",K89=""),0,(I89/12)*K89) -> 0 | AV89: =IF(OR(N89="",K89="",K89=0),0,(N89/K89)*12) -> 0
S90: Real | T90: 1 | X90: =SUM(U90:W90) -> 0 | AA90: =20000+26052 -> 46052 | AB90: =SUM(Y90:AA90) -> 46052 | AF90: =SUM(AC90:AE90) -> 0 | AJ90: =SUM(AG90:AI90) -> 0 | AK90: =SUM(X90,AB90,AF90,AJ90) -> 46052 | AP90: =C89 -> 18 - Venda de Embalagens, ativos e sucatas | AQ90: R | AR90: {=IF(OR(AP90="",AP90=0),"",IF(SUMPRODUCT(($C$55:$C$175=AP90)*($U$54:AI$54<=TODAY())*(ISNUMBER($U$56:AI$176)),$U$56:AI$176)=0,"",SUMPRODUCT(($C$55:$C$175=AP90)*($U$54:AI$54<=TODAY())*(ISNUMBER($U$56:AI$176)),$U$56:AI$176)))} -> 46052 | AS90: =A89 -> Kaizen - Ganho Recorrente
A91: Kaizen - Ganho Recorrente | B91: GGF | C91: 19 - Kaizen Facão. DA000481Z - PRODUTIVIDADE | D91: \\192.168.0.20\DEPARTAMENTOS\Engenharia\0. Kaizen Diadema\6. 2026\01 Janeiro\07 - Kaizen Facão_Sebastião Gomes\7 - KAIZEN FACÃO DA000418Z_JAN 2026.xlsx | E91: Reduzir a quantidade de MO de 2 para 1 MO. | F91: S. Gomes | G91: 46027 | H91: 46081 | I91: 54000 | J91: 46082 | K91: =IF(J91="", "", 12 - MONTH(J91) + 1) -> 10 | O91: ✓ Concluído | P91: NA | Q91: NA | R91: 1 | S91: Previsto | T91: 1 | U91: =IFERROR(IF(AND(U$54>=EOMONTH($J91,-1)+1,U$54<=EOMONTH(EOMONTH($J91,-1)+1,$K91-1)),IF(NOT(ISBLANK($N91)),$N91/$K91,$I91/$K91),0),0) -> 0 | V91: =IFERROR(IF(AND(V$54>=EOMONTH($J91,-1)+1,V$54<=EOMONTH(EOMONTH($J91,-1)+1,$K91-1)),IF(NOT(ISBLANK($N91)),$N91/$K91,$I91/$K91),0),0) -> 0 | W91: =IFERROR(IF(AND(W$54>=EOMONTH($J91,-1)+1,W$54<=EOMONTH(EOMONTH($J91,-1)+1,$K91-1)),IF(NOT(ISBLANK($N91)),$N91/$K91,$I91/$K91),0),0) -> 5400 | X91: =SUM(U91:W91) -> 5400 | Y91: =IFERROR(IF(AND(Y$54>=EOMONTH($J91,-1)+1,Y$54<=EOMONTH(EOMONTH($J91,-1)+1,$K91-1)),IF(NOT(ISBLANK($N91)),$N91/$K91,$I91/$K91),0),0) -> 5400 | Z91: =IFERROR(IF(AND(Z$54>=EOMONTH($J91,-1)+1,Z$54<=EOMONTH(EOMONTH($J91,-1)+1,$K91-1)),IF(NOT(ISBLANK($N91)),$N91/$K91,$I91/$K91),0),0) -> 5400 | AA91: =IFERROR(IF(AND(AA$54>=EOMONTH($J91,-1)+1,AA$54<=EOMONTH(EOMONTH($J91,-1)+1,$K91-1)),IF(NOT(ISBLANK($N91)),$N91/$K91,$I91/$K91),0),0) -> 5400 | AB91: =SUM(Y91:AA91) -> 16200 | AC91: =IFERROR(IF(AND(AC$54>=EOMONTH($J91,-1)+1,AC$54<=EOMONTH(EOMONTH($J91,-1)+1,$K91-1)),IF(NOT(ISBLANK($N91)),$N91/$K91,$I91/$K91),0),0) -> 5400 | AD91: =IFERROR(IF(AND(AD$54>=EOMONTH($J91,-1)+1,AD$54<=EOMONTH(EOMONTH($J91,-1)+1,$K91-1)),IF(NOT(ISBLANK($N91)),$N91/$K91,$I91/$K91),0),0) -> 5400 | AE91: =IFERROR(IF(AND(AE$54>=EOMONTH($J91,-1)+1,AE$54<=EOMONTH(EOMONTH($J91,-1)+1,$K91-1)),IF(NOT(ISBLANK($N91)),$N91/$K91,$I91/$K91),0),0) -> 5400 | AF91: =SUM(AC91:AE91) -> 16200 | AG91: =IFERROR(IF(AND(AG$54>=EOMONTH($J91,-1)+1,AG$54<=EOMONTH(EOMONTH($J91,-1)+1,$K91-1)),IF(NOT(ISBLANK($N91)),$N91/$K91,$I91/$K91),0),0) -> 5400 | AH91: =IFERROR(IF(AND(AH$54>=EOMONTH($J91,-1)+1,AH$54<=EOMONTH(EOMONTH($J91,-1)+1,$K91-1)),IF(NOT(ISBLANK($N91)),$N91/$K91,$I91/$K91),0),0) -> 5400 | AI91: =IFERROR(IF(AND(AI$54>=EOMONTH($J91,-1)+1,AI$54<=EOMONTH(EOMONTH($J91,-1)+1,$K91-1)),IF(NOT(ISBLANK($N91)),$N91/$K91,$I91/$K91),0),0) -> 5400 | AJ91: =SUM(AG91:AI91) -> 16200 | AK91: =SUM(X91,AB91,AF91,AJ91) -> 54000 | AL91: 05/02/2026: Falta atualizar a LT do SAP. Projeto de kaizen número 07 de 2026. | AO91: =N91*AN91 -> 0 | AP91: =C91 -> 19 - Kaizen Facão. DA000481Z - PRODUTIVIDADE | AQ91: P | AR91: {=IF(OR(AP91="",AP91=0),"",IF(SUMPRODUCT(($C$55:$C$175=AP91)*(U$54:$AI$54<EOMONTH(TODAY(),-1)+1)*(ISNUMBER(U$55:$AI$175)),U$55:$AI$175)=0,"",SUMPRODUCT(($C$55:$C$175=AP91)*(U$54:$AI$54<EOMONTH(TODAY(),-1)+1)*(ISNUMBER(U$55:$AI$175)),U$55:$AI$175)))} -> 27000 | AS91: =A91 -> Kaizen - Ganho Recorrente | AU91: =IF(OR(I91="",K91=""),0,(I91/12)*K91) -> 45000 | AV91: =IF(OR(N91="",K91="",K91=0),0,(N91/K91)*12) -> 0
S92: Real | T92: 1 | X92: =SUM(U92:W92) -> 0 | AB92: =SUM(Y92:AA92) -> 0 | AF92: =SUM(AC92:AE92) -> 0 | AJ92: =SUM(AG92:AI92) -> 0 | AK92: =SUM(X92,AB92,AF92,AJ92) -> 0 | AL92: Projeto concluído, tendo redução de 1MO somando este projeto com o projeto 3 (Cavalo Marinho) e projeto 4 (Pulmão). | AP92: =C91 -> 19 - Kaizen Facão. DA000481Z - PRODUTIVIDADE | AQ92: R | AR92: {=IF(OR(AP92="",AP92=0),"",IF(SUMPRODUCT(($C$55:$C$175=AP92)*($U$54:AI$54<=TODAY())*(ISNUMBER($U$56:AI$176)),$U$56:AI$176)=0,"",SUMPRODUCT(($C$55:$C$175=AP92)*($U$54:AI$54<=TODAY())*(ISNUMBER($U$56:AI$176)),$U$56:AI$176)))} | AS92: =A91 -> Kaizen - Ganho Recorrente
A93: Kaizen - Ganho Recorrente | B93: Outros | C93: 20 - Redução refugo em relação ao budget | D93: \\192.168.0.20\DEPARTAMENTOS\Engenharia\0. Kaizen Diadema\6. 2026\02 Fevereiro\19 - Redução de refugo em relação ao budget_Rodrigo Larrubia\19 - Redução de refugo em relação ao budget 2026.xlsx | E93: Para budget 2026 foi previsto R$442K (36,8k/mês). Objetivo 0,2% do faturamento, logo, R$360K. | F93: R. Larrubia | G93: 46027 | H93: 46387 | K93: =IF(J93="", "", 12 - MONTH(J93) + 1) | M93: Não Ok | N93: 0 | O93: ✓ Concluído | P93: NA | Q93: NA | R93: 1 | S93: Previsto | T93: 1 | U93: =IFERROR(IF(AND(U$54>=EOMONTH($J93,-1)+1,U$54<=EOMONTH(EOMONTH($J93,-1)+1,$K93-1)),IF(NOT(ISBLANK($N93)),$N93/$K93,$I93/$K93),0),0) -> 0 | V93: =IFERROR(IF(AND(V$54>=EOMONTH($J93,-1)+1,V$54<=EOMONTH(EOMONTH($J93,-1)+1,$K93-1)),IF(NOT(ISBLANK($N93)),$N93/$K93,$I93/$K93),0),0) -> 0 | W93: =IFERROR(IF(AND(W$54>=EOMONTH($J93,-1)+1,W$54<=EOMONTH(EOMONTH($J93,-1)+1,$K93-1)),IF(NOT(ISBLANK($N93)),$N93/$K93,$I93/$K93),0),0) -> 0 | X93: =SUM(U93:W93) -> 0 | Y93: =IFERROR(IF(AND(Y$54>=EOMONTH($J93,-1)+1,Y$54<=EOMONTH(EOMONTH($J93,-1)+1,$K93-1)),IF(NOT(ISBLANK($N93)),$N93/$K93,$I93/$K93),0),0) -> 0 | Z93: =IFERROR(IF(AND(Z$54>=EOMONTH($J93,-1)+1,Z$54<=EOMONTH(EOMONTH($J93,-1)+1,$K93-1)),IF(NOT(ISBLANK($N93)),$N93/$K93,$I93/$K93),0),0) -> 0 | AA93: =IFERROR(IF(AND(AA$54>=EOMONTH($J93,-1)+1,AA$54<=EOMONTH(EOMONTH($J93,-1)+1,$K93-1)),IF(NOT(ISBLANK($N93)),$N93/$K93,$I93/$K93),0),0) -> 0 | AB93: =SUM(Y93:AA93) -> 0 | AC93: =IFERROR(IF(AND(AC$54>=EOMONTH($J93,-1)+1,AC$54<=EOMONTH(EOMONTH($J93,-1)+1,$K93-1)),IF(NOT(ISBLANK($N93)),$N93/$K93,$I93/$K93),0),0) -> 0 | AD93: =IFERROR(IF(AND(AD$54>=EOMONTH($J93,-1)+1,AD$54<=EOMONTH(EOMONTH($J93,-1)+1,$K93-1)),IF(NOT(ISBLANK($N93)),$N93/$K93,$I93/$K93),0),0) -> 0 | AE93: =IFERROR(IF(AND(AE$54>=EOMONTH($J93,-1)+1,AE$54<=EOMONTH(EOMONTH($J93,-1)+1,$K93-1)),IF(NOT(ISBLANK($N93)),$N93/$K93,$I93/$K93),0),0) -> 0 | AF93: =SUM(AC93:AE93) -> 0 | AG93: =IFERROR(IF(AND(AG$54>=EOMONTH($J93,-1)+1,AG$54<=EOMONTH(EOMONTH($J93,-1)+1,$K93-1)),IF(NOT(ISBLANK($N93)),$N93/$K93,$I93/$K93),0),0) -> 0 | AH93: =IFERROR(IF(AND(AH$54>=EOMONTH($J93,-1)+1,AH$54<=EOMONTH(EOMONTH($J93,-1)+1,$K93-1)),IF(NOT(ISBLANK($N93)),$N93/$K93,$I93/$K93),0),0) -> 0 | AI93: =IFERROR(IF(AND(AI$54>=EOMONTH($J93,-1)+1,AI$54<=EOMONTH(EOMONTH($J93,-1)+1,$K93-1)),IF(NOT(ISBLANK($N93)),$N93/$K93,$I93/$K93),0),0) -> 0 | AJ93: =SUM(AG93:AI93) -> 0 | AK93: =SUM(X93,AB93,AF93,AJ93) -> 0 | AL93: 05/02/2026 - O objetivo é reduzir o custo médio mensal previsto no budget, para um custo de 0,2% em relação ao faturamento. Budget prevê R$442K. Se ficarmos anaixo de 0,2% do faturamento (R$360K), o potencial de ganho é R$82K - VALIDADO Custos >> Projeção de ganho anual de 83.506,82 ( nessa meta o interessante é praticar sempre menos do que o Budget mensal, visto que a projeção do Budget anual já considera 0,2% do faturamento. | AO93: =N93*AN93 -> 0 | AP93: =C93 -> 20 - Redução refugo em relação ao budget | AQ93: P | AR93: {=IF(OR(AP93="",AP93=0),"",IF(SUMPRODUCT(($C$55:$C$175=AP93)*(U$54:$AI$54<EOMONTH(TODAY(),-1)+1)*(ISNUMBER(U$55:$AI$175)),U$55:$AI$175)=0,"",SUMPRODUCT(($C$55:$C$175=AP93)*(U$54:$AI$54<EOMONTH(TODAY(),-1)+1)*(ISNUMBER(U$55:$AI$175)),U$55:$AI$175)))} | AS93: =A93 -> Kaizen - Ganho Recorrente | AU93: =IF(OR(I93="",K93=""),0,(I93/12)*K93) -> 0 | AV93: =IF(OR(N93="",K93="",K93=0),0,(N93/K93)*12) -> 0
S94: Real | T94: 100 | U94: 0 | V94: 0 | X94: =SUM(U94:W94) -> 0 | AB94: =SUM(Y94:AA94) -> 0 | AF94: =SUM(AC94:AE94) -> 0 | AJ94: =SUM(AG94:AI94) -> 0 | AK94: =SUM(X94,AB94,AF94,AJ94) -> 0 | AL94: 05/02/2026: e-mail do Paulo Ribeiro confirmando o R$ do budget, 05/02/2026 16h18, salvo na pasta, como evidência. Projeto de kaizen númrero 19 de 2026 | AP94: =C93 -> 20 - Redução refugo em relação ao budget | AQ94: R | AR94: {=IF(OR(AP94="",AP94=0),"",IF(SUMPRODUCT(($C$55:$C$175=AP94)*($U$54:AI$54<=TODAY())*(ISNUMBER($U$56:AI$176)),$U$56:AI$176)=0,"",SUMPRODUCT(($C$55:$C$175=AP94)*($U$54:AI$54<=TODAY())*(ISNUMBER($U$56:AI$176)),$U$56:AI$176)))} | AS94: =A93 -> Kaizen - Ganho Recorrente
A95: BSW | B95: VA | C95: 21 - Kaizen_Redução de peso bruto MB003537LA_MB003538LA | D95: \\192.168.0.20\DEPARTAMENTOS\\Engenharia\0. Kaizen Diadema\6. 2026\02 Fevereiro\14 - MB003537LA_MB003538LA - Bruno Manachini_Engenharia\14 - KAIZEN - MB003537LA_MB003538LA_Rev00_Bruno Manachini.xlsx | E95: De 111 peças por chapa para 168 | F95: B. Manachini | G95: 46054 | H95: 46112 | I95: 56826 | J95: 46082 | K95: =IF(J95="", "", 12 - MONTH(J95) + 1) -> 10 | M95: OK | N95: 37365.58 | O95: ✓ Concluído | P95: NA | Q95: NA | R95: 1 | S95: Previsto | T95: 1 | U95: =IFERROR(IF(AND(U$54>=EOMONTH($J95,-1)+1,U$54<=EOMONTH(EOMONTH($J95,-1)+1,$K95-1)),IF(NOT(ISBLANK($N95)),$N95/$K95,$I95/$K95),0),0) -> 0 | V95: =IFERROR(IF(AND(V$54>=EOMONTH($J95,-1)+1,V$54<=EOMONTH(EOMONTH($J95,-1)+1,$K95-1)),IF(NOT(ISBLANK($N95)),$N95/$K95,$I95/$K95),0),0) -> 0 | W95: =IFERROR(IF(AND(W$54>=EOMONTH($J95,-1)+1,W$54<=EOMONTH(EOMONTH($J95,-1)+1,$K95-1)),IF(NOT(ISBLANK($N95)),$N95/$K95,$I95/$K95),0),0) -> 3736.558 | X95: =SUM(U95:W95) -> 3736.558 | Y95: =IFERROR(IF(AND(Y$54>=EOMONTH($J95,-1)+1,Y$54<=EOMONTH(EOMONTH($J95,-1)+1,$K95-1)),IF(NOT(ISBLANK($N95)),$N95/$K95,$I95/$K95),0),0) -> 3736.558 | Z95: =IFERROR(IF(AND(Z$54>=EOMONTH($J95,-1)+1,Z$54<=EOMONTH(EOMONTH($J95,-1)+1,$K95-1)),IF(NOT(ISBLANK($N95)),$N95/$K95,$I95/$K95),0),0) -> 3736.558 | AA95: =IFERROR(IF(AND(AA$54>=EOMONTH($J95,-1)+1,AA$54<=EOMONTH(EOMONTH($J95,-1)+1,$K95-1)),IF(NOT(ISBLANK($N95)),$N95/$K95,$I95/$K95),0),0) -> 3736.558 | AB95: =SUM(Y95:AA95) -> 11209.674 | AC95: =IFERROR(IF(AND(AC$54>=EOMONTH($J95,-1)+1,AC$54<=EOMONTH(EOMONTH($J95,-1)+1,$K95-1)),IF(NOT(ISBLANK($N95)),$N95/$K95,$I95/$K95),0),0) -> 3736.558 | AD95: =IFERROR(IF(AND(AD$54>=EOMONTH($J95,-1)+1,AD$54<=EOMONTH(EOMONTH($J95,-1)+1,$K95-1)),IF(NOT(ISBLANK($N95)),$N95/$K95,$I95/$K95),0),0) -> 3736.558 | AE95: =IFERROR(IF(AND(AE$54>=EOMONTH($J95,-1)+1,AE$54<=EOMONTH(EOMONTH($J95,-1)+1,$K95-1)),IF(NOT(ISBLANK($N95)),$N95/$K95,$I95/$K95),0),0) -> 3736.558 | AF95: =SUM(AC95:AE95) -> 11209.674 | AG95: =IFERROR(IF(AND(AG$54>=EOMONTH($J95,-1)+1,AG$54<=EOMONTH(EOMONTH($J95,-1)+1,$K95-1)),IF(NOT(ISBLANK($N95)),$N95/$K95,$I95/$K95),0),0) -> 3736.558 | AH95: =IFERROR(IF(AND(AH$54>=EOMONTH($J95,-1)+1,AH$54<=EOMONTH(EOMONTH($J95,-1)+1,$K95-1)),IF(NOT(ISBLANK($N95)),$N95/$K95,$I95/$K95),0),0) -> 3736.558 | AI95: =IFERROR(IF(AND(AI$54>=EOMONTH($J95,-1)+1,AI$54<=EOMONTH(EOMONTH($J95,-1)+1,$K95-1)),IF(NOT(ISBLANK($N95)),$N95/$K95,$I95/$K95),0),0) -> 3736.558 | AJ95: =SUM(AG95:AI95) -> 11209.674 | AK95: =SUM(X95,AB95,AF95,AJ95) -> 37365.58 | AL95: 05/02/2026 - Projeto de kaizen número 14 de 2026, em processo de implementação. Programa de corte laser e LT SAP. | AO95: =N95*AN95 -> 0 | AP95: =C95 -> 21 - Kaizen_Redução de peso bruto MB003537LA_MB003538LA | AQ95: P | AR95: {=IF(OR(AP95="",AP95=0),"",IF(SUMPRODUCT(($C$55:$C$175=AP95)*(U$54:$AI$54<EOMONTH(TODAY(),-1)+1)*(ISNUMBER(U$55:$AI$175)),U$55:$AI$175)=0,"",SUMPRODUCT(($C$55:$C$175=AP95)*(U$54:$AI$54<EOMONTH(TODAY(),-1)+1)*(ISNUMBER(U$55:$AI$175)),U$55:$AI$175)))} -> 18682.79 | AS95: =A95 -> BSW | AU95: =IF(OR(I95="",K95=""),0,(I95/12)*K95) -> 47355 | AV95: =IF(OR(N95="",K95="",K95=0),0,(N95/K95)*12) -> 44838.696
S96: Real | T96: 1 | W96: 4391.241 | X96: =SUM(U96:W96) -> 4391.241 | Y96: 4250.3113 | Z96: 3015.575 | AA96: 3692.9984 | AB96: =SUM(Y96:AA96) -> 10958.885 | AC96: 3523.2422 | AF96: =SUM(AC96:AE96) -> 3523.2422 | AJ96: =SUM(AG96:AI96) -> 0 | AK96: =SUM(X96,AB96,AF96,AJ96) -> 18873.368 | AL96: 05/02/2026 - Aguardando validação dae Custos -> Calculado o ganho direto da MP, visto que os processos não mudam - baseado no volume Budget dos itens que são faturados (Março a Dezembro) | AP96: =C95 -> 21 - Kaizen_Redução de peso bruto MB003537LA_MB003538LA | AQ96: R | AR96: {=IF(OR(AP96="",AP96=0),"",IF(SUMPRODUCT(($C$55:$C$175=AP96)*($U$54:AI$54<=TODAY())*(ISNUMBER($U$56:AI$176)),$U$56:AI$176)=0,"",SUMPRODUCT(($C$55:$C$175=AP96)*($U$54:AI$54<=TODAY())*(ISNUMBER($U$56:AI$176)),$U$56:AI$176)))} -> 18873.368 | AS96: =A95 -> BSW
A97: BSW | B97: VA | C97: 22 - Aproveitamento de Retalho do corte laser - MB002316LA_MB003533LA_MB003673LC | D97: \\192.168.0.20\DEPARTAMENTOS\Engenharia\0. Kaizen Diadema\6. 2026\02 Fevereiro\15 - MB002316LA_MB003533LA_MB003673LC - Bruno Manachini_Engenharia\15 - KAIZEN - MB002316LA_MB003533LA_MB003673LC_Rev00_Bruno Manachini.xlsx | E97: Corta as peças MB003673LC e MB003533LA/LB no retalho da peça MB002316LA | F97: B. Manachini | G97: 46054 | H97: 46082 | I97: 36000 | K97: =IF(J97="", "", 12 - MONTH(J97) + 1) | M97: Não Ok | N97: 0 | O97: ✓ Concluído | P97: NA | Q97: NA | R97: 1 | S97: Previsto | T97: 1 | U97: =IFERROR(IF(AND(U$54>=EOMONTH($J97,-1)+1,U$54<=EOMONTH(EOMONTH($J97,-1)+1,$K97-1)),IF(NOT(ISBLANK($N97)),$N97/$K97,$I97/$K97),0),0) -> 0 | V97: =IFERROR(IF(AND(V$54>=EOMONTH($J97,-1)+1,V$54<=EOMONTH(EOMONTH($J97,-1)+1,$K97-1)),IF(NOT(ISBLANK($N97)),$N97/$K97,$I97/$K97),0),0) -> 0 | W97: =IFERROR(IF(AND(W$54>=EOMONTH($J97,-1)+1,W$54<=EOMONTH(EOMONTH($J97,-1)+1,$K97-1)),IF(NOT(ISBLANK($N97)),$N97/$K97,$I97/$K97),0),0) -> 0 | X97: =SUM(U97:W97) -> 0 | Y97: =IFERROR(IF(AND(Y$54>=EOMONTH($J97,-1)+1,Y$54<=EOMONTH(EOMONTH($J97,-1)+1,$K97-1)),IF(NOT(ISBLANK($N97)),$N97/$K97,$I97/$K97),0),0) -> 0 | Z97: =IFERROR(IF(AND(Z$54>=EOMONTH($J97,-1)+1,Z$54<=EOMONTH(EOMONTH($J97,-1)+1,$K97-1)),IF(NOT(ISBLANK($N97)),$N97/$K97,$I97/$K97),0),0) -> 0 | AA97: =IFERROR(IF(AND(AA$54>=EOMONTH($J97,-1)+1,AA$54<=EOMONTH(EOMONTH($J97,-1)+1,$K97-1)),IF(NOT(ISBLANK($N97)),$N97/$K97,$I97/$K97),0),0) -> 0 | AB97: =SUM(Y97:AA97) -> 0 | AC97: =IFERROR(IF(AND(AC$54>=EOMONTH($J97,-1)+1,AC$54<=EOMONTH(EOMONTH($J97,-1)+1,$K97-1)),IF(NOT(ISBLANK($N97)),$N97/$K97,$I97/$K97),0),0) -> 0 | AD97: =IFERROR(IF(AND(AD$54>=EOMONTH($J97,-1)+1,AD$54<=EOMONTH(EOMONTH($J97,-1)+1,$K97-1)),IF(NOT(ISBLANK($N97)),$N97/$K97,$I97/$K97),0),0) -> 0 | AE97: =IFERROR(IF(AND(AE$54>=EOMONTH($J97,-1)+1,AE$54<=EOMONTH(EOMONTH($J97,-1)+1,$K97-1)),IF(NOT(ISBLANK($N97)),$N97/$K97,$I97/$K97),0),0) -> 0 | AF97: =SUM(AC97:AE97) -> 0 | AG97: =IFERROR(IF(AND(AG$54>=EOMONTH($J97,-1)+1,AG$54<=EOMONTH(EOMONTH($J97,-1)+1,$K97-1)),IF(NOT(ISBLANK($N97)),$N97/$K97,$I97/$K97),0),0) -> 0 | AH97: =IFERROR(IF(AND(AH$54>=EOMONTH($J97,-1)+1,AH$54<=EOMONTH(EOMONTH($J97,-1)+1,$K97-1)),IF(NOT(ISBLANK($N97)),$N97/$K97,$I97/$K97),0),0) -> 0 | AI97: =IFERROR(IF(AND(AI$54>=EOMONTH($J97,-1)+1,AI$54<=EOMONTH(EOMONTH($J97,-1)+1,$K97-1)),IF(NOT(ISBLANK($N97)),$N97/$K97,$I97/$K97),0),0) -> 0 | AJ97: =SUM(AG97:AI97) -> 0 | AK97: =SUM(X97,AB97,AF97,AJ97) -> 0 | AL97: 13/02/2026: Projeto de kaizen número 15 de 2026. | AO97: =N97*AN97 -> 0 | AP97: =C97 -> 22 - Aproveitamento de Retalho do corte laser - MB002316LA_MB003533LA_MB003673LC | AQ97: P | AR97: {=IF(OR(AP97="",AP97=0),"",IF(SUMPRODUCT(($C$55:$C$175=AP97)*(U$54:$AI$54<EOMONTH(TODAY(),-1)+1)*(ISNUMBER(U$55:$AI$175)),U$55:$AI$175)=0,"",SUMPRODUCT(($C$55:$C$175=AP97)*(U$54:$AI$54<EOMONTH(TODAY(),-1)+1)*(ISNUMBER(U$55:$AI$175)),U$55:$AI$175)))} | AS97: =A97 -> BSW | AU97: =IF(OR(I97="",K97=""),0,(I97/12)*K97) -> 0 | AV97: =IF(OR(N97="",K97="",K97=0),0,(N97/K97)*12) -> 0
S98: Real | T98: 1 | X98: =SUM(U98:W98) -> 0 | AB98: =SUM(Y98:AA98) -> 0 | AF98: =SUM(AC98:AE98) -> 0 | AJ98: =SUM(AG98:AI98) -> 0 | AK98: =SUM(X98,AB98,AF98,AJ98) -> 0 | AP98: =C97 -> 22 - Aproveitamento de Retalho do corte laser - MB002316LA_MB003533LA_MB003673LC | AQ98: R | AR98: {=IF(OR(AP98="",AP98=0),"",IF(SUMPRODUCT(($C$55:$C$175=AP98)*($U$54:AI$54<=TODAY())*(ISNUMBER($U$56:AI$176)),$U$56:AI$176)=0,"",SUMPRODUCT(($C$55:$C$175=AP98)*($U$54:AI$54<=TODAY())*(ISNUMBER($U$56:AI$176)),$U$56:AI$176)))} | AS98: =A97 -> BSW
A99: BSW | B99: VA | C99: 23 - Redução do peso bruto VW000581Z / VW000582Z | D99: \\192.168.0.20\DEPARTAMENTOS\\Engenharia\0. Kaizen Diadema\6. 2026\02 Fevereiro\16 - VW000581Z_VW000582Z - Bruno Manachini\16 - KAIZEN - Redução do peso bruto VW000581Z VW000582Z_Rev00_B. Manachini.xlsx | E99: Reduzir o blank de 840mm para 820mm (passo). | F99: B. Manachini | G99: 46069 | H99: 46233 | I99: 270000 | J99: 46235 | K99: =IF(J99="", "", 12 - MONTH(J99) + 1) -> 5 | M99: OK | N99: 128107.04 | O99: ⏳ Em Execução | P99: Compras (Lucas): Aguardando retorno da SU | Q99: 46237 | R99: 0.8 | S99: Previsto | T99: 0.2 | U99: =IFERROR(IF(AND(U$54>=EOMONTH($J99,-1)+1,U$54<=EOMONTH(EOMONTH($J99,-1)+1,$K99-1)),IF(NOT(ISBLANK($N99)),$N99/$K99,$I99/$K99),0),0) -> 0 | V99: =IFERROR(IF(AND(V$54>=EOMONTH($J99,-1)+1,V$54<=EOMONTH(EOMONTH($J99,-1)+1,$K99-1)),IF(NOT(ISBLANK($N99)),$N99/$K99,$I99/$K99),0),0) -> 0 | W99: =IFERROR(IF(AND(W$54>=EOMONTH($J99,-1)+1,W$54<=EOMONTH(EOMONTH($J99,-1)+1,$K99-1)),IF(NOT(ISBLANK($N99)),$N99/$K99,$I99/$K99),0),0) -> 0 | X99: =SUM(U99:W99) -> 0 | Y99: =IFERROR(IF(AND(Y$54>=EOMONTH($J99,-1)+1,Y$54<=EOMONTH(EOMONTH($J99,-1)+1,$K99-1)),IF(NOT(ISBLANK($N99)),$N99/$K99,$I99/$K99),0),0) -> 0 | Z99: =IFERROR(IF(AND(Z$54>=EOMONTH($J99,-1)+1,Z$54<=EOMONTH(EOMONTH($J99,-1)+1,$K99-1)),IF(NOT(ISBLANK($N99)),$N99/$K99,$I99/$K99),0),0) -> 0 | AA99: =IFERROR(IF(AND(AA$54>=EOMONTH($J99,-1)+1,AA$54<=EOMONTH(EOMONTH($J99,-1)+1,$K99-1)),IF(NOT(ISBLANK($N99)),$N99/$K99,$I99/$K99),0),0) -> 0 | AB99: =SUM(Y99:AA99) -> 0 | AC99: =IFERROR(IF(AND(AC$54>=EOMONTH($J99,-1)+1,AC$54<=EOMONTH(EOMONTH($J99,-1)+1,$K99-1)),IF(NOT(ISBLANK($N99)),$N99/$K99,$I99/$K99),0),0) -> 0 | AD99: =IFERROR(IF(AND(AD$54>=EOMONTH($J99,-1)+1,AD$54<=EOMONTH(EOMONTH($J99,-1)+1,$K99-1)),IF(NOT(ISBLANK($N99)),$N99/$K99,$I99/$K99),0),0) -> 25621.408 | AE99: =IFERROR(IF(AND(AE$54>=EOMONTH($J99,-1)+1,AE$54<=EOMONTH(EOMONTH($J99,-1)+1,$K99-1)),IF(NOT(ISBLANK($N99)),$N99/$K99,$I99/$K99),0),0) -> 25621.408 | AF99: =SUM(AC99:AE99) -> 51242.816 | AG99: =IFERROR(IF(AND(AG$54>=EOMONTH($J99,-1)+1,AG$54<=EOMONTH(EOMONTH($J99,-1)+1,$K99-1)),IF(NOT(ISBLANK($N99)),$N99/$K99,$I99/$K99),0),0) -> 25621.408 | AH99: =IFERROR(IF(AND(AH$54>=EOMONTH($J99,-1)+1,AH$54<=EOMONTH(EOMONTH($J99,-1)+1,$K99-1)),IF(NOT(ISBLANK($N99)),$N99/$K99,$I99/$K99),0),0) -> 25621.408 | AI99: =IFERROR(IF(AND(AI$54>=EOMONTH($J99,-1)+1,AI$54<=EOMONTH(EOMONTH($J99,-1)+1,$K99-1)),IF(NOT(ISBLANK($N99)),$N99/$K99,$I99/$K99),0),0) -> 25621.408 | AJ99: =SUM(AG99:AI99) -> 76864.224 | AK99: =SUM(X99,AB99,AF99,AJ99) -> 128107.04 | AL99: 17/02/2026: Projeto de kaizen número 16 de 2026. Enviado 16/02/2026 para validação da Controladoria. | AO99: =N99*AN99 -> 0 | AP99: =C99 -> 23 - Redução do peso bruto VW000581Z / VW000582Z | AQ99: P | AR99: {=IF(OR(AP99="",AP99=0),"",IF(SUMPRODUCT(($C$55:$C$175=AP99)*(U$54:$AI$54<EOMONTH(TODAY(),-1)+1)*(ISNUMBER(U$55:$AI$175)),U$55:$AI$175)=0,"",SUMPRODUCT(($C$55:$C$175=AP99)*(U$54:$AI$54<EOMONTH(TODAY(),-1)+1)*(ISNUMBER(U$55:$AI$175)),U$55:$AI$175)))} | AS99: =A99 -> BSW | AU99: =IF(OR(I99="",K99=""),0,(I99/12)*K99) -> 112500 | AV99: =IF(OR(N99="",K99="",K99=0),0,(N99/K99)*12) -> 307456.9
S100: Real | T100: 0.25 | X100: =SUM(U100:W100) -> 0 | AB100: =SUM(Y100:AA100) -> 0 | AF100: =SUM(AC100:AE100) -> 0 | AJ100: =SUM(AG100:AI100) -> 0 | AK100: =SUM(X100,AB100,AF100,AJ100) -> 0 | AL100: >> Custos - validado, considerando volume de Março a Dezembro. | AP100: =C99 -> 23 - Redução do peso bruto VW000581Z / VW000582Z | AQ100: R | AR100: {=IF(OR(AP100="",AP100=0),"",IF(SUMPRODUCT(($C$55:$C$175=AP100)*($U$54:AI$54<=TODAY())*(ISNUMBER($U$56:AI$176)),$U$56:AI$176)=0,"",SUMPRODUCT(($C$55:$C$175=AP100)*($U$54:AI$54<=TODAY())*(ISNUMBER($U$56:AI$176)),$U$56:AI$176)))} | AS100: =A99 -> BSW
A101: BSW | B101: VA | C101: 24 - KAIZEN - Redução de peso bruto_MB002289LA_MB002290LA_Rev00_Bruno Manachini | D101: \\192.168.0.20\DEPARTAMENTOS\Engenharia\0. Kaizen Diadema\6. 2026\02 Fevereiro\20 - MB002289LA_MB002290LA - Bruno Manachini_Engenharia\20 - KAIZEN - Redução de peso bruto_MB002289LA_MB002290LA_Rev00_Bruno Manachini.xlsx | E101: Redução de 146g do peso bruto por peça (comprimento de 1540 para 2690) | F101: B. Manachini | G101: 46076 | H101: 46122 | I101: 33600 | J101: 46143 | K101: =IF(J101="", "", 12 - MONTH(J101) + 1) -> 8 | M101: OK | N101: 29532.29 | O101: ✓ Concluído | P101: NA | Q101: NA | R101: 0.8 | S101: Previsto | T101: 1 | U101: =IFERROR(IF(AND(U$54>=EOMONTH($J101,-1)+1,U$54<=EOMONTH(EOMONTH($J101,-1)+1,$K101-1)),IF(NOT(ISBLANK($N101)),$N101/$K101,$I101/$K101),0),0) -> 0 | V101: =IFERROR(IF(AND(V$54>=EOMONTH($J101,-1)+1,V$54<=EOMONTH(EOMONTH($J101,-1)+1,$K101-1)),IF(NOT(ISBLANK($N101)),$N101/$K101,$I101/$K101),0),0) -> 0 | W101: =IFERROR(IF(AND(W$54>=EOMONTH($J101,-1)+1,W$54<=EOMONTH(EOMONTH($J101,-1)+1,$K101-1)),IF(NOT(ISBLANK($N101)),$N101/$K101,$I101/$K101),0),0) -> 0 | X101: =SUM(U101:W101) -> 0 | Y101: =IFERROR(IF(AND(Y$54>=EOMONTH($J101,-1)+1,Y$54<=EOMONTH(EOMONTH($J101,-1)+1,$K101-1)),IF(NOT(ISBLANK($N101)),$N101/$K101,$I101/$K101),0),0) -> 0 | Z101: =IFERROR(IF(AND(Z$54>=EOMONTH($J101,-1)+1,Z$54<=EOMONTH(EOMONTH($J101,-1)+1,$K101-1)),IF(NOT(ISBLANK($N101)),$N101/$K101,$I101/$K101),0),0) -> 3691.5363 | AA101: =IFERROR(IF(AND(AA$54>=EOMONTH($J101,-1)+1,AA$54<=EOMONTH(EOMONTH($J101,-1)+1,$K101-1)),IF(NOT(ISBLANK($N101)),$N101/$K101,$I101/$K101),0),0) -> 3691.5363 | AB101: =SUM(Y101:AA101) -> 7383.0725 | AC101: =IFERROR(IF(AND(AC$54>=EOMONTH($J101,-1)+1,AC$54<=EOMONTH(EOMONTH($J101,-1)+1,$K101-1)),IF(NOT(ISBLANK($N101)),$N101/$K101,$I101/$K101),0),0) -> 3691.5363 | AD101: =IFERROR(IF(AND(AD$54>=EOMONTH($J101,-1)+1,AD$54<=EOMONTH(EOMONTH($J101,-1)+1,$K101-1)),IF(NOT(ISBLANK($N101)),$N101/$K101,$I101/$K101),0),0) -> 3691.5363 | AE101: =IFERROR(IF(AND(AE$54>=EOMONTH($J101,-1)+1,AE$54<=EOMONTH(EOMONTH($J101,-1)+1,$K101-1)),IF(NOT(ISBLANK($N101)),$N101/$K101,$I101/$K101),0),0) -> 3691.5363 | AF101: =SUM(AC101:AE101) -> 11074.609 | AG101: =IFERROR(IF(AND(AG$54>=EOMONTH($J101,-1)+1,AG$54<=EOMONTH(EOMONTH($J101,-1)+1,$K101-1)),IF(NOT(ISBLANK($N101)),$N101/$K101,$I101/$K101),0),0) -> 3691.5363 | AH101: =IFERROR(IF(AND(AH$54>=EOMONTH($J101,-1)+1,AH$54<=EOMONTH(EOMONTH($J101,-1)+1,$K101-1)),IF(NOT(ISBLANK($N101)),$N101/$K101,$I101/$K101),0),0) -> 3691.5363 | AI101: =IFERROR(IF(AND(AI$54>=EOMONTH($J101,-1)+1,AI$54<=EOMONTH(EOMONTH($J101,-1)+1,$K101-1)),IF(NOT(ISBLANK($N101)),$N101/$K101,$I101/$K101),0),0) -> 3691.5363 | AJ101: =SUM(AG101:AI101) -> 11074.609 | AK101: =SUM(X101,AB101,AF101,AJ101) -> 29532.29 | AL101: 24/02/2026: Projeto de kaizen número 20 de 2026. Enviado 23/02/2026 para validação da Controladoria. --> Aguardando confirmação de algumas informações (email enviado 11/03) | AO101: =N101*AN101 -> 0 | AP101: =C101 -> 24 - KAIZEN - Redução de peso bruto_MB002289LA_MB002290LA_Rev00_Bruno Manachini | AQ101: P | AR101: {=IF(OR(AP101="",AP101=0),"",IF(SUMPRODUCT(($C$55:$C$175=AP101)*(U$54:$AI$54<EOMONTH(TODAY(),-1)+1)*(ISNUMBER(U$55:$AI$175)),U$55:$AI$175)=0,"",SUMPRODUCT(($C$55:$C$175=AP101)*(U$54:$AI$54<EOMONTH(TODAY(),-1)+1)*(ISNUMBER(U$55:$AI$175)),U$55:$AI$175)))} -> 11074.609 | AS101: =A101 -> BSW | AU101: =IF(OR(I101="",K101=""),0,(I101/12)*K101) -> 22400 | AV101: =IF(OR(N101="",K101="",K101=0),0,(N101/K101)*12) -> 44298.435
S102: Real | T102: 1 | X102: =SUM(U102:W102) -> 0 | Z102: 3320.2091 | AA102: 3373.6041 | AB102: =SUM(Y102:AA102) -> 6693.8132 | AC102: 3115.3377 | AF102: =SUM(AC102:AE102) -> 3115.3377 | AJ102: =SUM(AG102:AI102) -> 0 | AK102: =SUM(X102,AB102,AF102,AJ102) -> 9809.1509 | AL102: -> Aguardando confirmação de algumas informações - email enviado em 11/03. | AP102: =C101 -> 24 - KAIZEN - Redução de peso bruto_MB002289LA_MB002290LA_Rev00_Bruno Manachini | AQ102: R | AR102: {=IF(OR(AP102="",AP102=0),"",IF(SUMPRODUCT(($C$55:$C$175=AP102)*($U$54:AI$54<=TODAY())*(ISNUMBER($U$56:AI$176)),$U$56:AI$176)=0,"",SUMPRODUCT(($C$55:$C$175=AP102)*($U$54:AI$54<=TODAY())*(ISNUMBER($U$56:AI$176)),$U$56:AI$176)))} -> 9809.1509 | AS102: =A101 -> BSW
...

Sheet Jarinu
A1: DASHBOARD EXECUTIVO - UNIDADE JARINU
A2: Gestão Estratégica de Projetos e Redução de Custos | Grupo Delga | 2026
A4: META DA UNIDADE | B4: RETORNO PREVISTO (Anual) | C4: Retorno Validado (Anual) | D4: PREVISTO 2026 | E4: 💰 RETORNO VALIDADO 2026 | G4: 💰 RETORNO REAL | I4: Extra DRE (Até o momento) | J4: % ATINGIMENTO DA META | L4: INICIATIVAS | O4: TOP 20 Raking de Projetos Valorizados
A5: =Parâmetros!E8 -> 5356000 | B5: =SUM(I55:I144) -> 5582548 | C5: =AU53 -> 7824805.1 | D5: =AT53-AT55 -> 3031400.1 | E5: =SUM(N55:N144) -> 2945612.6 | G5: =SUM(E9,E11:E14) -> 463507.45 | I5: =E8+E10 -> 1009000 | J5: =G5/A5 -> 0.086539852 | L5: =SUM(G8:G10) -> 37 | O5: POS | P5: Tipo | Q5: Valor Previsto | R5: Valor Previsto Custos | S5: Retorno Previsto | T5: Retorno Real até hoje | U5: Projetos | Z5: Peso | AA5: Pareto | AB5: % Previsto | AC5: % Real | AD5: Planejado | AE5: % Responsabilidade Delga
A6: 📊 SAVING PREVISTO POR PILAR | F6: 📋 STATUS DAS INICIATIVAS | I6: 🏭 INDICADORES OPERACIONAIS | O6: {=_xlfn.SEQUENCE(20)} -> 1 | P6: =_xlfn.XLOOKUP(U6,$C$55:$C$144,$A$55:$A$144) -> BSW | Q6: =MAX(I55:I144) -> 1063359 | R6: =_xlfn.XLOOKUP(Q6,$I$55:$I$144,$N$55:$N$144) -> 1145830.2 | S6: =_xlfn.XLOOKUP(U6,$C$55:$C$176,$J$55:$J$176) -> 46296 | T6: {=SUMPRODUCT(($C$55:$C$175=U6)*(U$54:$AI$54<=TODAY())*(ISNUMBER(U$56:$AI$176)),U$56:$AI$176)} -> 0 | U6: =IFERROR(HYPERLINK(INDEX($D$55:$D$144,MATCH(Q6,$I$55:$I$144,0)),INDEX($C$55:$C$144,MATCH(Q6,$I$55:$I$144,0)) ), "" ) -> 06 - Redução consumo MTP aplicando tolerância mínima | Z6: =Q6/$D$5 -> 0.35078148 | AA6: =Pareto!E70 -> 0.19047915 | AB6: {=IFERROR(INDEX($T$55:$T$144,MATCH(1,($AP$55:$AP$144=U6)*($S$55:$S$144="Previsto"), 0) ), "")} -> 0.32939189 | AC6: 0.29 | AD6: =IF(OR(AB6="",AC6=""),"",IF(AC6=100%,"CONCLUÍDO",IF(AC6=0,IF(AB6=0,"PROJETO NÃO INICIADO","FALTA DE ACOMPANHAMENTO"),IF(AC6>AB6,"ADIANTADO",IF(AC6=AB6,"CONFORME PLANEJADO","ATRASO"))))) -> ATRASO | AE6: {=_xlfn.XLOOKUP($U$6:$U$24,$C$55:$C$144,$R$55:$R$144)} -> 0.1
A7: Pilar | B7: Qtd. | C7: Saving (R$) | D7: Saving Validado 2026 | E7: Até o Momento | F7: Status | G7: Qtd. | H7: R$ Previsto | I7: Aderência SPD: Unidade | J7: Aderência SPD: Auditado | K7: Análise de Margem (Form 206) | O7: 2 | P7: =_xlfn.XLOOKUP(U7,$C$55:$C$144,$A$55:$A$144) -> Redução de custo | Q7: =IFERROR(LARGE($I$55:$I$144,O7)," ") -> 560000 | R7: =_xlfn.XLOOKUP(Q7,$I$55:$I$144,$N$55:$N$144) -> 0 | S7: =_xlfn.XLOOKUP(U7,$C$55:$C$176,$J$55:$J$176) -> 46388 | T7: {=SUMPRODUCT(($C$55:$C$175=U7)*(U$54:$AI$54<=TODAY())*(ISNUMBER(U$56:$AI$176)),U$56:$AI$176)} -> 0 | U7: =IFERROR(HYPERLINK(INDEX($D$55:$D$144,MATCH(Q7,$I$55:$I$144,0)),INDEX($C$55:$C$144,MATCH(Q7,$I$55:$I$144,0)) ), "" ) -> 01 - Desenvolver célula de solda para soldar porcas | Z7: =Q7/$D$5 -> 0.18473312 | AA7: =Pareto!E71 -> 0.29079177 | AB7: {=IFERROR(INDEX($T$55:$T$144,MATCH(1,($AP$55:$AP$144=U7)*($S$55:$S$144="Previsto"), 0) ), "")} -> 0.79032258 | AC7: {=IFERROR( INDEX($T$55:$T$144,MATCH(1,($AP$55:$AP$144=U7)*($S$55:$S$144="Real"),0)),"")} -> 0.79 | AD7: =IF(OR(AB7="",AC7=""),"",IF(AC7=100%,"CONCLUÍDO",IF(AC7=0,IF(AB7=0,"PROJETO NÃO INICIADO","FALTA DE ACOMPANHAMENTO"),IF(AC7>AB7,"ADIANTADO",IF(AC7=AB7,"CONFORME PLANEJADO","ATRASO"))))) -> ATRASO | AE7: 0.8
A8: Kaizen - Capital de Giro | B8: =COUNTIF($A$55:$A$144,A8) -> 0 | C8: =SUMIF($A$55:$A$144,A8,$I$55:$I$144) -> 0 | D8: =SUMIF($A$55:$A$144,A8,$N$55:$N$144) -> 0 | E8: =SUMIFS($AK$55:$AK$144,$S$55:$S$144,"Previsto",$AS$55:$AS$144,A8) -> 0 | F8: ✓ Concluído | G8: =COUNTIF($O$55:$O$144,F8) -> 10 | H8: =SUMIF($O$55:$O$144,F8,$I$55:$I$144) -> 1395112 | O8: 3 | P8: =_xlfn.XLOOKUP(U8,$C$55:$C$144,$A$55:$A$144) -> BSW | Q8: =IFERROR(LARGE($I$55:$I$144,O8)," ") -> 513721 | R8: =_xlfn.XLOOKUP(Q8,$I$55:$I$144,$N$55:$N$144) -> 0 | S8: =_xlfn.XLOOKUP(U8,$C$55:$C$176,$J$55:$J$176) -> 46266 | T8: {=SUMPRODUCT(($C$55:$C$175=U8)*(U$54:$AI$54<=TODAY())*(ISNUMBER(U$56:$AI$176)),U$56:$AI$176)} -> 0 | U8: =IFERROR(HYPERLINK(INDEX($D$55:$D$144,MATCH(Q8,$I$55:$I$144,0)),INDEX($C$55:$C$144,MATCH(Q8,$I$55:$I$144,0)) ), "" ) -> 03 - Redução de consumo de MP dos blanks com a técnica de corte Wave | Z8: =Q8/$D$5 -> 0.16946658 | AA8: =Pareto!E72 -> 0.38281444 | AB8: {=IFERROR(INDEX($T$55:$T$144,MATCH(1,($AP$55:$AP$144=U8)*($S$55:$S$144="Previsto"), 0) ), "")} -> 0.87668987 | AC8: {=IFERROR( INDEX($T$55:$T$144,MATCH(1,($AP$55:$AP$144=U8)*($S$55:$S$144="Real"),0)),"")} -> 0.78586513 | AD8: =IF(OR(AB8="",AC8=""),"",IF(AC8=100%,"CONCLUÍDO",IF(AC8=0,IF(AB8=0,"PROJETO NÃO INICIADO","FALTA DE ACOMPANHAMENTO"),IF(AC8>AB8,"ADIANTADO",IF(AC8=AB8,"CONFORME PLANEJADO","ATRASO"))))) -> ATRASO | AE8: 0.9
A9: Kaizen - Ganho Recorrente | B9: =COUNTIF($A$55:$A$144,A9) -> 8 | C9: =SUMIF($A$55:$A$144,A9,$I$55:$I$144) -> 336459.01 | D9: =SUMIF($A$55:$A$144,A9,$N$55:$N$144) -> 89081.02 | E9: =SUMIFS($AK$55:$AK$144,$S$55:$S$144,"Real",$AS$55:$AS$144,A9) -> 0 | F9: ⏳ Em Execução | G9: =COUNTIF($O$55:$O$144,F9) -> 23 | H9: =SUMIF($O$55:$O$144,F9,$I$55:$I$144) -> 4184436 | I9: =E175 -> 0.91666667 | J9: =F175 -> 0.91666667 | K9: =L170 -> 0.43333333 | O9: 4 | P9: =_xlfn.XLOOKUP(U9,$C$55:$C$144,$A$55:$A$144) -> BSW | Q9: =IFERROR(LARGE($I$55:$I$144,O9)," ") -> 435138 | R9: =_xlfn.XLOOKUP(Q9,$I$55:$I$144,$N$55:$N$144) -> 442663.07 | S9: =_xlfn.XLOOKUP(U9,$C$55:$C$176,$J$55:$J$176) -> 46233 | T9: {=SUMPRODUCT(($C$55:$C$175=U9)*(U$54:$AI$54<=TODAY())*(ISNUMBER(U$56:$AI$176)),U$56:$AI$176)} -> 0 | U9: =IFERROR(HYPERLINK(INDEX($D$55:$D$144,MATCH(Q9,$I$55:$I$144,0)),INDEX($C$55:$C$144,MATCH(Q9,$I$55:$I$144,0)) ), "" ) -> 27 - Redução consumo MTP aplicando tolerância mínima curva B | Z9: =Q9/$D$5 -> 0.14354357 | AA9: =Pareto!E73 -> 0.46076057 | AB9: {=IFERROR(INDEX($T$55:$T$144,MATCH(1,($AP$55:$AP$144=U9)*($S$55:$S$144="Previsto"), 0) ), "")} -> 0.2 | AC9: {=IFERROR( INDEX($T$55:$T$144,MATCH(1,($AP$55:$AP$144=U9)*($S$55:$S$144="Real"),0)),"")} -> 0 | AD9: =IF(OR(AB9="",AC9=""),"",IF(AC9=100%,"CONCLUÍDO",IF(AC9=0,IF(AB9=0,"PROJETO NÃO INICIADO","FALTA DE ACOMPANHAMENTO"),IF(AC9>AB9,"ADIANTADO",IF(AC9=AB9,"CONFORME PLANEJADO","ATRASO"))))) -> FALTA DE ACOMPANHAMENTO | AE9: 0
A10: Kaizen - Custo Evitado | B10: =COUNTIF($A$55:$A$144,A10) -> 4 | C10: =SUMIF($A$55:$A$144,A10,$I$55:$I$144) -> 1009000 | D10: =SUMIF($A$55:$A$144,A10,$N$55:$N$144) -> 0 | E10: =SUMIFS($AK$55:$AK$144,$S$55:$S$144,"Previsto",$AS$55:$AS$144,A10) -> 1009000 | F10: 📝 Não iniciado | G10: =COUNTIF($O$55:$O$144,F10) -> 4 | H10: =SUMIF($O$55:$O$144,F10,$I$55:$I$144) -> 3000.0078 | O10: 5 | P10: =_xlfn.XLOOKUP(U10,$C$55:$C$144,$A$55:$A$144) -> Redução de custo | Q10: =IFERROR(LARGE($I$55:$I$144,O10)," ") -> 390000 | R10: =_xlfn.XLOOKUP(Q10,$I$55:$I$144,$N$55:$N$144) -> 390000 | S10: =_xlfn.XLOOKUP(U10,$C$55:$C$176,$J$55:$J$176) -> 46023 | T10: {=SUMPRODUCT(($C$55:$C$175=U10)*(U$54:$AI$54<=TODAY())*(ISNUMBER(U$56:$AI$176)),U$56:$AI$176)} -> 390000 | U10: =IFERROR(HYPERLINK(INDEX($D$55:$D$144,MATCH(Q10,$I$55:$I$144,0)),INDEX($C$55:$C$144,MATCH(Q10,$I$55:$I$144,0)) ), "" ) -> 36 - Venda Robos | Z10: =Q10/$D$5 -> 0.12865342 | AA10: =Pareto!E74 -> 0.53062114 | AB10: {=IFERROR(INDEX($T$55:$T$144,MATCH(1,($AP$55:$AP$144=U10)*($S$55:$S$144="Previsto"), 0) ), "")} -> 1 | AC10: {=IFERROR( INDEX($T$55:$T$144,MATCH(1,($AP$55:$AP$144=U10)*($S$55:$S$144="Real"),0)),"")} -> 1 | AD10: =IF(OR(AB10="",AC10=""),"",IF(AC10=100%,"CONCLUÍDO",IF(AC10=0,IF(AB10=0,"PROJETO NÃO INICIADO","FALTA DE ACOMPANHAMENTO"),IF(AC10>AB10,"ADIANTADO",IF(AC10=AB10,"CONFORME PLANEJADO","ATRASO"))))) -> CONCLUÍDO | AE10: 0
A11: Kaizen | B11: =COUNTIF($A$55:$A$144,A11) -> 1 | C11: =SUMIF($A$55:$A$144,A11,$I$55:$I$144) -> 40000.001 | D11: =SUMIF($A$55:$A$144,A11,$N$55:$N$144) -> 0 | E11: =SUMIFS($AK$55:$AK$144,$S$55:$S$144,"Real",$AS$55:$AS$144,A11) -> 0 | O11: 6 | P11: =_xlfn.XLOOKUP(U11,$C$55:$C$144,$A$55:$A$144) -> Kaizen - Custo Evitado | Q11: =IFERROR(LARGE($I$55:$I$144,O11)," ") -> 359000 | R11: =_xlfn.XLOOKUP(Q11,$I$55:$I$144,$N$55:$N$144) -> 0 | S11: =_xlfn.XLOOKUP(U11,$C$55:$C$176,$J$55:$J$176) -> 46082 | T11: {=SUMPRODUCT(($C$55:$C$175=U11)*(U$54:$AI$54<=TODAY())*(ISNUMBER(U$56:$AI$176)),U$56:$AI$176)} -> 0 | U11: =IFERROR(HYPERLINK(INDEX($D$55:$D$144,MATCH(Q11,$I$55:$I$144,0)),INDEX($C$55:$C$144,MATCH(Q11,$I$55:$I$144,0)) ), "" ) -> 26 - Redução de gastos com HE | Z11: =Q11/$D$5 -> 0.11842713 | AA11: =Pareto!E75 -> 0.59492869 | AB11: {=IFERROR(INDEX($T$55:$T$144,MATCH(1,($AP$55:$AP$144=U11)*($S$55:$S$144="Previsto"), 0) ), "")} -> 1 | AC11: {=IFERROR( INDEX($T$55:$T$144,MATCH(1,($AP$55:$AP$144=U11)*($S$55:$S$144="Real"),0)),"")} -> 1 | AD11: =IF(OR(AB11="",AC11=""),"",IF(AC11=100%,"CONCLUÍDO",IF(AC11=0,IF(AB11=0,"PROJETO NÃO INICIADO","FALTA DE ACOMPANHAMENTO"),IF(AC11>AB11,"ADIANTADO",IF(AC11=AB11,"CONFORME PLANEJADO","ATRASO"))))) -> CONCLUÍDO | AE11: 1
A12: Redução de Custo | B12: =COUNTIF($A$55:$A$144,A12) -> 9 | C12: =SUMIF($A$55:$A$144,A12,$I$55:$I$144) -> 1324889 | D12: =SUMIF($A$55:$A$144,A12,$N$55:$N$144) -> 775553.55 | E12: =SUMIFS($AK$55:$AK$144,$S$55:$S$144,"Real",$AS$55:$AS$144,A12) -> 459396.51 | O12: 7 | P12: =_xlfn.XLOOKUP(U12,$C$55:$C$144,$A$55:$A$144) -> BSW | Q12: =IFERROR(LARGE($I$55:$I$144,O12)," ") -> 308498 | R12: =_xlfn.XLOOKUP(Q12,$I$55:$I$144,$N$55:$N$144) -> 209476.06 | S12: =_xlfn.XLOOKUP(U12,$C$55:$C$176,$J$55:$J$176) -> 46233 | T12: {=SUMPRODUCT(($C$55:$C$175=U12)*(U$54:$AI$54<=TODAY())*(ISNUMBER(U$56:$AI$176)),U$56:$AI$176)} -> 0 | U12: =IFERROR(HYPERLINK(INDEX($D$55:$D$144,MATCH(Q12,$I$55:$I$144,0)),INDEX($C$55:$C$144,MATCH(Q12,$I$55:$I$144,0)) ), "" ) -> 28 - Redução consumo MTP aplicando tolerância mínima curva C | Z12: =Q12/$D$5 -> 0.1017675 | AA12: =Pareto!E76 -> 0.65018984 | AB12: {=IFERROR(INDEX($T$55:$T$144,MATCH(1,($AP$55:$AP$144=U12)*($S$55:$S$144="Previsto"), 0) ), "")} -> 0.2 | AC12: {=IFERROR( INDEX($T$55:$T$144,MATCH(1,($AP$55:$AP$144=U12)*($S$55:$S$144="Real"),0)),"")} -> 0.21052632 | AD12: =IF(OR(AB12="",AC12=""),"",IF(AC12=100%,"CONCLUÍDO",IF(AC12=0,IF(AB12=0,"PROJETO NÃO INICIADO","FALTA DE ACOMPANHAMENTO"),IF(AC12>AB12,"ADIANTADO",IF(AC12=AB12,"CONFORME PLANEJADO","ATRASO"))))) -> ADIANTADO | AE12: 0
A13: Você Resolve | B13: =COUNTIF($A$55:$A$144,A13) -> 0 | C13: =SUMIF($A$55:$A$144,A13,$I$55:$I$144) -> 0 | D13: =SUMIF($A$55:$A$144,A13,$N$55:$N$144) -> 0 | E13: =SUMIFS($AK$55:$AK$144,$S$55:$S$144,"Real",$AS$55:$AS$144,A13) -> 0 | O13: 8 | P13: =_xlfn.XLOOKUP(U13,$C$55:$C$144,$A$55:$A$144) -> Redução de custo | Q13: =IFERROR(LARGE($I$55:$I$144,O13)," ") -> 306000 | R13: =_xlfn.XLOOKUP(Q13,$I$55:$I$144,$N$55:$N$144) -> 306000 | S13: =_xlfn.XLOOKUP(U13,$C$55:$C$176,$J$55:$J$176) -> 46143 | T13: {=SUMPRODUCT(($C$55:$C$175=U13)*(U$54:$AI$54<=TODAY())*(ISNUMBER(U$56:$AI$176)),U$56:$AI$176)} -> 0 | U13: =IFERROR(HYPERLINK(INDEX($D$55:$D$144,MATCH(Q13,$I$55:$I$144,0)),INDEX($C$55:$C$144,MATCH(Q13,$I$55:$I$144,0)) ), "" ) -> 30 - Redução de Refugo | Z13: =Q13/$D$5 -> 0.10094346 | AA13: =Pareto!E77 -> 0.70500352 | AB13: {=IFERROR(INDEX($T$55:$T$144,MATCH(1,($AP$55:$AP$144=U13)*($S$55:$S$144="Previsto"), 0) ), "")} -> 0.8 | AC13: {=IFERROR( INDEX($T$55:$T$144,MATCH(1,($AP$55:$AP$144=U13)*($S$55:$S$144="Real"),0)),"")} -> 0.8 | AD13: =IF(OR(AB13="",AC13=""),"",IF(AC13=100%,"CONCLUÍDO",IF(AC13=0,IF(AB13=0,"PROJETO NÃO INICIADO","FALTA DE ACOMPANHAMENTO"),IF(AC13>AB13,"ADIANTADO",IF(AC13=AB13,"CONFORME PLANEJADO","ATRASO"))))) -> CONFORME PLANEJADO | AE13: 0
A14: BSW | B14: =COUNTIF($A$55:$A$144,A14) -> 15 | C14: =SUMIF($A$55:$A$144,A14,$I$55:$I$144) -> 2872200 | D14: =SUMIF($A$55:$A$144,A14,$N$55:$N$144) -> 2080978 | E14: =SUMIFS($AK$55:$AK$144,$S$55:$S$144,"Real",$AS$55:$AS$144,A14) -> 4110.9372 | H14: ; | O14: 9 | P14: =_xlfn.XLOOKUP(U14,$C$55:$C$144,$A$55:$A$144) -> Kaizen - Ganho Recorrente | Q14: =IFERROR(LARGE($I$55:$I$144,O14)," ") -> 301000 | R14: =_xlfn.XLOOKUP(Q14,$I$55:$I$144,$N$55:$N$144) -> 89081.02 | S14: =_xlfn.XLOOKUP(U14,$C$55:$C$176,$J$55:$J$176) -> 46235 | T14: {=SUMPRODUCT(($C$55:$C$175=U14)*(U$54:$AI$54<=TODAY())*(ISNUMBER(U$56:$AI$176)),U$56:$AI$176)} -> 0 | U14: =IFERROR(HYPERLINK(INDEX($D$55:$D$144,MATCH(Q14,$I$55:$I$144,0)),INDEX($C$55:$C$144,MATCH(Q14,$I$55:$I$144,0)) ), "" ) -> 32 - Empilhadeiras Elétricas | Z14: =Q14/$D$5 -> 0.099294052 | AA14: =Pareto!E78 -> 0.75892155 | AB14: {=IFERROR(INDEX($T$55:$T$144,MATCH(1,($AP$55:$AP$144=U14)*($S$55:$S$144="Previsto"), 0) ), "")} -> 0 | AC14: {=IFERROR( INDEX($T$55:$T$144,MATCH(1,($AP$55:$AP$144=U14)*($S$55:$S$144="Real"),0)),"")} -> 0 | AD14: =IF(OR(AB14="",AC14=""),"",IF(AC14=100%,"CONCLUÍDO",IF(AC14=0,IF(AB14=0,"PROJETO NÃO INICIADO","FALTA DE ACOMPANHAMENTO"),IF(AC14>AB14,"ADIANTADO",IF(AC14=AB14,"CONFORME PLANEJADO","ATRASO"))))) -> PROJETO NÃO INICIADO | AE14: 0
A15: TOTAL | B15: =SUM(B8:B14) -> 37 | C15: =SUM(C8:C14) -> 5582548 | D15: =SUM(D8:D14) -> 2945612.6 | E15: =SUM(E8:E14) -> 1472507.4 | F15: VA | G15: =SUMIF($B$55:$B$192,F15,$N$55:$N$192) -> 1854110.4 | O15: 10 | P15: =_xlfn.XLOOKUP(U15,$C$55:$C$144,$A$55:$A$144) -> Kaizen - Custo Evitado | Q15: =IFERROR(LARGE($I$55:$I$144,O15)," ") -> 300000 | R15: =_xlfn.XLOOKUP(Q15,$I$55:$I$144,$N$55:$N$144) -> 0 | S15: =_xlfn.XLOOKUP(U15,$C$55:$C$176,$J$55:$J$176) -> 46054 | T15: {=SUMPRODUCT(($C$55:$C$175=U15)*(U$54:$AI$54<=TODAY())*(ISNUMBER(U$56:$AI$176)),U$56:$AI$176)} -> 0 | U15: =IFERROR(HYPERLINK(INDEX($D$55:$D$144,MATCH(Q15,$I$55:$I$144,0)),INDEX($C$55:$C$144,MATCH(Q15,$I$55:$I$144,0)) ), "" ) -> 21 - Redução de MOD CSR61014 | Z15: =Q15/$D$5 -> 0.098964172 | AA15: =Pareto!E79 -> 0.81266045 | AB15: {=IFERROR(INDEX($T$55:$T$144,MATCH(1,($AP$55:$AP$144=U15)*($S$55:$S$144="Previsto"), 0) ), "")} -> 1 | AC15: {=IFERROR( INDEX($T$55:$T$144,MATCH(1,($AP$55:$AP$144=U15)*($S$55:$S$144="Real"),0)),"")} -> 1 | AD15: =IF(OR(AB15="",AC15=""),"",IF(AC15=100%,"CONCLUÍDO",IF(AC15=0,IF(AB15=0,"PROJETO NÃO INICIADO","FALTA DE ACOMPANHAMENTO"),IF(AC15>AB15,"ADIANTADO",IF(AC15=AB15,"CONFORME PLANEJADO","ATRASO"))))) -> CONCLUÍDO | AE15: 1
F16: GGF | G16: =SUMIF($B$55:$B$192,F16,$N$55:$N$192) -> 612421.18 | O16: 11 | P16: =_xlfn.XLOOKUP(U16,$C$55:$C$144,$A$55:$A$144) -> Kaizen - Custo Evitado | Q16: =IFERROR(LARGE($I$55:$I$144,O16)," ") -> 300000 | R16: =_xlfn.XLOOKUP(Q16,$I$55:$I$144,$N$55:$N$144) -> 0 | S16: =_xlfn.XLOOKUP(U16,$C$55:$C$176,$J$55:$J$176) -> 46054 | T16: {=SUMPRODUCT(($C$55:$C$175=U16)*(U$54:$AI$54<=TODAY())*(ISNUMBER(U$56:$AI$176)),U$56:$AI$176)} -> 0 | U16: =IFERROR(HYPERLINK(INDEX($D$55:$D$144,MATCH(Q16,$I$55:$I$144,0)),INDEX($C$55:$C$144,MATCH(Q16,$I$55:$I$144,0)) ), "" ) -> 22 - Redução de MOD CSR61015 | Z16: =Q16/$D$5 -> 0.098964172 | AA16: =Pareto!E80 -> 0.86639936 | AB16: {=IFERROR(INDEX($T$55:$T$144,MATCH(1,($AP$55:$AP$144=U16)*($S$55:$S$144="Previsto"), 0) ), "")} -> 1 | AC16: {=IFERROR( INDEX($T$55:$T$144,MATCH(1,($AP$55:$AP$144=U16)*($S$55:$S$144="Real"),0)),"")} -> 1 | AD16: =IF(OR(AB16="",AC16=""),"",IF(AC16=100%,"CONCLUÍDO",IF(AC16=0,IF(AB16=0,"PROJETO NÃO INICIADO","FALTA DE ACOMPANHAMENTO"),IF(AC16>AB16,"ADIANTADO",IF(AC16=AB16,"CONFORME PLANEJADO","ATRASO"))))) -> CONCLUÍDO | AE16: 1
F17: MA | G17: =SUMIF($B$55:$B$192,F17,$N$55:$N$192) -> 89081.02 | O17: 12 | P17: =_xlfn.XLOOKUP(U17,$C$55:$C$144,$A$55:$A$144) -> BSW | Q17: =IFERROR(LARGE($I$55:$I$144,O17)," ") -> 102967 | R17: =_xlfn.XLOOKUP(Q17,$I$55:$I$144,$N$55:$N$144) -> 0 | S17: =_xlfn.XLOOKUP(U17,$C$55:$C$176,$J$55:$J$176) -> 46357 | T17: {=SUMPRODUCT(($C$55:$C$175=U17)*(U$54:$AI$54<=TODAY())*(ISNUMBER(U$56:$AI$176)),U$56:$AI$176)} -> 0 | U17: =IFERROR(HYPERLINK(INDEX($D$55:$D$144,MATCH(Q17,$I$55:$I$144,0)),INDEX($C$55:$C$144,MATCH(Q17,$I$55:$I$144,0)) ), "" ) -> 19 - Redução da largura da bobina mãe do Curvão | Z17: =Q17/$D$5 -> 0.033966813 | AA17: =Pareto!E81 -> 0.8848438 | AB17: {=IFERROR(INDEX($T$55:$T$144,MATCH(1,($AP$55:$AP$144=U17)*($S$55:$S$144="Previsto"), 0) ), "")} -> 0 | AC17: 0.9 | AD17: =IF(OR(AB17="",AC17=""),"",IF(AC17=100%,"CONCLUÍDO",IF(AC17=0,IF(AB17=0,"PROJETO NÃO INICIADO","FALTA DE ACOMPANHAMENTO"),IF(AC17>AB17,"ADIANTADO",IF(AC17=AB17,"CONFORME PLANEJADO","ATRASO"))))) -> ADIANTADO | AE17: 0.5
F18: Outros | G18: =SUMIF($B$55:$B$192,F18,$N$55:$N$192) -> 390000 | O18: 13 | P18: =_xlfn.XLOOKUP(U18,$C$55:$C$144,$A$55:$A$144) -> BSW | Q18: =IFERROR(LARGE($I$55:$I$144,O18)," ") -> 91444 | R18: =_xlfn.XLOOKUP(Q18,$I$55:$I$144,$N$55:$N$144) -> 0 | S18: =_xlfn.XLOOKUP(U18,$C$55:$C$176,$J$55:$J$176) -> 46235 | T18: {=SUMPRODUCT(($C$55:$C$175=U18)*(U$54:$AI$54<=TODAY())*(ISNUMBER(U$56:$AI$176)),U$56:$AI$176)} -> 0 | U18: =IFERROR(HYPERLINK(INDEX($D$55:$D$144,MATCH(Q18,$I$55:$I$144,0)),INDEX($C$55:$C$144,MATCH(Q18,$I$55:$I$144,0)) ), "" ) -> 05 - Aplicar borda aparadas nas bobinas | Z18: =Q18/$D$5 -> 0.030165599 | AA18: =Pareto!E82 -> 0.90122413 | AB18: {=IFERROR(INDEX($T$55:$T$144,MATCH(1,($AP$55:$AP$144=U18)*($S$55:$S$144="Previsto"), 0) ), "")} -> 0.41666667 | AC18: {=IFERROR( INDEX($T$55:$T$144,MATCH(1,($AP$55:$AP$144=U18)*($S$55:$S$144="Real"),0)),"")} -> 0.33333333 | AD18: =IF(OR(AB18="",AC18=""),"",IF(AC18=100%,"CONCLUÍDO",IF(AC18=0,IF(AB18=0,"PROJETO NÃO INICIADO","FALTA DE ACOMPANHAMENTO"),IF(AC18>AB18,"ADIANTADO",IF(AC18=AB18,"CONFORME PLANEJADO","ATRASO"))))) -> ATRASO | AE18: 0.8
O19: 14 | P19: =_xlfn.XLOOKUP(U19,$C$55:$C$144,$A$55:$A$144) -> BSW | Q19: =IFERROR(LARGE($I$55:$I$144,O19)," ") -> 90850 | R19: =_xlfn.XLOOKUP(Q19,$I$55:$I$144,$N$55:$N$144) -> 165883.52 | S19: =_xlfn.XLOOKUP(U19,$C$55:$C$176,$J$55:$J$176) -> 46235 | T19: {=SUMPRODUCT(($C$55:$C$175=U19)*(U$54:$AI$54<=TODAY())*(ISNUMBER(U$56:$AI$176)),U$56:$AI$176)} -> 0 | U19: =IFERROR(HYPERLINK(INDEX($D$55:$D$144,MATCH(Q19,$I$55:$I$144,0)),INDEX($C$55:$C$144,MATCH(Q19,$I$55:$I$144,0)) ), "" ) -> 24 - Redução de consumo de MTP China 1 porca (-10 mm) | Z19: =Q19/$D$5 -> 0.02996965 | AA19: =Pareto!E83 -> 0.91749807 | AB19: 0.4 | AC19: 0.4 | AD19: CONFORME PLANEJADO | AE19: 0
O20: 15 | P20: =_xlfn.XLOOKUP(U20,$C$55:$C$144,$A$55:$A$144) -> BSW | Q20: =IFERROR(LARGE($I$55:$I$144,O20)," ") -> 75733 | R20: =_xlfn.XLOOKUP(Q20,$I$55:$I$144,$N$55:$N$144) -> 0 | S20: =_xlfn.XLOOKUP(U20,$C$55:$C$176,$J$55:$J$176) -> 46357 | T20: {=SUMPRODUCT(($C$55:$C$175=U20)*(U$54:$AI$54<=TODAY())*(ISNUMBER(U$56:$AI$176)),U$56:$AI$176)} -> 0 | U20: =IFERROR(HYPERLINK(INDEX($D$55:$D$144,MATCH(Q20,$I$55:$I$144,0)),INDEX($C$55:$C$144,MATCH(Q20,$I$55:$I$144,0)) ), "" ) -> 04 - Redução da largura dos slitters | Z20: =Q20/$D$5 -> 0.024982845 | AA20: =Pareto!E84 -> 0.93106409 | AB20: {=IFERROR(INDEX($T$55:$T$144,MATCH(1,($AP$55:$AP$144=U20)*($S$55:$S$144="Previsto"), 0) ), "")} -> 0.4 | AC20: {=IFERROR( INDEX($T$55:$T$144,MATCH(1,($AP$55:$AP$144=U20)*($S$55:$S$144="Real"),0)),"")} -> 0.4 | AD20: =IF(OR(AB20="",AC20=""),"",IF(AC20=100%,"CONCLUÍDO",IF(AC20=0,IF(AB20=0,"PROJETO NÃO INICIADO","FALTA DE ACOMPANHAMENTO"),IF(AC20>AB20,"ADIANTADO",IF(AC20=AB20,"CONFORME PLANEJADO","ATRASO"))))) -> CONFORME PLANEJADO | AE20: 0.5
O21: 16 | P21: =_xlfn.XLOOKUP(U21,$C$55:$C$144,$A$55:$A$144) -> BSW | Q21: =IFERROR(LARGE($I$55:$I$144,O21)," ") -> 74000 | R21: =_xlfn.XLOOKUP(Q21,$I$55:$I$144,$N$55:$N$144) -> 0 | S21: =_xlfn.XLOOKUP(U21,$C$55:$C$176,$J$55:$J$176) -> 46266 | T21: {=SUMPRODUCT(($C$55:$C$175=U21)*(U$54:$AI$54<=TODAY())*(ISNUMBER(U$56:$AI$176)),U$56:$AI$176)} -> 0 | U21: =IFERROR(HYPERLINK(INDEX($D$55:$D$144,MATCH(Q21,$I$55:$I$144,0)),INDEX($C$55:$C$144,MATCH(Q21,$I$55:$I$144,0)) ), "" ) -> 40 - Redução de disperdicio bobina. | Z21: =Q21/$D$5 -> 0.024411162 | AA21: =Pareto!E85 -> 0.94431969 | AB21: {=IFERROR(INDEX($T$55:$T$144,MATCH(1,($AP$55:$AP$144=U21)*($S$55:$S$144="Previsto"), 0) ), "")} -> 0 | AC21: {=IFERROR( INDEX($T$55:$T$144,MATCH(1,($AP$55:$AP$144=U21)*($S$55:$S$144="Real"),0)),"")} -> 0 | AD21: =IF(OR(AB21="",AC21=""),"",IF(AC21=100%,"CONCLUÍDO",IF(AC21=0,IF(AB21=0,"PROJETO NÃO INICIADO","FALTA DE ACOMPANHAMENTO"),IF(AC21>AB21,"ADIANTADO",IF(AC21=AB21,"CONFORME PLANEJADO","ATRASO"))))) -> PROJETO NÃO INICIADO | AE21: 0
O22: 17 | P22: =_xlfn.XLOOKUP(U22,$C$55:$C$144,$A$55:$A$144) -> Kaizen - Custo Evitado | Q22: =IFERROR(LARGE($I$55:$I$144,O22)," ") -> 50000 | R22: =_xlfn.XLOOKUP(Q22,$I$55:$I$144,$N$55:$N$144) -> 0 | S22: =_xlfn.XLOOKUP(U22,$C$55:$C$176,$J$55:$J$176) -> 46264 | T22: {=SUMPRODUCT(($C$55:$C$175=U22)*(U$54:$AI$54<=TODAY())*(ISNUMBER(U$56:$AI$176)),U$56:$AI$176)} -> 0 | U22: =IFERROR(HYPERLINK(INDEX($D$55:$D$144,MATCH(Q22,$I$55:$I$144,0)),INDEX($C$55:$C$144,MATCH(Q22,$I$55:$I$144,0)) ), "" ) -> 34 - Iluminação em LED | Z22: =Q22/$D$5 -> 0.016494029 | AA22: =Pareto!E86 -> 0.95327617 | AB22: {=IFERROR(INDEX($T$55:$T$144,MATCH(1,($AP$55:$AP$144=U22)*($S$55:$S$144="Previsto"), 0) ), "")} | AC22: {=IFERROR( INDEX($T$55:$T$144,MATCH(1,($AP$55:$AP$144=U22)*($S$55:$S$144="Real"),0)),"")} | AD22: =IF(OR(AB22="",AC22=""),"",IF(AC22=100%,"CONCLUÍDO",IF(AC22=0,IF(AB22=0,"PROJETO NÃO INICIADO","FALTA DE ACOMPANHAMENTO"),IF(AC22>AB22,"ADIANTADO",IF(AC22=AB22,"CONFORME PLANEJADO","ATRASO"))))) | AE22: 0
O23: 18 | P23: =_xlfn.XLOOKUP(U23,$C$55:$C$144,$A$55:$A$144) -> BSW | Q23: =IFERROR(LARGE($I$55:$I$144,O23)," ") -> 47086 | R23: =_xlfn.XLOOKUP(Q23,$I$55:$I$144,$N$55:$N$144) -> 60984.11 | S23: =_xlfn.XLOOKUP(U23,$C$55:$C$176,$J$55:$J$176) -> 46235 | T23: {=SUMPRODUCT(($C$55:$C$175=U23)*(U$54:$AI$54<=TODAY())*(ISNUMBER(U$56:$AI$176)),U$56:$AI$176)} -> 0 | U23: =IFERROR(HYPERLINK(INDEX($D$55:$D$144,MATCH(Q23,$I$55:$I$144,0)),INDEX($C$55:$C$144,MATCH(Q23,$I$55:$I$144,0)) ), "" ) -> 25 - Redução de consumo de MTP China 2 porca (-10 mm) | Z23: =Q23/$D$5 -> 0.015532757 | AA23: =Pareto!E87 -> 0.96171067 | AB23: {=IFERROR(INDEX($T$55:$T$144,MATCH(1,($AP$55:$AP$144=U23)*($S$55:$S$144="Previsto"), 0) ), "")} | AC23: {=IFERROR( INDEX($T$55:$T$144,MATCH(1,($AP$55:$AP$144=U23)*($S$55:$S$144="Real"),0)),"")} | AD23: =IF(OR(AB23="",AC23=""),"",IF(AC23=100%,"CONCLUÍDO",IF(AC23=0,IF(AB23=0,"PROJETO NÃO INICIADO","FALTA DE ACOMPANHAMENTO"),IF(AC23>AB23,"ADIANTADO",IF(AC23=AB23,"CONFORME PLANEJADO","ATRASO"))))) | AE23: 0
O24: 19 | P24: =_xlfn.XLOOKUP(U24,$C$55:$C$144,$A$55:$A$144) -> Redução de custo | Q24: =IFERROR(LARGE($I$55:$I$144,O24)," ") -> 44856 | R24: =_xlfn.XLOOKUP(Q24,$I$55:$I$144,$N$55:$N$144) -> 62440 | S24: =_xlfn.XLOOKUP(U24,$C$55:$C$176,$J$55:$J$176) -> 46174 | T24: {=SUMPRODUCT(($C$55:$C$175=U24)*(U$54:$AI$54<=TODAY())*(ISNUMBER(U$56:$AI$176)),U$56:$AI$176)} -> 62700 | U24: =IFERROR(HYPERLINK(INDEX($D$55:$D$144,MATCH(Q24,$I$55:$I$144,0)),INDEX($C$55:$C$144,MATCH(Q24,$I$55:$I$144,0)) ), "" ) -> 38 - Venda de sucata | Z24: =Q24/$D$5 -> 0.014797123 | AA24: =Pareto!E88 -> 0.96974571 | AB24: {=IFERROR(INDEX($T$55:$T$144,MATCH(1,($AP$55:$AP$144=U24)*($S$55:$S$144="Previsto"), 0) ), "")} -> 0 | AC24: {=IFERROR( INDEX($T$55:$T$144,MATCH(1,($AP$55:$AP$144=U24)*($S$55:$S$144="Real"),0)),"")} -> 0 | AD24: =IF(OR(AB24="",AC24=""),"",IF(AC24=100%,"CONCLUÍDO",IF(AC24=0,IF(AB24=0,"PROJETO NÃO INICIADO","FALTA DE ACOMPANHAMENTO"),IF(AC24>AB24,"ADIANTADO",IF(AC24=AB24,"CONFORME PLANEJADO","ATRASO"))))) -> PROJETO NÃO INICIADO | AE24: 0
O25: 20 | P25: =_xlfn.XLOOKUP(U24,$C$55:$C$144,$A$55:$A$144) -> Redução de custo | Q25: =IFERROR(LARGE($I$55:$I$144,O25)," ") -> 40000.001 | R25: =_xlfn.XLOOKUP(Q25,$I$55:$I$144,$N$55:$N$144) -> 0 | S25: =_xlfn.XLOOKUP(U25,$C$55:$C$176,$J$55:$J$176) -> 46235 | T25: {=SUMPRODUCT(($C$55:$C$175=U25)*(U$54:$AI$54<=TODAY())*(ISNUMBER(U$56:$AI$176)),U$56:$AI$176)} -> 0 | U25: =IFERROR(HYPERLINK(INDEX($D$55:$D$144,MATCH(Q25,$I$55:$I$144,0)),INDEX($C$55:$C$144,MATCH(Q25,$I$55:$I$144,0)) ), "" ) -> 39 - Venda de sucata de cobre | Z25: =Q25/$D$5 -> 0.013195223 | AA25: =Pareto!E89 -> 0.9769109 | AB25: {=IFERROR(INDEX($T$55:$T$144,MATCH(1,($AP$55:$AP$144=U24)*($S$55:$S$144="Previsto"), 0) ), "")} -> 0 | AC25: {=IFERROR( INDEX($T$55:$T$144,MATCH(1,($AP$55:$AP$144=U24)*($S$55:$S$144="Real"),0)),"")} -> 0 | AD25: =IF(OR(AB25="",AC25=""),"",IF(AC25=100%,"CONCLUÍDO",IF(AC25=0,IF(AB25=0,"PROJETO NÃO INICIADO","FALTA DE ACOMPANHAMENTO"),IF(AC25>AB25,"ADIANTADO",IF(AC25=AB25,"CONFORME PLANEJADO","ATRASO"))))) -> PROJETO NÃO INICIADO
O26: Total | Q26: =SUM(Q6:Q25) -> 5453652 | R26: =SUM(R6:R25) -> 2872358
A27: 1. KPIs ESTRATÉGICOS
A28: CATEGORIA | B28: KPI | C28: UN | D28: Frequência | E28: TIPO | F28: BASELINE 2025 | G28: META 2026 | H28: Jan | I28: P. Ofensor1 | J28: Fev | K28: P. Ofensor2 | L28: Mar | M28: P. Ofensor3 | N28: Abr | O28: P. Ofensor4 | P28: Mai | Q28: P. Ofensor5 | R28: Jun | S28: P. Ofensor6 | T28: Jul | U28: P. Ofensor7 | V28: Ago | W28: P. Ofensor8 | X28: Set | Y28: P. Ofensor9 | Z28: Out | AA28: P. Ofensor10 | AB28: Nov | AC28: P. Ofensor11 | AD28: Dez | AE28: P. Ofensor12
A29: Financeiro | B29: Margem VA | C29: % | D29: Mensal | E29: Maior Melhor | F29: 0.366 | G29: 0.367 | H29: 0.372 | I29: Matéria Prima | J29: 0.327 | K29: Matéria Prima | L29: 0.358 | M29: Matéria Prima | N29: 0.38 | O29: Matéria Prima | P29: 0.411 | Q29: Matéria Prima | R29: 0.372 | S29: Matéria Prima | T29: 0.368 | Z29: =[14]Indicadores!$AS$11 | AB29: =[14]Indicadores!$AT$11 | AD29: =[14]Indicadores!$AU$139 -> 0
A30: Financeiro | B30: Custo de Scrap (Refugo) | C30: % | D30: Semanal | E30: Menor Melhor | F30: 0.0037 | G30: 0.002 | H30: 0.0028 | I30: Try Out | J30: 23595.82 | K30: Try Out | L30: 66468.61 | M30: Try Out | N30: 42764.61 | O30: Try Out | P30: 42189.13 | Q30: Try Out | R30: 41643.07 | S30: Try Out | T30: =[14]Indicadores!$AP$46 -> 0 | Z30: =[14]Indicadores!$AS$11 | AB30: =[14]Indicadores!$AT$11 | AD30: =[14]Indicadores!$AU$139 -> 0
A31: Operacional | B31: OEE | C31: % | D31: Semanal | E31: Maior Melhor | F31: 0.537 | G31: 75%% | H31: 0.418 | I31: Manutenção Mecanica | J31: 0.724 | K31: Manutenção Mecanica | L31: 0.541 | M31: Manutenção Mecanica | N31: 0.582 | O31: Manutenção Mecanica | P31: 0.631 | Q31: Manutenção Mecanica | R31: 0.6437 | S31: Manutenção Mecanica | T31: 0 | Z31: =[14]Indicadores!$AS$139 -> 0 | AB31: =[14]Indicadores!$AT$139 -> 0 | AD31: =[14]Indicadores!$AU$139 -> 0
A32: Operacional | B32: Eficiência de MO | C32: % | D32: Semanal | E32: Maior Melhor | F32: 0.7408 | G32: 0.77 | H32: 0.712 | I32: Turn Over | J32: 76.9 | K32: Turn Over | L32: 0.77 | M32: Turn Over | N32: 0.74 | O32: Turn Over | P32: 75,0%% | Q32: Turn Over | R32: 0.6437 | S32: Turn Over | T32: 0 | Z32: =[14]Indicadores!$AS$11 | AB32: =[14]Indicadores!$AT$11 | AD32: =[14]Indicadores!$AU$139 -> 0
A33: Operacional | B33: Performance | C33: % | D33: Semanal | E33: Maior Melhor | F33: 0.8807 | G33: 0.866 | H33: 0.8237 | I33: Turn Over | J33: 0.8477 | K33: Turn Over | L33: 0.8477 | M33: Turn Over | N33: 0.7533 | O33: Turn Over | P33: 0.8954 | Q33: Turn Over | R33: 0.83 | S33: Turn Over | T33: 0 | Z33: =[14]Indicadores!$AS$11 | AB33: =[14]Indicadores!$AT$11 | AD33: =[14]Indicadores!$AU$139 -> 0
A34: Operacional | B34: Qualidade | C34: % | D34: Semanal | E34: Maior Melhor | F34: NA | G34: NA | H34: NA | I34: NA | J34: NA | K34: NA | L34: NA | M34: NA | N34: NA | O34: NA | P34: NA | Q34: NA | R34: NA | S34: NA | T34: NA | Z34: =[14]Indicadores!$AS$11 | AB34: =[14]Indicadores!$AT$11 | AD34: =[14]Indicadores!$AU$139 -> 0
A35: Operacional | B35: Disponibilidade | C35: % | D35: Semanal | E35: Maior Melhor | F35: 0.6379 | G35: 86.6 | H35: 0.8319 | I35: Manutenção Mecanica | J35: 0.854 | K35: Manutenção Mecanica | L35: 0.8043 | M35: Manutenção Mecanica | N35: 0.7847 | O35: Manutenção Mecanica | P35: 0.7047 | Q35: Manutenção Mecanica | R35: 72\%% | S35: Manutenção Mecanica | T35: 0 | Z35: =[14]Indicadores!$AS$11 | AB35: =[14]Indicadores!$AT$11 | AD35: =[14]Indicadores!$AU$139 -> 0
A36: Operacional | B36: MTBF (Manutenção) | C36: h | D36: Semanal | E36: Maior Melhor | F36: 8.4993056 | G36: 8.3333333 | H36: 6.0243056 | I36: CSR54009 | J36: 6.3715278 | K36: NA | L36: 10.325694 | M36: NA | N36: 11.924306 | O36: NA | P36: 10.704167 | Q36: NA | R36: 12.788889 | S36: NA | T36: 10.458333 | Z36: =[14]Indicadores!$AS$11 | AB36: =[14]Indicadores!$AT$11 | AD36: =[14]Indicadores!$AU$139 -> 0
A37: Operacional | B37: MTTR (Manutenção) | C37: h | D37: Semanal | E37: Menor Melhor | F37: 0.020833333 | G37: 0.034722222 | H37: 0.020833333 | I37: NA | J37: 0.020138889 | K37: NA | L37: 0.017361111 | M37: NA | N37: 0.018055556 | O37: NA | P37: 0.022222222 | Q37: NA | R37: 0.024305556 | S37: NA | T37: 0.018055556 | Z37: =[14]Indicadores!$AS$11 | AB37: =[14]Indicadores!$AT$11 | AD37: =[14]Indicadores!$AU$139 -> 0
A38: Operacional | B38: Horas Extras | C38: Valor | D38: Semanal | E38: Menor Melhor | F38: 785490 | G38: 421705 | H38: 100336.44 | I38: Turn Over | J38: 32904 | K38: Turn Over | L38: 40106 | M38: Turn Over | N38: 83345.63 | O38: Turn Over | P38: 102906.25 | Q38: Turn Over | R38: R$ 84,356 | S38: Turn Over | Z38: =[14]Indicadores!$AS$11 | AB38: =[14]Indicadores!$AT$11 | AD38: =[14]Indicadores!$AU$139 -> 0
A39: Operacional | B39: Acuracidade Estoque | C39: Valor | D39: Semanal | E39: Menor Melhor | F39: 11267 | G39: -129647 | H39: 12008 | J39: 12431 | L39: 11056 | N39: 10502 | P39: 10724 | R39: 11351 | T39: 11700 | Z39: =[14]Indicadores!$AS$11 | AB39: =[14]Indicadores!$AT$11 | AD39: =[14]Indicadores!$AU$139 -> 0
A40: Qualidade | B40: PPM Interno | C40: ppm | D40: Semanal | E40: Menor Melhor | F40: 21979 | G40: 21000 | H40: 1837 | I40: Try Out | J40: 1926 | K40: Try Out | L40: 2902 | M40: Try Out | N40: 2870 | O40: Try Out | P40: 2522 | Q40: Try Out | R40: 1905 | S40: Try Out | T40: 0 | Z40: =[14]Indicadores!$AS$11 | AB40: =[14]Indicadores!$AT$11 | AD40: =[14]Indicadores!$AU$139 -> 0
A41: Qualidade | B41: PPM Externo | C41: ppm | D41: Semanal | E41: Menor Melhor | F41: 34297 | G41: 30000 | H41: 2474 | I41: NA | J41: 2249 | L41: 0 | N41: 0 | P41: 0 | R41: 2 | T41: 0 | Z41: =[14]Indicadores!$AS$11 | AB41: =[14]Indicadores!$AT$11 | AD41: =[14]Indicadores!$AU$139 -> 0
A42: Qualidade | B42: CONC | C42: % | D42: Mensal | E42: Menor Melhor | F42: 0.0087 | G42: 0.80% | H42: 0.0111 | I42: Hora Extra | J42: 0.0085 | K42: Hora Extra | L42: 0.0107 | M42: Hora Extra | N42: 0.0144 | O42: Hora Extra | P42: 1,44%% | Q42: Hora Extra | R42: 0.0107 | S42: Hora Extra | T42: 0 | Z42: =[14]Indicadores!$AS$11 | AB42: =[14]Indicadores!$AT$11 | AD42: =[14]Indicadores!$AU$139 -> 0
A43: Qualidade | B43: Reclamações de Clientes | C43: qtd | D43: Diário | E43: Menor Melhor | F43: 19 | G43: 14 | H43: 3 | I43: Falha na porca da ciser | J43: 0 | K43: NA | L43: 1 | M43: NA | N43: 2 | P43: 4 | Q43: NA | R43: 1 | T43: 2 | AD43: =[14]Indicadores!$AU$139 -> 0
A44: Segurança | B44: Taxa de Frequência de Acidente | C44: taxa | D44: 24 | E44: Menor Melhor | F44: 10 | G44: 20 | H44: 24 | I44: Corte na mão | J44: 26 | K44: NA | L44: 0 | M44: NA | N44: 0 | O44: NA | P44: 13 | Q44: NA | R44: 0 | S44: NA | T44: =[14]Indicadores!$AP$11 -> 0 | Z44: =[14]Indicadores!$AS$11 | AB44: =[14]Indicadores!$AT$11 | AD44: =[14]Indicadores!$AU$139 -> 0
A45: Validação Processo | B45: % Conformidade vs POC | C45: % | D45: P/ Prioridade | E45: Maior Melhor | F45: 0.5 | H45: 1 | J45: 1 | L45: 1 | N45: 1 | P45: 1 | R45: 1 | T45: 100 | Z45: =[14]Indicadores!$AS$11 | AB45: =[14]Indicadores!$AT$11 | AD45: =[14]Indicadores!$AU$139 -> 0 | AJ45: Departamento Suporte
A46: Sistema de Produção Delga (SPD) | B46: % Aderência às Ferramentas SPD | C46: % | D46: Semanal | E46: Maior Melhor | F46: 0.53 | G46: 1 | H46: 0.72 | I46: Utilização de form irregular | J46: 0.87 | K46: Utilização de form irregular | L46: 55.3% | M46: Utilização de form irregular | N46: 0.61 | O46: Utilização de form irregular | P46: 1 | Q46: Utilização de form irregular | R46: 0.92 | S46: Utilização de form irregular | T46: 95 | Z46: =[14]Indicadores!$AS$11 | AB46: =[14]Indicadores!$AT$11 | AD46: =[14]Indicadores!$AU$139 -> 0 | AJ46: Departamentos | AK46: Valor de Impacto
A47: Operacional | B47: MTBF (Ferramentaria) | C47: h | D47: Semanal | E47: Maior Melhor | F47: 18.708333 | G47: 14.583333 | H47: 0.36893519 | J47: 19.333333 | L47: 9.09697 | N47: 19.458333 | P47: 18.583333 | R47: 0.024305556 | T47: 20 | Z47: =[14]Indicadores!$AS$11 | AB47: =[14]Indicadores!$AT$11 | AD47: =[14]Indicadores!$AU$139 -> 0 | AJ47: Compras | AK47: =SUMIF($AM$55:$AM$144,AJ47,$AO$55:$AO$144) -> 0
A48: Operacional | B48: MTTR (Ferramentaria) | C48: h | D48: Semanal | E48: Menor Melhor | F48: 0.022916667 | G48: 0.020833333 | H48: 0.024814815 | J48: 0.027083333 | L48: 0.010416667 | N48: 0.0090277778 | P48: 0.00625 | R48: 12.789502 | T48: 0.011111111 | Z48: =[14]Indicadores!$AS$11 | AB48: =[14]Indicadores!$AT$11 | AD48: =[14]Indicadores!$AU$139 -> 0 | AJ48: Vendas | AK48: =SUMIF($AM$55:$AM$144,AJ48,$AO$55:$AO$144) -> 0
A49: Gerente de Planta | B49: Performance de GESTÂO | C49: R$ | D49: Mensal | E49: Maior Melhor ↑ | F49: ?? | G49: ?? | H49: ?? | I49: ?? | J49: ?? | K49: ?? | L49: ?? | M49: ?? | N49: ?? | O49: ?? | P49: ?? | Q49: ?? | R49: ?? | S49: ?? | Z49: =[14]Indicadores!$AS$11 | AB49: =[14]Indicadores!$AT$11 | AD49: =[14]Indicadores!$AU$139 -> 0 | AJ49: Orçamento | AK49: =SUMIF($AM$55:$AM$144,AJ49,$AO$55:$AO$144) -> 0
Z50: =[14]Indicadores!$AS$11 | AB50: =[14]Indicadores!$AT$11 | AD50: =[14]Indicadores!$AU$139 -> 0 | AJ50: Simulação | AK50: =SUMIF($AM$55:$AM$144,AJ50,$AO$55:$AO$144) -> 0
V51: =[14]Indicadores!$AQ$46 -> 0 | Z51: =[14]Indicadores!$AS$11 | AB51: =[14]Indicadores!$AT$11 | AD51: =[14]Indicadores!$AU$139 -> 0 | AJ51: Eng. Corporativa | AK51: =SUMIF($AM$55:$AM$144,AJ51,$AO$55:$AO$144) -> 0
A53: 2. IDEIAS DE KAIZENS E PROJETOS DE REDUÇÃO DE CUSTOS | U53: 1° Tri | Y53: 2° Tri | AC53: 3° Tri | AG53: 4° Tri | AT53: =SUM(AT55:AT176) -> 3031400.1 | AU53: =SUM(AU55:AU176) -> 7824805.1
A54: TIPO Redução de custos / Kaizen / Você resolve | B54: VA / GGF / Material Auxiliar | C54: Nome do Projeto | D54: Caminho da Evidência | E54: DESCRIÇÃO | F54: RESPONSÁVEL | G54: Inicio Mês/Ano | H54: Termino Mês/Ano | I54: PREVISTO (R$) | J54: Mês do 1º RETORNO | K54: Quantidade de meses com retorno | L54: Processo de entrega do projeto a custos | M54: VALIDADOR OK / NOK | N54: SAVING VALIDADO (R$ Valor) | O54: Status | P54: Onde esta parado | Q54: Data de liberação. | R54: % Responsabilidade Delga | T54: Avanço | U54: 46023 | V54: 46054 | W54: 46082 | X54: Total 1° Tri | Y54: 46113 | Z54: 46143 | AA54: 46174 | AB54: Total 2° Tri | AC54: 46204 | AD54: 46235 | AE54: 46266 | AF54: Total 3° Tri | AG54: 46296 | AH54: 46327 | AI54: 46357 | AJ54: Total 4° Tri | AK54: Total Ano | AL54: OBS | AM54: Departamento Suporte | AN54: % de Impacto | AO54: Impacto Financeiro | AP54: proj ref. | AR54: Retorno até hoje | AT54: Unidade até Dezembro | AU54: Custos (12M)
A55: Redução de custo | B55: GGF | C55: 01 - Desenvolver célula de solda para soldar porcas | D55: \\192.168.5.20\Departamentos\TI\Projetos\Master 2026\01 - Desenvolver célula de solda para soldar porcas\01 - Desenvolver célula de solda para soldar porcas.xlsx | E55: Confeccionar uma célula de solda para manufaturar conjuntos e sub conjuntos de elementos roscados substituindo as estacionarias | F55: Jonathan | G55: 46023 | H55: 46388 | I55: 560000 | J55: 46388 | K55: =IF(J55="", "", 12 - MONTH(J55) + 1) -> 12 | O55: ⏳ Em Execução | P55: Orçamentos | Q55: 46264 | R55: 0.8 | S55: Previsto | T55: =AVERAGE([15]Estrutura!$I$5:$I$9) -> 0.79032258 | U55: =IFERROR(IF(AND(U$54>=EOMONTH($J55,-1)+1,U$54<=EOMONTH(EOMONTH($J55,-1)+1,$K55-1)),IF(NOT(ISBLANK($N55)),$N55/$K55,$I55/$K55),0),0) -> 0 | V55: =IFERROR(IF(AND(V$54>=EOMONTH($J55,-1)+1,V$54<=EOMONTH(EOMONTH($J55,-1)+1,$K55-1)),IF(NOT(ISBLANK($N55)),$N55/$K55,$I55/$K55),0),0) -> 0 | W55: =IFERROR(IF(AND(W$54>=EOMONTH($J55,-1)+1,W$54<=EOMONTH(EOMONTH($J55,-1)+1,$K55-1)),IF(NOT(ISBLANK($N55)),$N55/$K55,$I55/$K55),0),0) -> 0 | X55: =SUM(U55:W55) -> 0 | Y55: =IFERROR(IF(AND(Y$54>=EOMONTH($J55,-1)+1,Y$54<=EOMONTH(EOMONTH($J55,-1)+1,$K55-1)),IF(NOT(ISBLANK($N55)),$N55/$K55,$I55/$K55),0),0) -> 0 | Z55: =IFERROR(IF(AND(Z$54>=EOMONTH($J55,-1)+1,Z$54<=EOMONTH(EOMONTH($J55,-1)+1,$K55-1)),IF(NOT(ISBLANK($N55)),$N55/$K55,$I55/$K55),0),0) -> 0 | AA55: =IFERROR(IF(AND(AA$54>=EOMONTH($J55,-1)+1,AA$54<=EOMONTH(EOMONTH($J55,-1)+1,$K55-1)),IF(NOT(ISBLANK($N55)),$N55/$K55,$I55/$K55),0),0) -> 0 | AB55: =SUM(Y55:AA55) -> 0 | AC55: =IFERROR(IF(AND(AC$54>=EOMONTH($J55,-1)+1,AC$54<=EOMONTH(EOMONTH($J55,-1)+1,$K55-1)),IF(NOT(ISBLANK($N55)),$N55/$K55,$I55/$K55),0),0) -> 0 | AD55: =IFERROR(IF(AND(AD$54>=EOMONTH($J55,-1)+1,AD$54<=EOMONTH(EOMONTH($J55,-1)+1,$K55-1)),IF(NOT(ISBLANK($N55)),$N55/$K55,$I55/$K55),0),0) -> 0 | AE55: =IFERROR(IF(AND(AE$54>=EOMONTH($J55,-1)+1,AE$54<=EOMONTH(EOMONTH($J55,-1)+1,$K55-1)),IF(NOT(ISBLANK($N55)),$N55/$K55,$I55/$K55),0),0) -> 0 | AF55: =SUM(AC55:AE55) -> 0 | AG55: =IFERROR(IF(AND(AG$54>=EOMONTH($J55,-1)+1,AG$54<=EOMONTH(EOMONTH($J55,-1)+1,$K55-1)),IF(NOT(ISBLANK($N55)),$N55/$K55,$I55/$K55),0),0) -> 0 | AH55: =IFERROR(IF(AND(AH$54>=EOMONTH($J55,-1)+1,AH$54<=EOMONTH(EOMONTH($J55,-1)+1,$K55-1)),IF(NOT(ISBLANK($N55)),$N55/$K55,$I55/$K55),0),0) -> 0 | AI55: =IFERROR(IF(AND(AI$54>=EOMONTH($J55,-1)+1,AI$54<=EOMONTH(EOMONTH($J55,-1)+1,$K55-1)),IF(NOT(ISBLANK($N55)),$N55/$K55,$I55/$K55),0),0) -> 0 | AJ55: =SUM(AG55:AI55) -> 0 | AK55: =SUM(X55,AB55,AF55,AJ55) -> 0 | AO55: =N55*AN55 -> 0 | AP55: =C55 -> 01 - Desenvolver célula de solda para soldar porcas | AQ55: P | AR55: {=IF(OR(AP55="",AP55=0),"",IF(SUMPRODUCT(($C$55:$C$144=AP55)*(U$54:$AI$54<EOMONTH(TODAY(),-1)+1)*(ISNUMBER(U$55:$AI$144)),U$55:$AI$144)=0,"",SUMPRODUCT(($C$55:$C$144=AP55)*(U$54:$AI$54<EOMONTH(TODAY(),-1)+1)*(ISNUMBER(U$55:$AI$144)),U$55:$AI$144)))} | AS55: =A55 -> Redução de custo | AT55: 0 | AU55: 0
S56: Real | T56: =AVERAGE([15]Estrutura!$J$5:$J$9) -> 0.79 | X56: =SUM(U56:W56) -> 0 | AB56: =SUM(Y56:AA56) -> 0 | AF56: =SUM(AC56:AE56) -> 0 | AJ56: =SUM(AG56:AI56) -> 0 | AK56: =SUM(X56,AB56,AF56,AJ56) -> 0 | AP56: =C55 -> 01 - Desenvolver célula de solda para soldar porcas | AQ56: R | AR56: {=IF(OR(AP56="",AP56=0),"",IF(SUMPRODUCT(($C$55:$C$159=AP56)*($U$54:AI$54<=TODAY())*(ISNUMBER($U$56:AI$160)),$U$56:AI$160)=0,"",SUMPRODUCT(($C$55:$C$159=AP56)*($U$54:AI$54<=TODAY())*(ISNUMBER($U$56:AI$160)),$U$56:AI$160)))} | AS56: =A55 -> Redução de custo
